Workbook

Sheet Instructions
A1: Personal Finance Analysis Template: Minimal Input + Canadian Sales Tax Estimator
A2: Fill only Expense_Input, Income_Input, Input_Settings, and Sales_Tax_Settings. Other sheets calculate automatically.
A3: Item | B3: Description
A4: Purpose | B4: Track personal income/expenses and automatically generate monthly cash flow, category mix, annual spending projection, emergency fund, investable cash, and sales tax estimates.
A5: Monthly Maintenance | B5: Append new rows and update current cash or tax assumptions only when they change.
A6: Amount Rule | B6: Enter expense and income amounts as positive numbers.
A7: Tax Rule | B7: Tax Type can be Auto, Zero-rated, Taxable, Exempt, Tax Unknown, or Not Applicable.
A8: Sample Data | B8: January and February 2026 sample data are included.
A10: Workflow
A11: 1. Add expense rows in Expense_Input.
A12: 2. Add income rows in Income_Input.
A13: 3. Update Input_Settings and Sales_Tax_Settings when assumptions change.
A14: 4. Review Dashboard first.
A15: 5. Sales tax estimates are approximate and are not refund, credit, or deductible amounts.

Sheet Dashboard
A1: Personal Finance Dashboard
A2: Main review page; all figures reference Formula_Hub.
A3: Average Monthly Expense | D3: Essential Monthly Expense | G3: Discretionary Monthly Expense | J3: Normal One-Year Reserve
A4: =Formula_Hub!$B$7 -> 5150 | D4: =Formula_Hub!$B$8 -> 4000 | G4: =Formula_Hub!$B$9 -> 1150 | J4: =Formula_Hub!$B$17 -> 61800
A7: Cash Coverage Months | D7: Suggested Investable Cash | G7: Estimated Annual Sales Tax | J7: Sales Tax Estimate Status
A8: =Formula_Hub!$B$16 -> 5.8252427 | D8: =Formula_Hub!$B$21 -> 0 | G8: =Formula_Hub!$B$24 -> 318.45075 | J8: =Formula_Hub!$B$25 -> Enabled
A12: Decision Summary
A13: Cash Safety Level | B13: =Formula_Hub!$B$23 -> Tight
A14: Cash Allocation Note | B14: =IF(Formula_Hub!$B$22>0,"Current cash reserve has a shortfall; prioritize rebuilding the reserve",IF(Formula_Hub!$B$21>0,"There is a potential amount to invest gradually","Enter current cash in Input_Settings first")) -> Current cash reserve has a shortfall; prioritize rebuilding the reserve
A15: Sales Tax Note | B15: =IF(Sales_Tax_Settings!$B$5="Yes","Sales tax estimate is enabled; this is not a refund, credit, or deductible amount","Sales tax estimate is disabled") -> Sales tax estimate is enabled; this is not a refund, credit, or deductible amount
A19: Chart Data: Monthly Cash Flow and Sales Tax | G19: Chart Data: Category Monthly Avg and Share
A20: Month | B20: Income | C20: Personal Expense | D20: Estimated Sales Tax | E20: Net Cash Flow | G20: Category | H20: Monthly Avg | I20: Share
A21: =Monthly_Summary!A4 -> 2026-01 | B21: =Monthly_Summary!B4 -> 6000 | C21: =Monthly_Summary!C4 -> 5000 | D21: =Formula_Hub!O28 -> 148.4801 | E21: =Formula_Hub!J28 -> 1000 | G21: =Category_Summary!A4 -> Housing | H21: =Category_Summary!N4 -> 3000 | I21: =Category_Summary!P4 -> 0.58252427
A22: =Monthly_Summary!A5 -> 2026-02 | B22: =Monthly_Summary!B5 -> 6900 | C22: =Monthly_Summary!C5 -> 5300 | D22: =Formula_Hub!O29 -> 169.97065 | E22: =Formula_Hub!J29 -> 1600 | G22: =Category_Summary!A5 -> Food & Dining | H22: =Category_Summary!N5 -> 820 | I22: =Category_Summary!P5 -> 0.1592233
A23: =Monthly_Summary!A6 -> 2026-03 | B23: =Monthly_Summary!B6 -> 0 | C23: =Monthly_Summary!C6 -> 0 | D23: =Formula_Hub!O30 -> 0 | E23: =Formula_Hub!J30 -> 0 | G23: =Category_Summary!A6 -> Transportation | H23: =Category_Summary!N6 -> 240 | I23: =Category_Summary!P6 -> 0.046601942
A24: =Monthly_Summary!A7 -> 2026-04 | B24: =Monthly_Summary!B7 -> 0 | C24: =Monthly_Summary!C7 -> 0 | D24: =Formula_Hub!O31 -> 0 | E24: =Formula_Hub!J31 -> 0 | G24: =Category_Summary!A7 -> Telecom | H24: =Category_Summary!N7 -> 60 | I24: =Category_Summary!P7 -> 0.011650485
A25: =Monthly_Summary!A8 -> 2026-05 | B25: =Monthly_Summary!B8 -> 0 | C25: =Monthly_Summary!C8 -> 0 | D25: =Formula_Hub!O32 -> 0 | E25: =Formula_Hub!J32 -> 0 | G25: =Category_Summary!A8 -> Subscriptions | H25: =Category_Summary!N8 -> 37.5 | I25: =Category_Summary!P8 -> 0.0072815534
A26: =Monthly_Summary!A9 -> 2026-06 | B26: =Monthly_Summary!B9 -> 0 | C26: =Monthly_Summary!C9 -> 0 | D26: =Formula_Hub!O33 -> 0 | E26: =Formula_Hub!J33 -> 0 | G26: =Category_Summary!A9 -> Shopping | H26: =Category_Summary!N9 -> 275 | I26: =Category_Summary!P9 -> 0.053398058
A27: =Monthly_Summary!A10 -> 2026-07 | B27: =Monthly_Summary!B10 -> 0 | C27: =Monthly_Summary!C10 -> 0 | D27: =Formula_Hub!O34 -> 0 | E27: =Formula_Hub!J34 -> 0 | G27: =Category_Summary!A10 -> Medical | H27: =Category_Summary!N10 -> 90 | I27: =Category_Summary!P10 -> 0.017475728
A28: =Monthly_Summary!A11 -> 2026-08 | B28: =Monthly_Summary!B11 -> 0 | C28: =Monthly_Summary!C11 -> 0 | D28: =Formula_Hub!O35 -> 0 | E28: =Formula_Hub!J35 -> 0 | G28: =Category_Summary!A11 -> Fitness | H28: =Category_Summary!N11 -> 70 | I28: =Category_Summary!P11 -> 0.013592233
A29: =Monthly_Summary!A12 -> 2026-09 | B29: =Monthly_Summary!B12 -> 0 | C29: =Monthly_Summary!C12 -> 0 | D29: =Formula_Hub!O36 -> 0 | E29: =Formula_Hub!J36 -> 0 | G29: =Category_Summary!A12 -> Education | H29: =Category_Summary!N12 -> 130 | I29: =Category_Summary!P12 -> 0.025242718
A30: =Monthly_Summary!A13 -> 2026-10 | B30: =Monthly_Summary!B13 -> 0 | C30: =Monthly_Summary!C13 -> 0 | D30: =Formula_Hub!O37 -> 0 | E30: =Formula_Hub!J37 -> 0 | G30: =Category_Summary!A13 -> Pet | H30: =Category_Summary!N13 -> 95 | I30: =Category_Summary!P13 -> 0.018446602
A31: =Monthly_Summary!A14 -> 2026-11 | B31: =Monthly_Summary!B14 -> 0 | C31: =Monthly_Summary!C14 -> 0 | D31: =Formula_Hub!O38 -> 0 | E31: =Formula_Hub!J38 -> 0 | G31: =Category_Summary!A14 -> Entertainment | H31: =Category_Summary!N14 -> 110 | I31: =Category_Summary!P14 -> 0.021359223
A32: =Monthly_Summary!A15 -> 2026-12 | B32: =Monthly_Summary!B15 -> 0 | C32: =Monthly_Summary!C15 -> 0 | D32: =Formula_Hub!O39 -> 0 | E32: =Formula_Hub!J39 -> 0 | G32: =Category_Summary!A15 -> Taxes & Gov Fees | H32: =Category_Summary!N15 -> 125 | I32: =Category_Summary!P15 -> 0.024271845
G33: =Category_Summary!A16 -> Other | H33: =Category_Summary!N16 -> 97.5 | I33: =Category_Summary!P16 -> 0.018932039

Sheet Expense_Input
A1: Total Expenses
A2: Formula ranges cover rows 4:500. Enter expense amounts as positive numbers.
A3: Record ID | B3: Date | C3: Expense Description | D3: Expense Amount | E3: Main Category | F3: Expense Nature | G3: Necessity | H3: Analysis Scope | I3: Tax Type | J3: Notes
A4: EXP-0001 | B4: 46023 | C4: Rent | D4: 3000 | E4: Housing | F4: Fixed | G4: Essential | H4: Personal Expense | I4: Exempt | J4: Sample rent
A5: EXP-0002 | B5: 46025 | C5: Basic groceries | D5: 450 | E5: Food & Dining | F5: Variable | G5: Essential | H5: Personal Expense | I5: Zero-rated | J5: Basic groceries
A6: EXP-0003 | B6: 46027 | C6: Restaurant dining | D6: 320 | E6: Food & Dining | F6: Variable | G6: Discretionary | H6: Personal Expense | I6: Taxable
A7: EXP-0004 | B7: 46029 | C7: Gas | D7: 220 | E7: Transportation | F7: Variable | G7: Essential | H7: Personal Expense | I7: Taxable
A8: EXP-0005 | B8: 46030 | C8: Mobile phone plan | D8: 60 | E8: Telecom | F8: Fixed | G8: Essential | H8: Personal Expense | I8: Taxable
A9: EXP-0006 | B9: 46031 | C9: Cloud subscription | D9: 30 | E9: Subscriptions | F9: Fixed | G9: Discretionary | H9: Personal Expense | I9: Taxable
A10: EXP-0007 | B10: 46032 | C10: Shopping | D10: 250 | E10: Shopping | F10: Variable | G10: Discretionary | H10: Personal Expense | I10: Taxable
A11: EXP-0008 | B11: 46034 | C11: Medical supplies | D11: 80 | E11: Medical | F11: Variable | G11: Essential | H11: Personal Expense | I11: Exempt
A12: EXP-0009 | B12: 46037 | C12: Gym membership | D12: 70 | E12: Fitness | F12: Fixed | G12: Discretionary | H12: Personal Expense | I12: Taxable
A13: EXP-0010 | B13: 46038 | C13: Courses and books | D13: 120 | E13: Education | F13: One-time | G13: Discretionary | H13: Personal Expense | I13: Tax Unknown
A14: EXP-0011 | B14: 46040 | C14: Pet supplies | D14: 90 | E14: Pet | F14: Variable | G14: Discretionary | H14: Personal Expense | I14: Taxable
A15: EXP-0012 | B15: 46042 | C15: Entertainment | D15: 100 | E15: Entertainment | F15: Variable | G15: Discretionary | H15: Personal Expense | I15: Taxable
A16: EXP-0013 | B16: 46047 | C16: Government fee | D16: 100 | E16: Taxes & Gov Fees | F16: One-time | G16: Essential | H16: Personal Expense | I16: Not Applicable
A17: EXP-0014 | B17: 46050 | C17: Miscellaneous | D17: 110 | E17: Other | F17: Variable | G17: Discretionary | H17: Personal Expense | I17: Tax Unknown
... A31: EXP-0028 | B31: 46079 | C31: Miscellaneous | D31: 85 | E31: Other | F31: Variable | G31: Discretionary | H31: Personal Expense | I31: Tax Unknown

Sheet Income_Input
A1: Total Income
A2: Formula ranges cover rows 4:500. Enter income amounts as positive numbers.
A3: Record ID | B3: Date | C3: Income Source | D3: Income Amount | E3: Income Type | F3: Notes
A4: INC-0001 | B4: 46030 | C4: Salary | D4: 6000 | E4: Salary | F4: Sample income
A5: INC-0002 | B5: 46061 | C5: Salary | D5: 6700 | E5: Salary | F5: Sample income
A6: INC-0003 | B6: 46073 | C6: Refund | D6: 200 | E6: Refund | F6: Example refund

Sheet Input_Settings
A1: Input Settings
A2: Manual variable area.
A4: Setting | B4: Current Value | C4: Description
A5: Current Available Cash | B5: 30000 | C5: Used to calculate cash coverage months and investable cash
A6: Extra Safety Buffer | B6: 1000 | C6: Additional cash held above recommended reserve
A7: Risk Preference | B7: Balanced | C7: Conservative, Balanced, or Growth
A8: Emergency Fund Months | B8: 12 | C8: Recommended reserve = average monthly expense × months
A9: Minimum Cash Reserve Floor | B9: 15000 | C9: Minimum cash reserve floor
A12: Optional: Monthly Housing Baseline
B13: 2026-01 | C13: 2026-02 | D13: 2026-03 | E13: 2026-04 | F13: 2026-05 | G13: 2026-06 | H13: 2026-07 | I13: 2026-08 | J13: 2026-09 | K13: 2026-10 | L13: 2026-11 | M13: 2026-12
A14: Housing Baseline | B14: 3000 | C14: 3000 | D14: 3000 | E14: 3000 | F14: 3000 | G14: 3000 | H14: 3000 | I14: 3000 | J14: 3000 | K14: 3000 | L14: 3000 | M14: 3000

Sheet Sales_Tax_Settings
A1: Sales Tax Settings
A2: Sales tax estimates are approximate and editable.
A4: Setting | B4: Current Value | C4: Description
A5: Enable Sales Tax Estimate | B5: Yes | C5: If No, estimated tax is 0
A6: Expense Amounts Include Tax | B6: Yes | C6: Most personal records are tax-included cash outflows
A7: Region | B7: Quebec | C7: Default GST/QST example
A8: Federal Sales Tax Rate | B8: 0.05 | C8: GST
A9: Provincial Sales Tax Rate | B9: 0.09975 | C9: QST
A10: Combined Sales Tax Rate | B10: =B8+B9 -> 0.14975 | C10: Used to back out included tax
A13: Default Tax Type by Main Category
A14: Main Category | B14: Default Tax Type | C14: Notes
A15: Housing | B15: Exempt | C15: Residential rent is usually outside sales tax estimate
A16: Food & Dining | B16: Taxable | C16: Restaurants/takeout taxable; basic groceries zero-rated
A17: Transportation | B17: Taxable | C17: Gas, parking, repair usually taxable
A18: Telecom | B18: Taxable | C18: Mobile/internet usually taxable
A19: Subscriptions | B19: Taxable | C19: Software/streaming usually taxable
A20: Shopping | B20: Taxable | C20: Goods usually taxable
A21: Medical | B21: Exempt | C21: Medical varies
A22: Fitness | B22: Taxable | C22: Gym usually taxable
A23: Education | B23: Tax Unknown | C23: Books/courses vary
A24: Pet | B24: Taxable | C24: Pet items usually taxable
A25: Entertainment | B25: Taxable | C25: Games/events usually taxable
... A27: Other | B27: Tax Unknown | C27: Use receipt
A30: Sources
A31: Topic | B31: Link
A32: Quebec sales tax calculation rules | B32: https://www.revenuquebec.ca/en/businesses/consumption-taxes/gsthst-and-qst/collecting-gst-and-qst/calculating-the-taxes/
A33: Quebec GST/QST rate tables | B33: https://www.revenuquebec.ca/en/businesses/consumption-taxes/gsthst-and-qst/basic-rules-for-applying-the-gsthst-and-qst/tables-of-gst-and-qst-rates/
A34: Examples of taxable supplies | B34: https://www.revenuquebec.ca/en/businesses/consumption-taxes/gsthst-and-qst/basic-rules-for-applying-the-gsthst-and-qst/types-of-supplies/taxable-supplies/
A35: Federal GST/HST credit overview | B35: https://www.canada.ca/en/revenue-agency/services/child-family-benefits/gst-hst-credit.html

Sheet Monthly_Summary
A1: Monthly Summary
A2: Display sheet: references Formula_Hub.
A3: Month | B3: Total Income | C3: Personal Expense | D3: Essential Expense | E3: Discretionary Expense | F3: Fixed Expense | G3: Variable Expense | H3: One-time Expense | I3: Housing Expense | J3: Net Cash Flow | K3: Included in Average | L3: Property Expense | M3: Investment Transfer | N3: Internal Transfer | O3: Estimated Sales Tax
A4: =Formula_Hub!A28 -> 2026-01 | B4: =Formula_Hub!B28 -> 6000 | C4: =Formula_Hub!C28 -> 5000 | D4: =Formula_Hub!D28 -> 3910 | E4: =Formula_Hub!E28 -> 1090 | F4: =Formula_Hub!F28 -> 3160 | G4: =Formula_Hub!G28 -> 1620 | H4: =Formula_Hub!H28 -> 220 | ... O4: =Formula_Hub!O28 -> 148.4801
A5: =Formula_Hub!A29 -> 2026-02 | B5: =Formula_Hub!B29 -> 6900 | C5: =Formula_Hub!C29 -> 5300 | D5: =Formula_Hub!D29 -> 4090 | E5: =Formula_Hub!E29 -> 1210 | F5: =Formula_Hub!F29 -> 3175 | G5: =Formula_Hub!G29 -> 1835 | H5: =Formula_Hub!H29 -> 290 | ... O5: =Formula_Hub!O29 -> 169.97065
A6: =Formula_Hub!A30 -> 2026-03 | B6: =Formula_Hub!B30 -> 0 | C6: =Formula_Hub!C30 -> 0 | D6: =Formula_Hub!D30 -> 0 | E6: =Formula_Hub!E30 -> 0 | F6: =Formula_Hub!F30 -> 0 | G6: =Formula_Hub!G30 -> 0 | H6: =Formula_Hub!H30 -> 0 | ... O6: =Formula_Hub!O30 -> 0
A7: =Formula_Hub!A31 -> 2026-04 | B7: =Formula_Hub!B31 -> 0 | C7: =Formula_Hub!C31 -> 0 | D7: =Formula_Hub!D31 -> 0 | E7: =Formula_Hub!E31 -> 0 | F7: =Formula_Hub!F31 -> 0 | G7: =Formula_Hub!G31 -> 0 | H7: =Formula_Hub!H31 -> 0 | ... O7: =Formula_Hub!O31 -> 0
A8: =Formula_Hub!A32 -> 2026-05 | B8: =Formula_Hub!B32 -> 0 | C8: =Formula_Hub!C32 -> 0 | D8: =Formula_Hub!D32 -> 0 | E8: =Formula_Hub!E32 -> 0 | F8: =Formula_Hub!F32 -> 0 | G8: =Formula_Hub!G32 -> 0 | H8: =Formula_Hub!H32 -> 0 | ... O8: =Formula_Hub!O32 -> 0
A9: =Formula_Hub!A33 -> 2026-06 | B9: =Formula_Hub!B33 -> 0 | C9: =Formula_Hub!C33 -> 0 | D9: =Formula_Hub!D33 -> 0 | E9: =Formula_Hub!E33 -> 0 | F9: =Formula_Hub!F33 -> 0 | G9: =Formula_Hub!G33 -> 0 | H9: =Formula_Hub!H33 -> 0 | ... O9: =Formula_Hub!O33 -> 0
A10: =Formula_Hub!A34 -> 2026-07 | B10: =Formula_Hub!B34 -> 0 | C10: =Formula_Hub!C34 -> 0 | D10: =Formula_Hub!D34 -> 0 | E10: =Formula_Hub!E34 -> 0 | F10: =Formula_Hub!F34 -> 0 | G10: =Formula_Hub!G34 -> 0 | H10: =Formula_Hub!H34 -> 0 | ... O10: =Formula_Hub!O34 -> 0
A11: =Formula_Hub!A35 -> 2026-08 | B11: =Formula_Hub!B35 -> 0 | C11: =Formula_Hub!C35 -> 0 | D11: =Formula_Hub!D35 -> 0 | E11: =Formula_Hub!E35 -> 0 | F11: =Formula_Hub!F35 -> 0 | G11: =Formula_Hub!G35 -> 0 | H11: =Formula_Hub!H35 -> 0 | ... O11: =Formula_Hub!O35 -> 0
A12: =Formula_Hub!A36 -> 2026-09 | B12: =Formula_Hub!B36 -> 0 | C12: =Formula_Hub!C36 -> 0 | D12: =Formula_Hub!D36 -> 0 | E12: =Formula_Hub!E36 -> 0 | F12: =Formula_Hub!F36 -> 0 | G12: =Formula_Hub!G36 -> 0 | H12: =Formula_Hub!H36 -> 0 | ... O12: =Formula_Hub!O36 -> 0
A13: =Formula_Hub!A37 -> 2026-10 | B13: =Formula_Hub!B37 -> 0 | C13: =Formula_Hub!C37 -> 0 | D13: =Formula_Hub!D37 -> 0 | E13: =Formula_Hub!E37 -> 0 | F13: =Formula_Hub!F37 -> 0 | G13: =Formula_Hub!G37 -> 0 | H13: =Formula_Hub!H37 -> 0 | ... O13: =Formula_Hub!O37 -> 0
A14: =Formula_Hub!A38 -> 2026-11 | B14: =Formula_Hub!B38 -> 0 | C14: =Formula_Hub!C38 -> 0 | D14: =Formula_Hub!D38 -> 0 | E14: =Formula_Hub!E38 -> 0 | F14: =Formula_Hub!F38 -> 0 | G14: =Formula_Hub!G38 -> 0 | H14: =Formula_Hub!H38 -> 0 | ... O14: =Formula_Hub!O38 -> 0
A15: =Formula_Hub!A39 -> 2026-12 | B15: =Formula_Hub!B39 -> 0 | C15: =Formula_Hub!C39 -> 0 | D15: =Formula_Hub!D39 -> 0 | E15: =Formula_Hub!E39 -> 0 | F15: =Formula_Hub!F39 -> 0 | G15: =Formula_Hub!G39 -> 0 | H15: =Formula_Hub!H39 -> 0 | ... O15: =Formula_Hub!O39 -> 0

Sheet Category_Summary
A1: Category Summary
A2: Display sheet: references Formula_Hub.
A3: Main Category | B3: 2026-01 | C3: 2026-02 | D3: 2026-03 | E3: 2026-04 | F3: 2026-05 | G3: 2026-06 | H3: 2026-07 | I3: 2026-08 | J3: 2026-09 | K3: 2026-10 | L3: 2026-11 | M3: 2026-12 | N3: Monthly Avg | O3: Annualized | P3: Share of Personal Monthly Expense
A4: =Formula_Hub!A45 -> Housing | B4: =Formula_Hub!B45 -> 3000 | C4: =Formula_Hub!C45 -> 3000 | D4: =Formula_Hub!D45 -> 0 | E4: =Formula_Hub!E45 -> 0 | F4: =Formula_Hub!F45 -> 0 | G4: =Formula_Hub!G45 -> 0 | H4: =Formula_Hub!H45 -> 0 | ... P4: =Formula_Hub!P45 -> 0.58252427
A5: =Formula_Hub!A46 -> Food & Dining | B5: =Formula_Hub!B46 -> 770 | C5: =Formula_Hub!C46 -> 870 | D5: =Formula_Hub!D46 -> 0 | E5: =Formula_Hub!E46 -> 0 | F5: =Formula_Hub!F46 -> 0 | G5: =Formula_Hub!G46 -> 0 | H5: =Formula_Hub!H46 -> 0 | ... P5: =Formula_Hub!P46 -> 0.1592233
A6: =Formula_Hub!A47 -> Transportation | B6: =Formula_Hub!B47 -> 220 | C6: =Formula_Hub!C47 -> 260 | D6: =Formula_Hub!D47 -> 0 | E6: =Formula_Hub!E47 -> 0 | F6: =Formula_Hub!F47 -> 0 | G6: =Formula_Hub!G47 -> 0 | H6: =Formula_Hub!H47 -> 0 | ... P6: =Formula_Hub!P47 -> 0.046601942
A7: =Formula_Hub!A48 -> Telecom | B7: =Formula_Hub!B48 -> 60 | C7: =Formula_Hub!C48 -> 60 | D7: =Formula_Hub!D48 -> 0 | E7: =Formula_Hub!E48 -> 0 | F7: =Formula_Hub!F48 -> 0 | G7: =Formula_Hub!G48 -> 0 | H7: =Formula_Hub!H48 -> 0 | ... P7: =Formula_Hub!P48 -> 0.011650485
A8: =Formula_Hub!A49 -> Subscriptions | B8: =Formula_Hub!B49 -> 30 | C8: =Formula_Hub!C49 -> 45 | D8: =Formula_Hub!D49 -> 0 | E8: =Formula_Hub!E49 -> 0 | F8: =Formula_Hub!F49 -> 0 | G8: =Formula_Hub!G49 -> 0 | H8: =Formula_Hub!H49 -> 0 | ... P8: =Formula_Hub!P49 -> 0.0072815534
A9: =Formula_Hub!A50 -> Shopping | B9: =Formula_Hub!B50 -> 250 | C9: =Formula_Hub!C50 -> 300 | D9: =Formula_Hub!D50 -> 0 | E9: =Formula_Hub!E50 -> 0 | F9: =Formula_Hub!F50 -> 0 | G9: =Formula_Hub!G50 -> 0 | H9: =Formula_Hub!H50 -> 0 | ... P9: =Formula_Hub!P50 -> 0.053398058
A10: =Formula_Hub!A51 -> Medical | B10: =Formula_Hub!B51 -> 80 | C10: =Formula_Hub!C51 -> 100 | D10: =Formula_Hub!D51 -> 0 | E10: =Formula_Hub!E51 -> 0 | F10: =Formula_Hub!F51 -> 0 | G10: =Formula_Hub!G51 -> 0 | H10: =Formula_Hub!H51 -> 0 | ... P10: =Formula_Hub!P51 -> 0.017475728
A11: =Formula_Hub!A52 -> Fitness | B11: =Formula_Hub!B52 -> 70 | C11: =Formula_Hub!C52 -> 70 | D11: =Formula_Hub!D52 -> 0 | E11: =Formula_Hub!E52 -> 0 | F11: =Formula_Hub!F52 -> 0 | G11: =Formula_Hub!G52 -> 0 | H11: =Formula_Hub!H52 -> 0 | ... P11: =Formula_Hub!P52 -> 0.013592233
A12: =Formula_Hub!A53 -> Education | B12: =Formula_Hub!B53 -> 120 | C12: =Formula_Hub!C53 -> 140 | D12: =Formula_Hub!D53 -> 0 | E12: =Formula_Hub!E53 -> 0 | F12: =Formula_Hub!F53 -> 0 | G12: =Formula_Hub!G53 -> 0 | H12: =Formula_Hub!H53 -> 0 | ... P12: =Formula_Hub!P53 -> 0.025242718
A13: =Formula_Hub!A54 -> Pet | B13: =Formula_Hub!B54 -> 90 | C13: =Formula_Hub!C54 -> 100 | D13: =Formula_Hub!D54 -> 0 | E13: =Formula_Hub!E54 -> 0 | F13: =Formula_Hub!F54 -> 0 | G13: =Formula_Hub!G54 -> 0 | H13: =Formula_Hub!H54 -> 0 | ... P13: =Formula_Hub!P54 -> 0.018446602
A14: =Formula_Hub!A55 -> Entertainment | B14: =Formula_Hub!B55 -> 100 | C14: =Formula_Hub!C55 -> 120 | D14: =Formula_Hub!D55 -> 0 | E14: =Formula_Hub!E55 -> 0 | F14: =Formula_Hub!F55 -> 0 | G14: =Formula_Hub!G55 -> 0 | H14: =Formula_Hub!H55 -> 0 | ... P14: =Formula_Hub!P55 -> 0.021359223
A15: =Formula_Hub!A56 -> Taxes & Gov Fees | B15: =Formula_Hub!B56 -> 100 | C15: =Formula_Hub!C56 -> 150 | D15: =Formula_Hub!D56 -> 0 | E15: =Formula_Hub!E56 -> 0 | F15: =Formula_Hub!F56 -> 0 | G15: =Formula_Hub!G56 -> 0 | H15: =Formula_Hub!H56 -> 0 | ... P15: =Formula_Hub!P56 -> 0.024271845
A16: =Formula_Hub!A57 -> Other | B16: =Formula_Hub!B57 -> 110 | C16: =Formula_Hub!C57 -> 85 | D16: =Formula_Hub!D57 -> 0 | E16: =Formula_Hub!E57 -> 0 | F16: =Formula_Hub!F57 -> 0 | G16: =Formula_Hub!G57 -> 0 | H16: =Formula_Hub!H57 -> 0 | ... P16: =Formula_Hub!P57 -> 0.018932039

Sheet Sales_Tax_Analysis
A1: Sales Tax Analysis
A2: Summarizes estimated sales tax by month.
A3: Month | B3: Taxable Spending | C3: Zero-rated Spending | D3: Exempt Spending | E3: Other / N.A. | F3: Pre-tax Amount | G3: Federal Tax Estimate | H3: Provincial Tax Estimate | I3: Estimated Sales Tax | J3: Note
A4: 2026-01 | B4: =SUMIFS(Sales_Tax_Detail!$L$4:$L$500,Sales_Tax_Detail!$C$4:$C$500,$A4) -> 1140 | C4: =SUMIFS(Sales_Tax_Detail!$M$4:$M$500,Sales_Tax_Detail!$C$4:$C$500,$A4) -> 450 | D4: =SUMIFS(Sales_Tax_Detail!$N$4:$N$500,Sales_Tax_Detail!$C$4:$C$500,$A4) -> 3080 | E4: =SUMIFS(Sales_Tax_Detail!$O$4:$O$500,Sales_Tax_Detail!$C$4:$C$500,$A4) -> 330 | F4: =SUMIFS(Sales_Tax_Detail!$P$4:$P$500,Sales_Tax_Detail!$C$4:$C$500,$A4) -> 991.5199 | G4: =SUMIFS(Sales_Tax_Detail!$Q$4:$Q$500,Sales_Tax_Detail!$C$4:$C$500,$A4) -> 49.575995 | H4: =SUMIFS(Sales_Tax_Detail!$R$4:$R$500,Sales_Tax_Detail!$C$4:$C$500,$A4) -> 98.90411 | I4: =SUMIFS(Sales_Tax_Detail!$S$4:$S$500,Sales_Tax_Detail!$C$4:$C$500,$A4) -> 148.4801 | J4: =IF(I4>0,"Estimated","No estimated tax") -> Estimated
A5: 2026-02 | B5: =SUMIFS(Sales_Tax_Detail!$L$4:$L$500,Sales_Tax_Detail!$C$4:$C$500,$A5) -> 1305 | C5: =SUMIFS(Sales_Tax_Detail!$M$4:$M$500,Sales_Tax_Detail!$C$4:$C$500,$A5) -> 520 | D5: =SUMIFS(Sales_Tax_Detail!$N$4:$N$500,Sales_Tax_Detail!$C$4:$C$500,$A5) -> 3100 | E5: =SUMIFS(Sales_Tax_Detail!$O$4:$O$500,Sales_Tax_Detail!$C$4:$C$500,$A5) -> 375 | F5: =SUMIFS(Sales_Tax_Detail!$P$4:$P$500,Sales_Tax_Detail!$C$4:$C$500,$A5) -> 1135.0294 | G5: =SUMIFS(Sales_Tax_Detail!$Q$4:$Q$500,Sales_Tax_Detail!$C$4:$C$500,$A5) -> 56.751468 | H5: =SUMIFS(Sales_Tax_Detail!$R$4:$R$500,Sales_Tax_Detail!$C$4:$C$500,$A5) -> 113.21918 | I5: =SUMIFS(Sales_Tax_Detail!$S$4:$S$500,Sales_Tax_Detail!$C$4:$C$500,$A5) -> 169.97065 | J5: =IF(I5>0,"Estimated","No estimated tax") -> Estimated
A6: 2026-03 | B6: =SUMIFS(Sales_Tax_Detail!$L$4:$L$500,Sales_Tax_Detail!$C$4:$C$500,$A6) -> 0 | C6: =SUMIFS(Sales_Tax_Detail!$M$4:$M$500,Sales_Tax_Detail!$C$4:$C$500,$A6) -> 0 | D6: =SUMIFS(Sales_Tax_Detail!$N$4:$N$500,Sales_Tax_Detail!$C$4:$C$500,$A6) -> 0 | E6: =SUMIFS(Sales_Tax_Detail!$O$4:$O$500,Sales_Tax_Detail!$C$4:$C$500,$A6) -> 0 | F6: =SUMIFS(Sales_Tax_Detail!$P$4:$P$500,Sales_Tax_Detail!$C$4:$C$500,$A6) -> 0 | G6: =SUMIFS(Sales_Tax_Detail!$Q$4:$Q$500,Sales_Tax_Detail!$C$4:$C$500,$A6) -> 0 | H6: =SUMIFS(Sales_Tax_Detail!$R$4:$R$500,Sales_Tax_Detail!$C$4:$C$500,$A6) -> 0 | I6: =SUMIFS(Sales_Tax_Detail!$S$4:$S$500,Sales_Tax_Detail!$C$4:$C$500,$A6) -> 0 | J6: =IF(I6>0,"Estimated","No estimated tax") -> No estimated tax
A7: 2026-04 | B7: =SUMIFS(Sales_Tax_Detail!$L$4:$L$500,Sales_Tax_Detail!$C$4:$C$500,$A7) -> 0 | C7: =SUMIFS(Sales_Tax_Detail!$M$4:$M$500,Sales_Tax_Detail!$C$4:$C$500,$A7) -> 0 | D7: =SUMIFS(Sales_Tax_Detail!$N$4:$N$500,Sales_Tax_Detail!$C$4:$C$500,$A7) -> 0 | E7: =SUMIFS(Sales_Tax_Detail!$O$4:$O$500,Sales_Tax_Detail!$C$4:$C$500,$A7) -> 0 | F7: =SUMIFS(Sales_Tax_Detail!$P$4:$P$500,Sales_Tax_Detail!$C$4:$C$500,$A7) -> 0 | G7: =SUMIFS(Sales_Tax_Detail!$Q$4:$Q$500,Sales_Tax_Detail!$C$4:$C$500,$A7) -> 0 | H7: =SUMIFS(Sales_Tax_Detail!$R$4:$R$500,Sales_Tax_Detail!$C$4:$C$500,$A7) -> 0 | I7: =SUMIFS(Sales_Tax_Detail!$S$4:$S$500,Sales_Tax_Detail!$C$4:$C$500,$A7) -> 0 | J7: =IF(I7>0,"Estimated","No estimated tax") -> No estimated tax
A8: 2026-05 | B8: =SUMIFS(Sales_Tax_Detail!$L$4:$L$500,Sales_Tax_Detail!$C$4:$C$500,$A8) -> 0 | C8: =SUMIFS(Sales_Tax_Detail!$M$4:$M$500,Sales_Tax_Detail!$C$4:$C$500,$A8) -> 0 | D8: =SUMIFS(Sales_Tax_Detail!$N$4:$N$500,Sales_Tax_Detail!$C$4:$C$500,$A8) -> 0 | E8: =SUMIFS(Sales_Tax_Detail!$O$4:$O$500,Sales_Tax_Detail!$C$4:$C$500,$A8) -> 0 | F8: =SUMIFS(Sales_Tax_Detail!$P$4:$P$500,Sales_Tax_Detail!$C$4:$C$500,$A8) -> 0 | G8: =SUMIFS(Sales_Tax_Detail!$Q$4:$Q$500,Sales_Tax_Detail!$C$4:$C$500,$A8) -> 0 | H8: =SUMIFS(Sales_Tax_Detail!$R$4:$R$500,Sales_Tax_Detail!$C$4:$C$500,$A8) -> 0 | I8: =SUMIFS(Sales_Tax_Detail!$S$4:$S$500,Sales_Tax_Detail!$C$4:$C$500,$A8) -> 0 | J8: =IF(I8>0,"Estimated","No estimated tax") -> No estimated tax
A9: 2026-06 | B9: =SUMIFS(Sales_Tax_Detail!$L$4:$L$500,Sales_Tax_Detail!$C$4:$C$500,$A9) -> 0 | C9: =SUMIFS(Sales_Tax_Detail!$M$4:$M$500,Sales_Tax_Detail!$C$4:$C$500,$A9) -> 0 | D9: =SUMIFS(Sales_Tax_Detail!$N$4:$N$500,Sales_Tax_Detail!$C$4:$C$500,$A9) -> 0 | E9: =SUMIFS(Sales_Tax_Detail!$O$4:$O$500,Sales_Tax_Detail!$C$4:$C$500,$A9) -> 0 | F9: =SUMIFS(Sales_Tax_Detail!$P$4:$P$500,Sales_Tax_Detail!$C$4:$C$500,$A9) -> 0 | G9: =SUMIFS(Sales_Tax_Detail!$Q$4:$Q$500,Sales_Tax_Detail!$C$4:$C$500,$A9) -> 0 | H9: =SUMIFS(Sales_Tax_Detail!$R$4:$R$500,Sales_Tax_Detail!$C$4:$C$500,$A9) -> 0 | I9: =SUMIFS(Sales_Tax_Detail!$S$4:$S$500,Sales_Tax_Detail!$C$4:$C$500,$A9) -> 0 | J9: =IF(I9>0,"Estimated","No estimated tax") -> No estimated tax
A10: 2026-07 | B10: =SUMIFS(Sales_Tax_Detail!$L$4:$L$500,Sales_Tax_Detail!$C$4:$C$500,$A10) -> 0 | C10: =SUMIFS(Sales_Tax_Detail!$M$4:$M$500,Sales_Tax_Detail!$C$4:$C$500,$A10) -> 0 | D10: =SUMIFS(Sales_Tax_Detail!$N$4:$N$500,Sales_Tax_Detail!$C$4:$C$500,$A10) -> 0 | E10: =SUMIFS(Sales_Tax_Detail!$O$4:$O$500,Sales_Tax_Detail!$C$4:$C$500,$A10) -> 0 | F10: =SUMIFS(Sales_Tax_Detail!$P$4:$P$500,Sales_Tax_Detail!$C$4:$C$500,$A10) -> 0 | G10: =SUMIFS(Sales_Tax_Detail!$Q$4:$Q$500,Sales_Tax_Detail!$C$4:$C$500,$A10) -> 0 | H10: =SUMIFS(Sales_Tax_Detail!$R$4:$R$500,Sales_Tax_Detail!$C$4:$C$500,$A10) -> 0 | I10: =SUMIFS(Sales_Tax_Detail!$S$4:$S$500,Sales_Tax_Detail!$C$4:$C$500,$A10) -> 0 | J10: =IF(I10>0,"Estimated","No estimated tax") -> No estimated tax
A11: 2026-08 | B11: =SUMIFS(Sales_Tax_Detail!$L$4:$L$500,Sales_Tax_Detail!$C$4:$C$500,$A11) -> 0 | C11: =SUMIFS(Sales_Tax_Detail!$M$4:$M$500,Sales_Tax_Detail!$C$4:$C$500,$A11) -> 0 | D11: =SUMIFS(Sales_Tax_Detail!$N$4:$N$500,Sales_Tax_Detail!$C$4:$C$500,$A11) -> 0 | E11: =SUMIFS(Sales_Tax_Detail!$O$4:$O$500,Sales_Tax_Detail!$C$4:$C$500,$A11) -> 0 | F11: =SUMIFS(Sales_Tax_Detail!$P$4:$P$500,Sales_Tax_Detail!$C$4:$C$500,$A11) -> 0 | G11: =SUMIFS(Sales_Tax_Detail!$Q$4:$Q$500,Sales_Tax_Detail!$C$4:$C$500,$A11) -> 0 | H11: =SUMIFS(Sales_Tax_Detail!$R$4:$R$500,Sales_Tax_Detail!$C$4:$C$500,$A11) -> 0 | I11: =SUMIFS(Sales_Tax_Detail!$S$4:$S$500,Sales_Tax_Detail!$C$4:$C$500,$A11) -> 0 | J11: =IF(I11>0,"Estimated","No estimated tax") -> No estimated tax
A12: 2026-09 | B12: =SUMIFS(Sales_Tax_Detail!$L$4:$L$500,Sales_Tax_Detail!$C$4:$C$500,$A12) -> 0 | C12: =SUMIFS(Sales_Tax_Detail!$M$4:$M$500,Sales_Tax_Detail!$C$4:$C$500,$A12) -> 0 | D12: =SUMIFS(Sales_Tax_Detail!$N$4:$N$500,Sales_Tax_Detail!$C$4:$C$500,$A12) -> 0 | E12: =SUMIFS(Sales_Tax_Detail!$O$4:$O$500,Sales_Tax_Detail!$C$4:$C$500,$A12) -> 0 | F12: =SUMIFS(Sales_Tax_Detail!$P$4:$P$500,Sales_Tax_Detail!$C$4:$C$500,$A12) -> 0 | G12: =SUMIFS(Sales_Tax_Detail!$Q$4:$Q$500,Sales_Tax_Detail!$C$4:$C$500,$A12) -> 0 | H12: =SUMIFS(Sales_Tax_Detail!$R$4:$R$500,Sales_Tax_Detail!$C$4:$C$500,$A12) -> 0 | I12: =SUMIFS(Sales_Tax_Detail!$S$4:$S$500,Sales_Tax_Detail!$C$4:$C$500,$A12) -> 0 | J12: =IF(I12>0,"Estimated","No estimated tax") -> No estimated tax
A13: 2026-10 | B13: =SUMIFS(Sales_Tax_Detail!$L$4:$L$500,Sales_Tax_Detail!$C$4:$C$500,$A13) -> 0 | C13: =SUMIFS(Sales_Tax_Detail!$M$4:$M$500,Sales_Tax_Detail!$C$4:$C$500,$A13) -> 0 | D13: =SUMIFS(Sales_Tax_Detail!$N$4:$N$500,Sales_Tax_Detail!$C$4:$C$500,$A13) -> 0 | E13: =SUMIFS(Sales_Tax_Detail!$O$4:$O$500,Sales_Tax_Detail!$C$4:$C$500,$A13) -> 0 | F13: =SUMIFS(Sales_Tax_Detail!$P$4:$P$500,Sales_Tax_Detail!$C$4:$C$500,$A13) -> 0 | G13: =SUMIFS(Sales_Tax_Detail!$Q$4:$Q$500,Sales_Tax_Detail!$C$4:$C$500,$A13) -> 0 | H13: =SUMIFS(Sales_Tax_Detail!$R$4:$R$500,Sales_Tax_Detail!$C$4:$C$500,$A13) -> 0 | I13: =SUMIFS(Sales_Tax_Detail!$S$4:$S$500,Sales_Tax_Detail!$C$4:$C$500,$A13) -> 0 | J13: =IF(I13>0,"Estimated","No estimated tax") -> No estimated tax
A14: 2026-11 | B14: =SUMIFS(Sales_Tax_Detail!$L$4:$L$500,Sales_Tax_Detail!$C$4:$C$500,$A14) -> 0 | C14: =SUMIFS(Sales_Tax_Detail!$M$4:$M$500,Sales_Tax_Detail!$C$4:$C$500,$A14) -> 0 | D14: =SUMIFS(Sales_Tax_Detail!$N$4:$N$500,Sales_Tax_Detail!$C$4:$C$500,$A14) -> 0 | E14: =SUMIFS(Sales_Tax_Detail!$O$4:$O$500,Sales_Tax_Detail!$C$4:$C$500,$A14) -> 0 | F14: =SUMIFS(Sales_Tax_Detail!$P$4:$P$500,Sales_Tax_Detail!$C$4:$C$500,$A14) -> 0 | G14: =SUMIFS(Sales_Tax_Detail!$Q$4:$Q$500,Sales_Tax_Detail!$C$4:$C$500,$A14) -> 0 | H14: =SUMIFS(Sales_Tax_Detail!$R$4:$R$500,Sales_Tax_Detail!$C$4:$C$500,$A14) -> 0 | I14: =SUMIFS(Sales_Tax_Detail!$S$4:$S$500,Sales_Tax_Detail!$C$4:$C$500,$A14) -> 0 | J14: =IF(I14>0,"Estimated","No estimated tax") -> No estimated tax
A15: 2026-12 | B15: =SUMIFS(Sales_Tax_Detail!$L$4:$L$500,Sales_Tax_Detail!$C$4:$C$500,$A15) -> 0 | C15: =SUMIFS(Sales_Tax_Detail!$M$4:$M$500,Sales_Tax_Detail!$C$4:$C$500,$A15) -> 0 | D15: =SUMIFS(Sales_Tax_Detail!$N$4:$N$500,Sales_Tax_Detail!$C$4:$C$500,$A15) -> 0 | E15: =SUMIFS(Sales_Tax_Detail!$O$4:$O$500,Sales_Tax_Detail!$C$4:$C$500,$A15) -> 0 | F15: =SUMIFS(Sales_Tax_Detail!$P$4:$P$500,Sales_Tax_Detail!$C$4:$C$500,$A15) -> 0 | G15: =SUMIFS(Sales_Tax_Detail!$Q$4:$Q$500,Sales_Tax_Detail!$C$4:$C$500,$A15) -> 0 | H15: =SUMIFS(Sales_Tax_Detail!$R$4:$R$500,Sales_Tax_Detail!$C$4:$C$500,$A15) -> 0 | I15: =SUMIFS(Sales_Tax_Detail!$S$4:$S$500,Sales_Tax_Detail!$C$4:$C$500,$A15) -> 0 | J15: =IF(I15>0,"Estimated","No estimated tax") -> No estimated tax
A17: Annual Total | B17: =SUM(B4:B15) -> 2445 | C17: =SUM(C4:C15) -> 970 | D17: =SUM(D4:D15) -> 6180 | E17: =SUM(E4:E15) -> 705 | F17: =SUM(F4:F15) -> 2126.5492 | G17: =SUM(G4:G15) -> 106.32746 | H17: =SUM(H4:H15) -> 212.12329 | I17: =SUM(I4:I15) -> 318.45075
A18: Sales tax as % of personal expense | B18: =IFERROR(I17/Formula_Hub!$B$6,0) -> 0.030917549

Sheet Formula_Hub
A1: Formula Hub
A2: All core calculations are centralized here.
A4: Included Analysis Months | B4: =SUM($K$28:$K$39) -> 2
A5: Total Income | B5: =SUM($B$28:$B$39) -> 12900
A6: Total Personal Expense | B6: =SUM($C$28:$C$39) -> 10300
A7: Average Monthly Personal Expense | B7: =IF($B$4=0,0,$B$6/$B$4) -> 5150
A8: Average Monthly Essential Expense | B8: =IF($B$4=0,0,SUM($D$28:$D$39)/$B$4) -> 4000
A9: Average Monthly Discretionary Expense | B9: =IF($B$4=0,0,SUM($E$28:$E$39)/$B$4) -> 1150
A10: Average Monthly Fixed Expense | B10: =IF($B$4=0,0,SUM($F$28:$F$39)/$B$4) -> 3167.5
A11: Average Monthly Variable Expense | B11: =IF($B$4=0,0,SUM($G$28:$G$39)/$B$4) -> 1727.5
A12: Average Monthly One-time Expense | B12: =IF($B$4=0,0,SUM($H$28:$H$39)/$B$4) -> 255
A13: Average Monthly Housing Expense | B13: =IF($B$4=0,0,SUM($I$28:$I$39)/$B$4) -> 3000
A14: Housing Expense Ratio | B14: =IFERROR($B$13/$B$7,0) -> 0.58252427
A15: Savings Rate | B15: =IFERROR(($B$5-$B$6)/$B$5,0) -> 0.20155039
A16: Cash Coverage Months | B16: =IFERROR(Input_Settings!$B$5/$B$7,0) -> 5.8252427
A17: Normal One-Year Living Reserve | B17: =B7*12 -> 61800
A18: Essential One-Year Living Reserve | B18: =B8*12 -> 48000
A19: Conservative One-Year Living Reserve | B19: =MAX($C$28:$C$39)*12 -> 63600
A20: Recommended Cash Reserve | B20: =MAX($B$7*Input_Settings!$B$8,Input_Settings!$B$9)+Input_Settings!$B$6 -> 62800
A21: Suggested Investable Cash | B21: =MAX(0,Input_Settings!$B$5-$B$20) -> 0
A22: Cash Shortfall | B22: =MAX(0,$B$20-Input_Settings!$B$5) -> 32800
A23: Cash Safety Level | B23: =IF($B$16>=12,"Safe",IF($B$16>=6,"Moderately Safe","Tight")) -> Tight
A24: Estimated Annual Sales Tax | B24: =Sales_Tax_Analysis!$I$17 -> 318.45075
A25: Sales Tax Estimate Status | B25: =IF(Sales_Tax_Settings!$B$5="Yes","Enabled","Disabled") -> Enabled
A27: Month | B27: Total Income | C27: Personal Expense | D27: Essential Expense | E27: Discretionary Expense | F27: Fixed Expense | G27: Variable Expense | H27: One-time Expense | I27: Housing Expense | J27: Net Cash Flow | K27: Included in Average | L27: Property Expense | M27: Investment Transfer | N27: Internal Transfer | O27: Estimated Sales Tax
A28: 2026-01 | B28: =SUMIFS(Income_Input!$D$4:$D$500,Income_Input!$B$4:$B$500,">="&DATE(VALUE(LEFT($A28,4)),VALUE(RIGHT($A28,2)),1),Income_Input!$B$4:$B$500,"<"&DATE(VALUE(LEFT($A28,4)),VALUE(RIGHT($A28,2))+1,1)) -> 6000 | C28: =SUMIFS(Expense_Input!$D$4:$D$500,Expense_Input!$B$4:$B$500,">="&DATE(VALUE(LEFT($A28,4)),VALUE(RIGHT($A28,2)),1),Expense_Input!$B$4:$B$500,"<"&DATE(VALUE(LEFT($A28,4)),VALUE(RIGHT($A28,2))+1,1),Expense_Input!$H$4:$H$500,"Personal Expense") -> 5000 | D28: =SUMIFS(Expense_Input!$D$4:$D$500,Expense_Input!$B$4:$B$500,">="&DATE(VALUE(LEFT($A28,4)),VALUE(RIGHT($A28,2)),1),Expense_Input!$B$4:$B$500,"<"&DATE(VALUE(LEFT($A28,4)),VALUE(RIGHT($A28,2))+1,1),Expense_Input!$H$4:$H$500,"Personal Expense",Expense_Input!$G$4:$G$500,"Essential") -> 3910 | E28: =SUMIFS(Expense_Input!$D$4:$D$500,Expense_Input!$B$4:$B$500,">="&DATE(VALUE(LEFT($A28,4)),VALUE(RIGHT($A28,2)),1),Expense_Input!$B$4:$B$500,"<"&DATE(VALUE(LEFT($A28,4)),VALUE(RIGHT($A28,2))+1,1),Expense_Input!$H$4:$H$500,"Personal Expense",Expense_Input!$G$4:$G$500,"Discretionary") -> 1090 | F28: =SUMIFS(Expense_Input!$D$4:$D$500,Expense_Input!$B$4:$B$500,">="&DATE(VALUE(LEFT($A28,4)),VALUE(RIGHT($A28,2)),1),Expense_Input!$B$4:$B$500,"<"&DATE(VALUE(LEFT($A28,4)),VALUE(RIGHT($A28,2))+1,1),Expense_Input!$H$4:$H$500,"Personal Expense",Expense_Input!$F$4:$F$500,"Fixed") -> 3160 | G28: =SUMIFS(Expense_Input!$D$4:$D$500,Expense_Input!$B$4:$B$500,">="&DATE(VALUE(LEFT($A28,4)),VALUE(RIGHT($A28,2)),1),Expense_Input!$B$4:$B$500,"<"&DATE(VALUE(LEFT($A28,4)),VALUE(RIGHT($A28,2))+1,1),Expense_Input!$H$4:$H$500,"Personal Expense",Expense_Input!$F$4:$F$500,"Variable") -> 1620 | H28: =SUMIFS(Expense_Input!$D$4:$D$500,Expense_Input!$B$4:$B$500,">="&DATE(VALUE(LEFT($A28,4)),VALUE(RIGHT($A28,2)),1),Expense_Input!$B$4:$B$500,"<"&DATE(VALUE(LEFT($A28,4)),VALUE(RIGHT($A28,2))+1,1),Expense_Input!$H$4:$H$500,"Personal Expense",Expense_Input!$F$4:$F$500,"One-time") -> 220 | I28: =SUMIFS(Expense_Input!$D$4:$D$500,Expense_Input!$B$4:$B$500,">="&DATE(VALUE(LEFT($A28,4)),VALUE(RIGHT($A28,2)),1),Expense_Input!$B$4:$B$500,"<"&DATE(VALUE(LEFT($A28,4)),VALUE(RIGHT($A28,2))+1,1),Expense_Input!$H$4:$H$500,"Personal Expense",Expense_Input!$E$4:$E$500,"Housing") -> 3000 | J28: =B28-C28 -> 1000 | K28: =IF(C28>0,1,0) -> 1 | L28: =SUMIFS(Expense_Input!$D$4:$D$500,Expense_Input!$B$4:$B$500,">="&DATE(VALUE(LEFT($A28,4)),VALUE(RIGHT($A28,2)),1),Expense_Input!$B$4:$B$500,"<"&DATE(VALUE(LEFT($A28,4)),VALUE(RIGHT($A28,2))+1,1),Expense_Input!$H$4:$H$500,"Property Expense") -> 0 | M28: =SUMIFS(Expense_Input!$D$4:$D$500,Expense_Input!$B$4:$B$500,">="&DATE(VALUE(LEFT($A28,4)),VALUE(RIGHT($A28,2)),1),Expense_Input!$B$4:$B$500,"<"&DATE(VALUE(LEFT($A28,4)),VALUE(RIGHT($A28,2))+1,1),Expense_Input!$H$4:$H$500,"Investment Transfer") -> 0 | N28: =SUMIFS(Expense_Input!$D$4:$D$500,Expense_Input!$B$4:$B$500,">="&DATE(VALUE(LEFT($A28,4)),VALUE(RIGHT($A28,2)),1),Expense_Input!$B$4:$B$500,"<"&DATE(VALUE(LEFT($A28,4)),VALUE(RIGHT($A28,2))+1,1),Expense_Input!$H$4:$H$500,"Internal Transfer") -> 0 | O28: =SUMIFS(Sales_Tax_Detail!$S$4:$S$500,Sales_Tax_Detail!$C$4:$C$500,$A28) -> 148.4801
A29: 2026-02 | B29: =SUMIFS(Income_Input!$D$4:$D$500,Income_Input!$B$4:$B$500,">="&DATE(VALUE(LEFT($A29,4)),VALUE(RIGHT($A29,2)),1),Income_Input!$B$4:$B$500,"<"&DATE(VALUE(LEFT($A29,4)),VALUE(RIGHT($A29,2))+1,1)) -> 6900 | C29: =SUMIFS(Expense_Input!$D$4:$D$500,Expense_Input!$B$4:$B$500,">="&DATE(VALUE(LEFT($A29,4)),VALUE(RIGHT($A29,2)),1),Expense_Input!$B$4:$B$500,"<"&DATE(VALUE(LEFT($A29,4)),VALUE(RIGHT($A29,2))+1,1),Expense_Input!$H$4:$H$500,"Personal Expense") -> 5300 | D29: =SUMIFS(Expense_Input!$D$4:$D$500,Expense_Input!$B$4:$B$500,">="&DATE(VALUE(LEFT($A29,4)),VALUE(RIGHT($A29,2)),1),Expense_Input!$B$4:$B$500,"<"&DATE(VALUE(LEFT($A29,4)),VALUE(RIGHT($A29,2))+1,1),Expense_Input!$H$4:$H$500,"Personal Expense",Expense_Input!$G$4:$G$500,"Essential") -> 4090 | E29: =SUMIFS(Expense_Input!$D$4:$D$500,Expense_Input!$B$4:$B$500,">="&DATE(VALUE(LEFT($A29,4)),VALUE(RIGHT($A29,2)),1),Expense_Input!$B$4:$B$500,"<"&DATE(VALUE(LEFT($A29,4)),VALUE(RIGHT($A29,2))+1,1),Expense_Input!$H$4:$H$500,"Personal Expense",Expense_Input!$G$4:$G$500,"Discretionary") -> 1210 | F29: =SUMIFS(Expense_Input!$D$4:$D$500,Expense_Input!$B$4:$B$500,">="&DATE(VALUE(LEFT($A29,4)),VALUE(RIGHT($A29,2)),1),Expense_Input!$B$4:$B$500,"<"&DATE(VALUE(LEFT($A29,4)),VALUE(RIGHT($A29,2))+1,1),Expense_Input!$H$4:$H$500,"Personal Expense",Expense_Input!$F$4:$F$500,"Fixed") -> 3175 | G29: =SUMIFS(Expense_Input!$D$4:$D$500,Expense_Input!$B$4:$B$500,">="&DATE(VALUE(LEFT($A29,4)),VALUE(RIGHT($A29,2)),1),Expense_Input!$B$4:$B$500,"<"&DATE(VALUE(LEFT($A29,4)),VALUE(RIGHT($A29,2))+1,1),Expense_Input!$H$4:$H$500,"Personal Expense",Expense_Input!$F$4:$F$500,"Variable") -> 1835 | H29: =SUMIFS(Expense_Input!$D$4:$D$500,Expense_Input!$B$4:$B$500,">="&DATE(VALUE(LEFT($A29,4)),VALUE(RIGHT($A29,2)),1),Expense_Input!$B$4:$B$500,"<"&DATE(VALUE(LEFT($A29,4)),VALUE(RIGHT($A29,2))+1,1),Expense_Input!$H$4:$H$500,"Personal Expense",Expense_Input!$F$4:$F$500,"One-time") -> 290 | I29: =SUMIFS(Expense_Input!$D$4:$D$500,Expense_Input!$B$4:$B$500,">="&DATE(VALUE(LEFT($A29,4)),VALUE(RIGHT($A29,2)),1),Expense_Input!$B$4:$B$500,"<"&DATE(VALUE(LEFT($A29,4)),VALUE(RIGHT($A29,2))+1,1),Expense_Input!$H$4:$H$500,"Personal Expense",Expense_Input!$E$4:$E$500,"Housing") -> 3000 | J29: =B29-C29 -> 1600 | K29: =IF(C29>0,1,0) -> 1 | L29: =SUMIFS(Expense_Input!$D$4:$D$500,Expense_Input!$B$4:$B$500,">="&DATE(VALUE(LEFT($A29,4)),VALUE(RIGHT($A29,2)),1),Expense_Input!$B$4:$B$500,"<"&DATE(VALUE(LEFT($A29,4)),VALUE(RIGHT($A29,2))+1,1),Expense_Input!$H$4:$H$500,"Property Expense") -> 0 | M29: =SUMIFS(Expense_Input!$D$4:$D$500,Expense_Input!$B$4:$B$500,">="&DATE(VALUE(LEFT($A29,4)),VALUE(RIGHT($A29,2)),1),Expense_Input!$B$4:$B$500,"<"&DATE(VALUE(LEFT($A29,4)),VALUE(RIGHT($A29,2))+1,1),Expense_Input!$H$4:$H$500,"Investment Transfer") -> 0 | N29: =SUMIFS(Expense_Input!$D$4:$D$500,Expense_Input!$B$4:$B$500,">="&DATE(VALUE(LEFT($A29,4)),VALUE(RIGHT($A29,2)),1),Expense_Input!$B$4:$B$500,"<"&DATE(VALUE(LEFT($A29,4)),VALUE(RIGHT($A29,2))+1,1),Expense_Input!$H$4:$H$500,"Internal Transfer") -> 0 | O29: =SUMIFS(Sales_Tax_Detail!$S$4:$S$500,Sales_Tax_Detail!$C$4:$C$500,$A29) -> 169.97065
A30: 2026-03 | B30: =SUMIFS(Income_Input!$D$4:$D$500,Income_Input!$B$4:$B$500,">="&DATE(VALUE(LEFT($A30,4)),VALUE(RIGHT($A30,2)),1),Income_Input!$B$4:$B$500,"<"&DATE(VALUE(LEFT($A30,4)),VALUE(RIGHT($A30,2))+1,1)) -> 0 | C30: =SUMIFS(Expense_Input!$D$4:$D$500,Expense_Input!$B$4:$B$500,">="&DATE(VALUE(LEFT($A30,4)),VALUE(RIGHT($A30,2)),1),Expense_Input!$B$4:$B$500,"<"&DATE(VALUE(LEFT($A30,4)),VALUE(RIGHT($A30,2))+1,1),Expense_Input!$H$4:$H$500,"Personal Expense") -> 0 | D30: =SUMIFS(Expense_Input!$D$4:$D$500,Expense_Input!$B$4:$B$500,">="&DATE(VALUE(LEFT($A30,4)),VALUE(RIGHT($A30,2)),1),Expense_Input!$B$4:$B$500,"<"&DATE(VALUE(LEFT($A30,4)),VALUE(RIGHT($A30,2))+1,1),Expense_Input!$H$4:$H$500,"Personal Expense",Expense_Input!$G$4:$G$500,"Essential") -> 0 | E30: =SUMIFS(Expense_Input!$D$4:$D$500,Expense_Input!$B$4:$B$500,">="&DATE(VALUE(LEFT($A30,4)),VALUE(RIGHT($A30,2)),1),Expense_Input!$B$4:$B$500,"<"&DATE(VALUE(LEFT($A30,4)),VALUE(RIGHT($A30,2))+1,1),Expense_Input!$H$4:$H$500,"Personal Expense",Expense_Input!$G$4:$G$500,"Discretionary") -> 0 | F30: =SUMIFS(Expense_Input!$D$4:$D$500,Expense_Input!$B$4:$B$500,">="&DATE(VALUE(LEFT($A30,4)),VALUE(RIGHT($A30,2)),1),Expense_Input!$B$4:$B$500,"<"&DATE(VALUE(LEFT($A30,4)),VALUE(RIGHT($A30,2))+1,1),Expense_Input!$H$4:$H$500,"Personal Expense",Expense_Input!$F$4:$F$500,"Fixed") -> 0 | G30: =SUMIFS(Expense_Input!$D$4:$D$500,Expense_Input!$B$4:$B$500,">="&DATE(VALUE(LEFT($A30,4)),VALUE(RIGHT($A30,2)),1),Expense_Input!$B$4:$B$500,"<"&DATE(VALUE(LEFT($A30,4)),VALUE(RIGHT($A30,2))+1,1),Expense_Input!$H$4:$H$500,"Personal Expense",Expense_Input!$F$4:$F$500,"Variable") -> 0 | H30: =SUMIFS(Expense_Input!$D$4:$D$500,Expense_Input!$B$4:$B$500,">="&DATE(VALUE(LEFT($A30,4)),VALUE(RIGHT($A30,2)),1),Expense_Input!$B$4:$B$500,"<"&DATE(VALUE(LEFT($A30,4)),VALUE(RIGHT($A30,2))+1,1),Expense_Input!$H$4:$H$500,"Personal Expense",Expense_Input!$F$4:$F$500,"One-time") -> 0 | I30: =SUMIFS(Expense_Input!$D$4:$D$500,Expense_Input!$B$4:$B$500,">="&DATE(VALUE(LEFT($A30,4)),VALUE(RIGHT($A30,2)),1),Expense_Input!$B$4:$B$500,"<"&DATE(VALUE(LEFT($A30,4)),VALUE(RIGHT($A30,2))+1,1),Expense_Input!$H$4:$H$500,"Personal Expense",Expense_Input!$E$4:$E$500,"Housing") -> 0 | J30: =B30-C30 -> 0 | K30: =IF(C30>0,1,0) -> 0 | L30: =SUMIFS(Expense_Input!$D$4:$D$500,Expense_Input!$B$4:$B$500,">="&DATE(VALUE(LEFT($A30,4)),VALUE(RIGHT($A30,2)),1),Expense_Input!$B$4:$B$500,"<"&DATE(VALUE(LEFT($A30,4)),VALUE(RIGHT($A30,2))+1,1),Expense_Input!$H$4:$H$500,"Property Expense") -> 0 | M30: =SUMIFS(Expense_Input!$D$4:$D$500,Expense_Input!$B$4:$B$500,">="&DATE(VALUE(LEFT($A30,4)),VALUE(RIGHT($A30,2)),1),Expense_Input!$B$4:$B$500,"<"&DATE(VALUE(LEFT($A30,4)),VALUE(RIGHT($A30,2))+1,1),Expense_Input!$H$4:$H$500,"Investment Transfer") -> 0 | N30: =SUMIFS(Expense_Input!$D$4:$D$500,Expense_Input!$B$4:$B$500,">="&DATE(VALUE(LEFT($A30,4)),VALUE(RIGHT($A30,2)),1),Expense_Input!$B$4:$B$500,"<"&DATE(VALUE(LEFT($A30,4)),VALUE(RIGHT($A30,2))+1,1),Expense_Input!$H$4:$H$500,"Internal Transfer") -> 0 | O30: =SUMIFS(Sales_Tax_Detail!$S$4:$S$500,Sales_Tax_Detail!$C$4:$C$500,$A30) -> 0
A31: 2026-04 | B31: =SUMIFS(Income_Input!$D$4:$D$500,Income_Input!$B$4:$B$500,">="&DATE(VALUE(LEFT($A31,4)),VALUE(RIGHT($A31,2)),1),Income_Input!$B$4:$B$500,"<"&DATE(VALUE(LEFT($A31,4)),VALUE(RIGHT($A31,2))+1,1)) -> 0 | C31: =SUMIFS(Expense_Input!$D$4:$D$500,Expense_Input!$B$4:$B$500,">="&DATE(VALUE(LEFT($A31,4)),VALUE(RIGHT($A31,2)),1),Expense_Input!$B$4:$B$500,"<"&DATE(VALUE(LEFT($A31,4)),VALUE(RIGHT($A31,2))+1,1),Expense_Input!$H$4:$H$500,"Personal Expense") -> 0 | D31: =SUMIFS(Expense_Input!$D$4:$D$500,Expense_Input!$B$4:$B$500,">="&DATE(VALUE(LEFT($A31,4)),VALUE(RIGHT($A31,2)),1),Expense_Input!$B$4:$B$500,"<"&DATE(VALUE(LEFT($A31,4)),VALUE(RIGHT($A31,2))+1,1),Expense_Input!$H$4:$H$500,"Personal Expense",Expense_Input!$G$4:$G$500,"Essential") -> 0 | E31: =SUMIFS(Expense_Input!$D$4:$D$500,Expense_Input!$B$4:$B$500,">="&DATE(VALUE(LEFT($A31,4)),VALUE(RIGHT($A31,2)),1),Expense_Input!$B$4:$B$500,"<"&DATE(VALUE(LEFT($A31,4)),VALUE(RIGHT($A31,2))+1,1),Expense_Input!$H$4:$H$500,"Personal Expense",Expense_Input!$G$4:$G$500,"Discretionary") -> 0 | F31: =SUMIFS(Expense_Input!$D$4:$D$500,Expense_Input!$B$4:$B$500,">="&DATE(VALUE(LEFT($A31,4)),VALUE(RIGHT($A31,2)),1),Expense_Input!$B$4:$B$500,"<"&DATE(VALUE(LEFT($A31,4)),VALUE(RIGHT($A31,2))+1,1),Expense_Input!$H$4:$H$500,"Personal Expense",Expense_Input!$F$4:$F$500,"Fixed") -> 0 | G31: =SUMIFS(Expense_Input!$D$4:$D$500,Expense_Input!$B$4:$B$500,">="&DATE(VALUE(LEFT($A31,4)),VALUE(RIGHT($A31,2)),1),Expense_Input!$B$4:$B$500,"<"&DATE(VALUE(LEFT($A31,4)),VALUE(RIGHT($A31,2))+1,1),Expense_Input!$H$4:$H$500,"Personal Expense",Expense_Input!$F$4:$F$500,"Variable") -> 0 | H31: =SUMIFS(Expense_Input!$D$4:$D$500,Expense_Input!$B$4:$B$500,">="&DATE(VALUE(LEFT($A31,4)),VALUE(RIGHT($A31,2)),1),Expense_Input!$B$4:$B$500,"<"&DATE(VALUE(LEFT($A31,4)),VALUE(RIGHT($A31,2))+1,1),Expense_Input!$H$4:$H$500,"Personal Expense",Expense_Input!$F$4:$F$500,"One-time") -> 0 | I31: =SUMIFS(Expense_Input!$D$4:$D$500,Expense_Input!$B$4:$B$500,">="&DATE(VALUE(LEFT($A31,4)),VALUE(RIGHT($A31,2)),1),Expense_Input!$B$4:$B$500,"<"&DATE(VALUE(LEFT($A31,4)),VALUE(RIGHT($A31,2))+1,1),Expense_Input!$H$4:$H$500,"Personal Expense",Expense_Input!$E$4:$E$500,"Housing") -> 0 | J31: =B31-C31 -> 0 | K31: =IF(C31>0,1,0) -> 0 | L31: =SUMIFS(Expense_Input!$D$4:$D$500,Expense_Input!$B$4:$B$500,">="&DATE(VALUE(LEFT($A31,4)),VALUE(RIGHT($A31,2)),1),Expense_Input!$B$4:$B$500,"<"&DATE(VALUE(LEFT($A31,4)),VALUE(RIGHT($A31,2))+1,1),Expense_Input!$H$4:$H$500,"Property Expense") -> 0 | M31: =SUMIFS(Expense_Input!$D$4:$D$500,Expense_Input!$B$4:$B$500,">="&DATE(VALUE(LEFT($A31,4)),VALUE(RIGHT($A31,2)),1),Expense_Input!$B$4:$B$500,"<"&DATE(VALUE(LEFT($A31,4)),VALUE(RIGHT($A31,2))+1,1),Expense_Input!$H$4:$H$500,"Investment Transfer") -> 0 | N31: =SUMIFS(Expense_Input!$D$4:$D$500,Expense_Input!$B$4:$B$500,">="&DATE(VALUE(LEFT($A31,4)),VALUE(RIGHT($A31,2)),1),Expense_Input!$B$4:$B$500,"<"&DATE(VALUE(LEFT($A31,4)),VALUE(RIGHT($A31,2))+1,1),Expense_Input!$H$4:$H$500,"Internal Transfer") -> 0 | O31: =SUMIFS(Sales_Tax_Detail!$S$4:$S$500,Sales_Tax_Detail!$C$4:$C$500,$A31) -> 0
A32: 2026-05 | B32: =SUMIFS(Income_Input!$D$4:$D$500,Income_Input!$B$4:$B$500,">="&DATE(VALUE(LEFT($A32,4)),VALUE(RIGHT($A32,2)),1),Income_Input!$B$4:$B$500,"<"&DATE(VALUE(LEFT($A32,4)),VALUE(RIGHT($A32,2))+1,1)) -> 0 | C32: =SUMIFS(Expense_Input!$D$4:$D$500,Expense_Input!$B$4:$B$500,">="&DATE(VALUE(LEFT($A32,4)),VALUE(RIGHT($A32,2)),1),Expense_Input!$B$4:$B$500,"<"&DATE(VALUE(LEFT($A32,4)),VALUE(RIGHT($A32,2))+1,1),Expense_Input!$H$4:$H$500,"Personal Expense") -> 0 | D32: =SUMIFS(Expense_Input!$D$4:$D$500,Expense_Input!$B$4:$B$500,">="&DATE(VALUE(LEFT($A32,4)),VALUE(RIGHT($A32,2)),1),Expense_Input!$B$4:$B$500,"<"&DATE(VALUE(LEFT($A32,4)),VALUE(RIGHT($A32,2))+1,1),Expense_Input!$H$4:$H$500,"Personal Expense",Expense_Input!$G$4:$G$500,"Essential") -> 0 | E32: =SUMIFS(Expense_Input!$D$4:$D$500,Expense_Input!$B$4:$B$500,">="&DATE(VALUE(LEFT($A32,4)),VALUE(RIGHT($A32,2)),1),Expense_Input!$B$4:$B$500,"<"&DATE(VALUE(LEFT($A32,4)),VALUE(RIGHT($A32,2))+1,1),Expense_Input!$H$4:$H$500,"Personal Expense",Expense_Input!$G$4:$G$500,"Discretionary") -> 0 | F32: =SUMIFS(Expense_Input!$D$4:$D$500,Expense_Input!$B$4:$B$500,">="&DATE(VALUE(LEFT($A32,4)),VALUE(RIGHT($A32,2)),1),Expense_Input!$B$4:$B$500,"<"&DATE(VALUE(LEFT($A32,4)),VALUE(RIGHT($A32,2))+1,1),Expense_Input!$H$4:$H$500,"Personal Expense",Expense_Input!$F$4:$F$500,"Fixed") -> 0 | G32: =SUMIFS(Expense_Input!$D$4:$D$500,Expense_Input!$B$4:$B$500,">="&DATE(VALUE(LEFT($A32,4)),VALUE(RIGHT($A32,2)),1),Expense_Input!$B$4:$B$500,"<"&DATE(VALUE(LEFT($A32,4)),VALUE(RIGHT($A32,2))+1,1),Expense_Input!$H$4:$H$500,"Personal Expense",Expense_Input!$F$4:$F$500,"Variable") -> 0 | H32: =SUMIFS(Expense_Input!$D$4:$D$500,Expense_Input!$B$4:$B$500,">="&DATE(VALUE(LEFT($A32,4)),VALUE(RIGHT($A32,2)),1),Expense_Input!$B$4:$B$500,"<"&DATE(VALUE(LEFT($A32,4)),VALUE(RIGHT($A32,2))+1,1),Expense_Input!$H$4:$H$500,"Personal Expense",Expense_Input!$F$4:$F$500,"One-time") -> 0 | I32: =SUMIFS(Expense_Input!$D$4:$D$500,Expense_Input!$B$4:$B$500,">="&DATE(VALUE(LEFT($A32,4)),VALUE(RIGHT($A32,2)),1),Expense_Input!$B$4:$B$500,"<"&DATE(VALUE(LEFT($A32,4)),VALUE(RIGHT($A32,2))+1,1),Expense_Input!$H$4:$H$500,"Personal Expense",Expense_Input!$E$4:$E$500,"Housing") -> 0 | J32: =B32-C32 -> 0 | K32: =IF(C32>0,1,0) -> 0 | L32: =SUMIFS(Expense_Input!$D$4:$D$500,Expense_Input!$B$4:$B$500,">="&DATE(VALUE(LEFT($A32,4)),VALUE(RIGHT($A32,2)),1),Expense_Input!$B$4:$B$500,"<"&DATE(VALUE(LEFT($A32,4)),VALUE(RIGHT($A32,2))+1,1),Expense_Input!$H$4:$H$500,"Property Expense") -> 0 | M32: =SUMIFS(Expense_Input!$D$4:$D$500,Expense_Input!$B$4:$B$500,">="&DATE(VALUE(LEFT($A32,4)),VALUE(RIGHT($A32,2)),1),Expense_Input!$B$4:$B$500,"<"&DATE(VALUE(LEFT($A32,4)),VALUE(RIGHT($A32,2))+1,1),Expense_Input!$H$4:$H$500,"Investment Transfer") -> 0 | N32: =SUMIFS(Expense_Input!$D$4:$D$500,Expense_Input!$B$4:$B$500,">="&DATE(VALUE(LEFT($A32,4)),VALUE(RIGHT($A32,2)),1),Expense_Input!$B$4:$B$500,"<"&DATE(VALUE(LEFT($A32,4)),VALUE(RIGHT($A32,2))+1,1),Expense_Input!$H$4:$H$500,"Internal Transfer") -> 0 | O32: =SUMIFS(Sales_Tax_Detail!$S$4:$S$500,Sales_Tax_Detail!$C$4:$C$500,$A32) -> 0
A33: 2026-06 | B33: =SUMIFS(Income_Input!$D$4:$D$500,Income_Input!$B$4:$B$500,">="&DATE(VALUE(LEFT($A33,4)),VALUE(RIGHT($A33,2)),1),Income_Input!$B$4:$B$500,"<"&DATE(VALUE(LEFT($A33,4)),VALUE(RIGHT($A33,2))+1,1)) -> 0 | C33: =SUMIFS(Expense_Input!$D$4:$D$500,Expense_Input!$B$4:$B$500,">="&DATE(VALUE(LEFT($A33,4)),VALUE(RIGHT($A33,2)),1),Expense_Input!$B$4:$B$500,"<"&DATE(VALUE(LEFT($A33,4)),VALUE(RIGHT($A33,2))+1,1),Expense_Input!$H$4:$H$500,"Personal Expense") -> 0 | D33: =SUMIFS(Expense_Input!$D$4:$D$500,Expense_Input!$B$4:$B$500,">="&DATE(VALUE(LEFT($A33,4)),VALUE(RIGHT($A33,2)),1),Expense_Input!$B$4:$B$500,"<"&DATE(VALUE(LEFT($A33,4)),VALUE(RIGHT($A33,2))+1,1),Expense_Input!$H$4:$H$500,"Personal Expense",Expense_Input!$G$4:$G$500,"Essential") -> 0 | E33: =SUMIFS(Expense_Input!$D$4:$D$500,Expense_Input!$B$4:$B$500,">="&DATE(VALUE(LEFT($A33,4)),VALUE(RIGHT($A33,2)),1),Expense_Input!$B$4:$B$500,"<"&DATE(VALUE(LEFT($A33,4)),VALUE(RIGHT($A33,2))+1,1),Expense_Input!$H$4:$H$500,"Personal Expense",Expense_Input!$G$4:$G$500,"Discretionary") -> 0 | F33: =SUMIFS(Expense_Input!$D$4:$D$500,Expense_Input!$B$4:$B$500,">="&DATE(VALUE(LEFT($A33,4)),VALUE(RIGHT($A33,2)),1),Expense_Input!$B$4:$B$500,"<"&DATE(VALUE(LEFT($A33,4)),VALUE(RIGHT($A33,2))+1,1),Expense_Input!$H$4:$H$500,"Personal Expense",Expense_Input!$F$4:$F$500,"Fixed") -> 0 | G33: =SUMIFS(Expense_Input!$D$4:$D$500,Expense_Input!$B$4:$B$500,">="&DATE(VALUE(LEFT($A33,4)),VALUE(RIGHT($A33,2)),1),Expense_Input!$B$4:$B$500,"<"&DATE(VALUE(LEFT($A33,4)),VALUE(RIGHT($A33,2))+1,1),Expense_Input!$H$4:$H$500,"Personal Expense",Expense_Input!$F$4:$F$500,"Variable") -> 0 | H33: =SUMIFS(Expense_Input!$D$4:$D$500,Expense_Input!$B$4:$B$500,">="&DATE(VALUE(LEFT($A33,4)),VALUE(RIGHT($A33,2)),1),Expense_Input!$B$4:$B$500,"<"&DATE(VALUE(LEFT($A33,4)),VALUE(RIGHT($A33,2))+1,1),Expense_Input!$H$4:$H$500,"Personal Expense",Expense_Input!$F$4:$F$500,"One-time") -> 0 | I33: =SUMIFS(Expense_Input!$D$4:$D$500,Expense_Input!$B$4:$B$500,">="&DATE(VALUE(LEFT($A33,4)),VALUE(RIGHT($A33,2)),1),Expense_Input!$B$4:$B$500,"<"&DATE(VALUE(LEFT($A33,4)),VALUE(RIGHT($A33,2))+1,1),Expense_Input!$H$4:$H$500,"Personal Expense",Expense_Input!$E$4:$E$500,"Housing") -> 0 | J33: =B33-C33 -> 0 | K33: =IF(C33>0,1,0) -> 0 | L33: =SUMIFS(Expense_Input!$D$4:$D$500,Expense_Input!$B$4:$B$500,">="&DATE(VALUE(LEFT($A33,4)),VALUE(RIGHT($A33,2)),1),Expense_Input!$B$4:$B$500,"<"&DATE(VALUE(LEFT($A33,4)),VALUE(RIGHT($A33,2))+1,1),Expense_Input!$H$4:$H$500,"Property Expense") -> 0 | M33: =SUMIFS(Expense_Input!$D$4:$D$500,Expense_Input!$B$4:$B$500,">="&DATE(VALUE(LEFT($A33,4)),VALUE(RIGHT($A33,2)),1),Expense_Input!$B$4:$B$500,"<"&DATE(VALUE(LEFT($A33,4)),VALUE(RIGHT($A33,2))+1,1),Expense_Input!$H$4:$H$500,"Investment Transfer") -> 0 | N33: =SUMIFS(Expense_Input!$D$4:$D$500,Expense_Input!$B$4:$B$500,">="&DATE(VALUE(LEFT($A33,4)),VALUE(RIGHT($A33,2)),1),Expense_Input!$B$4:$B$500,"<"&DATE(VALUE(LEFT($A33,4)),VALUE(RIGHT($A33,2))+1,1),Expense_Input!$H$4:$H$500,"Internal Transfer") -> 0 | O33: =SUMIFS(Sales_Tax_Detail!$S$4:$S$500,Sales_Tax_Detail!$C$4:$C$500,$A33) -> 0
A34: 2026-07 | B34: =SUMIFS(Income_Input!$D$4:$D$500,Income_Input!$B$4:$B$500,">="&DATE(VALUE(LEFT($A34,4)),VALUE(RIGHT($A34,2)),1),Income_Input!$B$4:$B$500,"<"&DATE(VALUE(LEFT($A34,4)),VALUE(RIGHT($A34,2))+1,1)) -> 0 | C34: =SUMIFS(Expense_Input!$D$4:$D$500,Expense_Input!$B$4:$B$500,">="&DATE(VALUE(LEFT($A34,4)),VALUE(RIGHT($A34,2)),1),Expense_Input!$B$4:$B$500,"<"&DATE(VALUE(LEFT($A34,4)),VALUE(RIGHT($A34,2))+1,1),Expense_Input!$H$4:$H$500,"Personal Expense") -> 0 | D34: =SUMIFS(Expense_Input!$D$4:$D$500,Expense_Input!$B$4:$B$500,">="&DATE(VALUE(LEFT($A34,4)),VALUE(RIGHT($A34,2)),1),Expense_Input!$B$4:$B$500,"<"&DATE(VALUE(LEFT($A34,4)),VALUE(RIGHT($A34,2))+1,1),Expense_Input!$H$4:$H$500,"Personal Expense",Expense_Input!$G$4:$G$500,"Essential") -> 0 | E34: =SUMIFS(Expense_Input!$D$4:$D$500,Expense_Input!$B$4:$B$500,">="&DATE(VALUE(LEFT($A34,4)),VALUE(RIGHT($A34,2)),1),Expense_Input!$B$4:$B$500,"<"&DATE(VALUE(LEFT($A34,4)),VALUE(RIGHT($A34,2))+1,1),Expense_Input!$H$4:$H$500,"Personal Expense",Expense_Input!$G$4:$G$500,"Discretionary") -> 0 | F34: =SUMIFS(Expense_Input!$D$4:$D$500,Expense_Input!$B$4:$B$500,">="&DATE(VALUE(LEFT($A34,4)),VALUE(RIGHT($A34,2)),1),Expense_Input!$B$4:$B$500,"<"&DATE(VALUE(LEFT($A34,4)),VALUE(RIGHT($A34,2))+1,1),Expense_Input!$H$4:$H$500,"Personal Expense",Expense_Input!$F$4:$F$500,"Fixed") -> 0 | G34: =SUMIFS(Expense_Input!$D$4:$D$500,Expense_Input!$B$4:$B$500,">="&DATE(VALUE(LEFT($A34,4)),VALUE(RIGHT($A34,2)),1),Expense_Input!$B$4:$B$500,"<"&DATE(VALUE(LEFT($A34,4)),VALUE(RIGHT($A34,2))+1,1),Expense_Input!$H$4:$H$500,"Personal Expense",Expense_Input!$F$4:$F$500,"Variable") -> 0 | H34: =SUMIFS(Expense_Input!$D$4:$D$500,Expense_Input!$B$4:$B$500,">="&DATE(VALUE(LEFT($A34,4)),VALUE(RIGHT($A34,2)),1),Expense_Input!$B$4:$B$500,"<"&DATE(VALUE(LEFT($A34,4)),VALUE(RIGHT($A34,2))+1,1),Expense_Input!$H$4:$H$500,"Personal Expense",Expense_Input!$F$4:$F$500,"One-time") -> 0 | I34: =SUMIFS(Expense_Input!$D$4:$D$500,Expense_Input!$B$4:$B$500,">="&DATE(VALUE(LEFT($A34,4)),VALUE(RIGHT($A34,2)),1),Expense_Input!$B$4:$B$500,"<"&DATE(VALUE(LEFT($A34,4)),VALUE(RIGHT($A34,2))+1,1),Expense_Input!$H$4:$H$500,"Personal Expense",Expense_Input!$E$4:$E$500,"Housing") -> 0 | J34: =B34-C34 -> 0 | K34: =IF(C34>0,1,0) -> 0 | L34: =SUMIFS(Expense_Input!$D$4:$D$500,Expense_Input!$B$4:$B$500,">="&DATE(VALUE(LEFT($A34,4)),VALUE(RIGHT($A34,2)),1),Expense_Input!$B$4:$B$500,"<"&DATE(VALUE(LEFT($A34,4)),VALUE(RIGHT($A34,2))+1,1),Expense_Input!$H$4:$H$500,"Property Expense") -> 0 | M34: =SUMIFS(Expense_Input!$D$4:$D$500,Expense_Input!$B$4:$B$500,">="&DATE(VALUE(LEFT($A34,4)),VALUE(RIGHT($A34,2)),1),Expense_Input!$B$4:$B$500,"<"&DATE(VALUE(LEFT($A34,4)),VALUE(RIGHT($A34,2))+1,1),Expense_Input!$H$4:$H$500,"Investment Transfer") -> 0 | N34: =SUMIFS(Expense_Input!$D$4:$D$500,Expense_Input!$B$4:$B$500,">="&DATE(VALUE(LEFT($A34,4)),VALUE(RIGHT($A34,2)),1),Expense_Input!$B$4:$B$500,"<"&DATE(VALUE(LEFT($A34,4)),VALUE(RIGHT($A34,2))+1,1),Expense_Input!$H$4:$H$500,"Internal Transfer") -> 0 | O34: =SUMIFS(Sales_Tax_Detail!$S$4:$S$500,Sales_Tax_Detail!$C$4:$C$500,$A34) -> 0
A35: 2026-08 | B35: =SUMIFS(Income_Input!$D$4:$D$500,Income_Input!$B$4:$B$500,">="&DATE(VALUE(LEFT($A35,4)),VALUE(RIGHT($A35,2)),1),Income_Input!$B$4:$B$500,"<"&DATE(VALUE(LEFT($A35,4)),VALUE(RIGHT($A35,2))+1,1)) -> 0 | C35: =SUMIFS(Expense_Input!$D$4:$D$500,Expense_Input!$B$4:$B$500,">="&DATE(VALUE(LEFT($A35,4)),VALUE(RIGHT($A35,2)),1),Expense_Input!$B$4:$B$500,"<"&DATE(VALUE(LEFT($A35,4)),VALUE(RIGHT($A35,2))+1,1),Expense_Input!$H$4:$H$500,"Personal Expense") -> 0 | D35: =SUMIFS(Expense_Input!$D$4:$D$500,Expense_Input!$B$4:$B$500,">="&DATE(VALUE(LEFT($A35,4)),VALUE(RIGHT($A35,2)),1),Expense_Input!$B$4:$B$500,"<"&DATE(VALUE(LEFT($A35,4)),VALUE(RIGHT($A35,2))+1,1),Expense_Input!$H$4:$H$500,"Personal Expense",Expense_Input!$G$4:$G$500,"Essential") -> 0 | E35: =SUMIFS(Expense_Input!$D$4:$D$500,Expense_Input!$B$4:$B$500,">="&DATE(VALUE(LEFT($A35,4)),VALUE(RIGHT($A35,2)),1),Expense_Input!$B$4:$B$500,"<"&DATE(VALUE(LEFT($A35,4)),VALUE(RIGHT($A35,2))+1,1),Expense_Input!$H$4:$H$500,"Personal Expense",Expense_Input!$G$4:$G$500,"Discretionary") -> 0 | F35: =SUMIFS(Expense_Input!$D$4:$D$500,Expense_Input!$B$4:$B$500,">="&DATE(VALUE(LEFT($A35,4)),VALUE(RIGHT($A35,2)),1),Expense_Input!$B$4:$B$500,"<"&DATE(VALUE(LEFT($A35,4)),VALUE(RIGHT($A35,2))+1,1),Expense_Input!$H$4:$H$500,"Personal Expense",Expense_Input!$F$4:$F$500,"Fixed") -> 0 | G35: =SUMIFS(Expense_Input!$D$4:$D$500,Expense_Input!$B$4:$B$500,">="&DATE(VALUE(LEFT($A35,4)),VALUE(RIGHT($A35,2)),1),Expense_Input!$B$4:$B$500,"<"&DATE(VALUE(LEFT($A35,4)),VALUE(RIGHT($A35,2))+1,1),Expense_Input!$H$4:$H$500,"Personal Expense",Expense_Input!$F$4:$F$500,"Variable") -> 0 | H35: =SUMIFS(Expense_Input!$D$4:$D$500,Expense_Input!$B$4:$B$500,">="&DATE(VALUE(LEFT($A35,4)),VALUE(RIGHT($A35,2)),1),Expense_Input!$B$4:$B$500,"<"&DATE(VALUE(LEFT($A35,4)),VALUE(RIGHT($A35,2))+1,1),Expense_Input!$H$4:$H$500,"Personal Expense",Expense_Input!$F$4:$F$500,"One-time") -> 0 | I35: =SUMIFS(Expense_Input!$D$4:$D$500,Expense_Input!$B$4:$B$500,">="&DATE(VALUE(LEFT($A35,4)),VALUE(RIGHT($A35,2)),1),Expense_Input!$B$4:$B$500,"<"&DATE(VALUE(LEFT($A35,4)),VALUE(RIGHT($A35,2))+1,1),Expense_Input!$H$4:$H$500,"Personal Expense",Expense_Input!$E$4:$E$500,"Housing") -> 0 | J35: =B35-C35 -> 0 | K35: =IF(C35>0,1,0) -> 0 | L35: =SUMIFS(Expense_Input!$D$4:$D$500,Expense_Input!$B$4:$B$500,">="&DATE(VALUE(LEFT($A35,4)),VALUE(RIGHT($A35,2)),1),Expense_Input!$B$4:$B$500,"<"&DATE(VALUE(LEFT($A35,4)),VALUE(RIGHT($A35,2))+1,1),Expense_Input!$H$4:$H$500,"Property Expense") -> 0 | M35: =SUMIFS(Expense_Input!$D$4:$D$500,Expense_Input!$B$4:$B$500,">="&DATE(VALUE(LEFT($A35,4)),VALUE(RIGHT($A35,2)),1),Expense_Input!$B$4:$B$500,"<"&DATE(VALUE(LEFT($A35,4)),VALUE(RIGHT($A35,2))+1,1),Expense_Input!$H$4:$H$500,"Investment Transfer") -> 0 | N35: =SUMIFS(Expense_Input!$D$4:$D$500,Expense_Input!$B$4:$B$500,">="&DATE(VALUE(LEFT($A35,4)),VALUE(RIGHT($A35,2)),1),Expense_Input!$B$4:$B$500,"<"&DATE(VALUE(LEFT($A35,4)),VALUE(RIGHT($A35,2))+1,1),Expense_Input!$H$4:$H$500,"Internal Transfer") -> 0 | O35: =SUMIFS(Sales_Tax_Detail!$S$4:$S$500,Sales_Tax_Detail!$C$4:$C$500,$A35) -> 0
A36: 2026-09 | B36: =SUMIFS(Income_Input!$D$4:$D$500,Income_Input!$B$4:$B$500,">="&DATE(VALUE(LEFT($A36,4)),VALUE(RIGHT($A36,2)),1),Income_Input!$B$4:$B$500,"<"&DATE(VALUE(LEFT($A36,4)),VALUE(RIGHT($A36,2))+1,1)) -> 0 | C36: =SUMIFS(Expense_Input!$D$4:$D$500,Expense_Input!$B$4:$B$500,">="&DATE(VALUE(LEFT($A36,4)),VALUE(RIGHT($A36,2)),1),Expense_Input!$B$4:$B$500,"<"&DATE(VALUE(LEFT($A36,4)),VALUE(RIGHT($A36,2))+1,1),Expense_Input!$H$4:$H$500,"Personal Expense") -> 0 | D36: =SUMIFS(Expense_Input!$D$4:$D$500,Expense_Input!$B$4:$B$500,">="&DATE(VALUE(LEFT($A36,4)),VALUE(RIGHT($A36,2)),1),Expense_Input!$B$4:$B$500,"<"&DATE(VALUE(LEFT($A36,4)),VALUE(RIGHT($A36,2))+1,1),Expense_Input!$H$4:$H$500,"Personal Expense",Expense_Input!$G$4:$G$500,"Essential") -> 0 | E36: =SUMIFS(Expense_Input!$D$4:$D$500,Expense_Input!$B$4:$B$500,">="&DATE(VALUE(LEFT($A36,4)),VALUE(RIGHT($A36,2)),1),Expense_Input!$B$4:$B$500,"<"&DATE(VALUE(LEFT($A36,4)),VALUE(RIGHT($A36,2))+1,1),Expense_Input!$H$4:$H$500,"Personal Expense",Expense_Input!$G$4:$G$500,"Discretionary") -> 0 | F36: =SUMIFS(Expense_Input!$D$4:$D$500,Expense_Input!$B$4:$B$500,">="&DATE(VALUE(LEFT($A36,4)),VALUE(RIGHT($A36,2)),1),Expense_Input!$B$4:$B$500,"<"&DATE(VALUE(LEFT($A36,4)),VALUE(RIGHT($A36,2))+1,1),Expense_Input!$H$4:$H$500,"Personal Expense",Expense_Input!$F$4:$F$500,"Fixed") -> 0 | G36: =SUMIFS(Expense_Input!$D$4:$D$500,Expense_Input!$B$4:$B$500,">="&DATE(VALUE(LEFT($A36,4)),VALUE(RIGHT($A36,2)),1),Expense_Input!$B$4:$B$500,"<"&DATE(VALUE(LEFT($A36,4)),VALUE(RIGHT($A36,2))+1,1),Expense_Input!$H$4:$H$500,"Personal Expense",Expense_Input!$F$4:$F$500,"Variable") -> 0 | H36: =SUMIFS(Expense_Input!$D$4:$D$500,Expense_Input!$B$4:$B$500,">="&DATE(VALUE(LEFT($A36,4)),VALUE(RIGHT($A36,2)),1),Expense_Input!$B$4:$B$500,"<"&DATE(VALUE(LEFT($A36,4)),VALUE(RIGHT($A36,2))+1,1),Expense_Input!$H$4:$H$500,"Personal Expense",Expense_Input!$F$4:$F$500,"One-time") -> 0 | I36: =SUMIFS(Expense_Input!$D$4:$D$500,Expense_Input!$B$4:$B$500,">="&DATE(VALUE(LEFT($A36,4)),VALUE(RIGHT($A36,2)),1),Expense_Input!$B$4:$B$500,"<"&DATE(VALUE(LEFT($A36,4)),VALUE(RIGHT($A36,2))+1,1),Expense_Input!$H$4:$H$500,"Personal Expense",Expense_Input!$E$4:$E$500,"Housing") -> 0 | J36: =B36-C36 -> 0 | K36: =IF(C36>0,1,0) -> 0 | L36: =SUMIFS(Expense_Input!$D$4:$D$500,Expense_Input!$B$4:$B$500,">="&DATE(VALUE(LEFT($A36,4)),VALUE(RIGHT($A36,2)),1),Expense_Input!$B$4:$B$500,"<"&DATE(VALUE(LEFT($A36,4)),VALUE(RIGHT($A36,2))+1,1),Expense_Input!$H$4:$H$500,"Property Expense") -> 0 | M36: =SUMIFS(Expense_Input!$D$4:$D$500,Expense_Input!$B$4:$B$500,">="&DATE(VALUE(LEFT($A36,4)),VALUE(RIGHT($A36,2)),1),Expense_Input!$B$4:$B$500,"<"&DATE(VALUE(LEFT($A36,4)),VALUE(RIGHT($A36,2))+1,1),Expense_Input!$H$4:$H$500,"Investment Transfer") -> 0 | N36: =SUMIFS(Expense_Input!$D$4:$D$500,Expense_Input!$B$4:$B$500,">="&DATE(VALUE(LEFT($A36,4)),VALUE(RIGHT($A36,2)),1),Expense_Input!$B$4:$B$500,"<"&DATE(VALUE(LEFT($A36,4)),VALUE(RIGHT($A36,2))+1,1),Expense_Input!$H$4:$H$500,"Internal Transfer") -> 0 | O36: =SUMIFS(Sales_Tax_Detail!$S$4:$S$500,Sales_Tax_Detail!$C$4:$C$500,$A36) -> 0
A37: 2026-10 | B37: =SUMIFS(Income_Input!$D$4:$D$500,Income_Input!$B$4:$B$500,">="&DATE(VALUE(LEFT($A37,4)),VALUE(RIGHT($A37,2)),1),Income_Input!$B$4:$B$500,"<"&DATE(VALUE(LEFT($A37,4)),VALUE(RIGHT($A37,2))+1,1)) -> 0 | C37: =SUMIFS(Expense_Input!$D$4:$D$500,Expense_Input!$B$4:$B$500,">="&DATE(VALUE(LEFT($A37,4)),VALUE(RIGHT($A37,2)),1),Expense_Input!$B$4:$B$500,"<"&DATE(VALUE(LEFT($A37,4)),VALUE(RIGHT($A37,2))+1,1),Expense_Input!$H$4:$H$500,"Personal Expense") -> 0 | D37: =SUMIFS(Expense_Input!$D$4:$D$500,Expense_Input!$B$4:$B$500,">="&DATE(VALUE(LEFT($A37,4)),VALUE(RIGHT($A37,2)),1),Expense_Input!$B$4:$B$500,"<"&DATE(VALUE(LEFT($A37,4)),VALUE(RIGHT($A37,2))+1,1),Expense_Input!$H$4:$H$500,"Personal Expense",Expense_Input!$G$4:$G$500,"Essential") -> 0 | E37: =SUMIFS(Expense_Input!$D$4:$D$500,Expense_Input!$B$4:$B$500,">="&DATE(VALUE(LEFT($A37,4)),VALUE(RIGHT($A37,2)),1),Expense_Input!$B$4:$B$500,"<"&DATE(VALUE(LEFT($A37,4)),VALUE(RIGHT($A37,2))+1,1),Expense_Input!$H$4:$H$500,"Personal Expense",Expense_Input!$G$4:$G$500,"Discretionary") -> 0 | F37: =SUMIFS(Expense_Input!$D$4:$D$500,Expense_Input!$B$4:$B$500,">="&DATE(VALUE(LEFT($A37,4)),VALUE(RIGHT($A37,2)),1),Expense_Input!$B$4:$B$500,"<"&DATE(VALUE(LEFT($A37,4)),VALUE(RIGHT($A37,2))+1,1),Expense_Input!$H$4:$H$500,"Personal Expense",Expense_Input!$F$4:$F$500,"Fixed") -> 0 | G37: =SUMIFS(Expense_Input!$D$4:$D$500,Expense_Input!$B$4:$B$500,">="&DATE(VALUE(LEFT($A37,4)),VALUE(RIGHT($A37,2)),1),Expense_Input!$B$4:$B$500,"<"&DATE(VALUE(LEFT($A37,4)),VALUE(RIGHT($A37,2))+1,1),Expense_Input!$H$4:$H$500,"Personal Expense",Expense_Input!$F$4:$F$500,"Variable") -> 0 | H37: =SUMIFS(Expense_Input!$D$4:$D$500,Expense_Input!$B$4:$B$500,">="&DATE(VALUE(LEFT($A37,4)),VALUE(RIGHT($A37,2)),1),Expense_Input!$B$4:$B$500,"<"&DATE(VALUE(LEFT($A37,4)),VALUE(RIGHT($A37,2))+1,1),Expense_Input!$H$4:$H$500,"Personal Expense",Expense_Input!$F$4:$F$500,"One-time") -> 0 | I37: =SUMIFS(Expense_Input!$D$4:$D$500,Expense_Input!$B$4:$B$500,">="&DATE(VALUE(LEFT($A37,4)),VALUE(RIGHT($A37,2)),1),Expense_Input!$B$4:$B$500,"<"&DATE(VALUE(LEFT($A37,4)),VALUE(RIGHT($A37,2))+1,1),Expense_Input!$H$4:$H$500,"Personal Expense",Expense_Input!$E$4:$E$500,"Housing") -> 0 | J37: =B37-C37 -> 0 | K37: =IF(C37>0,1,0) -> 0 | L37: =SUMIFS(Expense_Input!$D$4:$D$500,Expense_Input!$B$4:$B$500,">="&DATE(VALUE(LEFT($A37,4)),VALUE(RIGHT($A37,2)),1),Expense_Input!$B$4:$B$500,"<"&DATE(VALUE(LEFT($A37,4)),VALUE(RIGHT($A37,2))+1,1),Expense_Input!$H$4:$H$500,"Property Expense") -> 0 | M37: =SUMIFS(Expense_Input!$D$4:$D$500,Expense_Input!$B$4:$B$500,">="&DATE(VALUE(LEFT($A37,4)),VALUE(RIGHT($A37,2)),1),Expense_Input!$B$4:$B$500,"<"&DATE(VALUE(LEFT($A37,4)),VALUE(RIGHT($A37,2))+1,1),Expense_Input!$H$4:$H$500,"Investment Transfer") -> 0 | N37: =SUMIFS(Expense_Input!$D$4:$D$500,Expense_Input!$B$4:$B$500,">="&DATE(VALUE(LEFT($A37,4)),VALUE(RIGHT($A37,2)),1),Expense_Input!$B$4:$B$500,"<"&DATE(VALUE(LEFT($A37,4)),VALUE(RIGHT($A37,2))+1,1),Expense_Input!$H$4:$H$500,"Internal Transfer") -> 0 | O37: =SUMIFS(Sales_Tax_Detail!$S$4:$S$500,Sales_Tax_Detail!$C$4:$C$500,$A37) -> 0
A38: 2026-11 | B38: =SUMIFS(Income_Input!$D$4:$D$500,Income_Input!$B$4:$B$500,">="&DATE(VALUE(LEFT($A38,4)),VALUE(RIGHT($A38,2)),1),Income_Input!$B$4:$B$500,"<"&DATE(VALUE(LEFT($A38,4)),VALUE(RIGHT($A38,2))+1,1)) -> 0 | C38: =SUMIFS(Expense_Input!$D$4:$D$500,Expense_Input!$B$4:$B$500,">="&DATE(VALUE(LEFT($A38,4)),VALUE(RIGHT($A38,2)),1),Expense_Input!$B$4:$B$500,"<"&DATE(VALUE(LEFT($A38,4)),VALUE(RIGHT($A38,2))+1,1),Expense_Input!$H$4:$H$500,"Personal Expense") -> 0 | D38: =SUMIFS(Expense_Input!$D$4:$D$500,Expense_Input!$B$4:$B$500,">="&DATE(VALUE(LEFT($A38,4)),VALUE(RIGHT($A38,2)),1),Expense_Input!$B$4:$B$500,"<"&DATE(VALUE(LEFT($A38,4)),VALUE(RIGHT($A38,2))+1,1),Expense_Input!$H$4:$H$500,"Personal Expense",Expense_Input!$G$4:$G$500,"Essential") -> 0 | E38: =SUMIFS(Expense_Input!$D$4:$D$500,Expense_Input!$B$4:$B$500,">="&DATE(VALUE(LEFT($A38,4)),VALUE(RIGHT($A38,2)),1),Expense_Input!$B$4:$B$500,"<"&DATE(VALUE(LEFT($A38,4)),VALUE(RIGHT($A38,2))+1,1),Expense_Input!$H$4:$H$500,"Personal Expense",Expense_Input!$G$4:$G$500,"Discretionary") -> 0 | F38: =SUMIFS(Expense_Input!$D$4:$D$500,Expense_Input!$B$4:$B$500,">="&DATE(VALUE(LEFT($A38,4)),VALUE(RIGHT($A38,2)),1),Expense_Input!$B$4:$B$500,"<"&DATE(VALUE(LEFT($A38,4)),VALUE(RIGHT($A38,2))+1,1),Expense_Input!$H$4:$H$500,"Personal Expense",Expense_Input!$F$4:$F$500,"Fixed") -> 0 | G38: =SUMIFS(Expense_Input!$D$4:$D$500,Expense_Input!$B$4:$B$500,">="&DATE(VALUE(LEFT($A38,4)),VALUE(RIGHT($A38,2)),1),Expense_Input!$B$4:$B$500,"<"&DATE(VALUE(LEFT($A38,4)),VALUE(RIGHT($A38,2))+1,1),Expense_Input!$H$4:$H$500,"Personal Expense",Expense_Input!$F$4:$F$500,"Variable") -> 0 | H38: =SUMIFS(Expense_Input!$D$4:$D$500,Expense_Input!$B$4:$B$500,">="&DATE(VALUE(LEFT($A38,4)),VALUE(RIGHT($A38,2)),1),Expense_Input!$B$4:$B$500,"<"&DATE(VALUE(LEFT($A38,4)),VALUE(RIGHT($A38,2))+1,1),Expense_Input!$H$4:$H$500,"Personal Expense",Expense_Input!$F$4:$F$500,"One-time") -> 0 | I38: =SUMIFS(Expense_Input!$D$4:$D$500,Expense_Input!$B$4:$B$500,">="&DATE(VALUE(LEFT($A38,4)),VALUE(RIGHT($A38,2)),1),Expense_Input!$B$4:$B$500,"<"&DATE(VALUE(LEFT($A38,4)),VALUE(RIGHT($A38,2))+1,1),Expense_Input!$H$4:$H$500,"Personal Expense",Expense_Input!$E$4:$E$500,"Housing") -> 0 | J38: =B38-C38 -> 0 | K38: =IF(C38>0,1,0) -> 0 | L38: =SUMIFS(Expense_Input!$D$4:$D$500,Expense_Input!$B$4:$B$500,">="&DATE(VALUE(LEFT($A38,4)),VALUE(RIGHT($A38,2)),1),Expense_Input!$B$4:$B$500,"<"&DATE(VALUE(LEFT($A38,4)),VALUE(RIGHT($A38,2))+1,1),Expense_Input!$H$4:$H$500,"Property Expense") -> 0 | M38: =SUMIFS(Expense_Input!$D$4:$D$500,Expense_Input!$B$4:$B$500,">="&DATE(VALUE(LEFT($A38,4)),VALUE(RIGHT($A38,2)),1),Expense_Input!$B$4:$B$500,"<"&DATE(VALUE(LEFT($A38,4)),VALUE(RIGHT($A38,2))+1,1),Expense_Input!$H$4:$H$500,"Investment Transfer") -> 0 | N38: =SUMIFS(Expense_Input!$D$4:$D$500,Expense_Input!$B$4:$B$500,">="&DATE(VALUE(LEFT($A38,4)),VALUE(RIGHT($A38,2)),1),Expense_Input!$B$4:$B$500,"<"&DATE(VALUE(LEFT($A38,4)),VALUE(RIGHT($A38,2))+1,1),Expense_Input!$H$4:$H$500,"Internal Transfer") -> 0 | O38: =SUMIFS(Sales_Tax_Detail!$S$4:$S$500,Sales_Tax_Detail!$C$4:$C$500,$A38) -> 0
A39: 2026-12 | B39: =SUMIFS(Income_Input!$D$4:$D$500,Income_Input!$B$4:$B$500,">="&DATE(VALUE(LEFT($A39,4)),VALUE(RIGHT($A39,2)),1),Income_Input!$B$4:$B$500,"<"&DATE(VALUE(LEFT($A39,4)),VALUE(RIGHT($A39,2))+1,1)) -> 0 | C39: =SUMIFS(Expense_Input!$D$4:$D$500,Expense_Input!$B$4:$B$500,">="&DATE(VALUE(LEFT($A39,4)),VALUE(RIGHT($A39,2)),1),Expense_Input!$B$4:$B$500,"<"&DATE(VALUE(LEFT($A39,4)),VALUE(RIGHT($A39,2))+1,1),Expense_Input!$H$4:$H$500,"Personal Expense") -> 0 | D39: =SUMIFS(Expense_Input!$D$4:$D$500,Expense_Input!$B$4:$B$500,">="&DATE(VALUE(LEFT($A39,4)),VALUE(RIGHT($A39,2)),1),Expense_Input!$B$4:$B$500,"<"&DATE(VALUE(LEFT($A39,4)),VALUE(RIGHT($A39,2))+1,1),Expense_Input!$H$4:$H$500,"Personal Expense",Expense_Input!$G$4:$G$500,"Essential") -> 0 | E39: =SUMIFS(Expense_Input!$D$4:$D$500,Expense_Input!$B$4:$B$500,">="&DATE(VALUE(LEFT($A39,4)),VALUE(RIGHT($A39,2)),1),Expense_Input!$B$4:$B$500,"<"&DATE(VALUE(LEFT($A39,4)),VALUE(RIGHT($A39,2))+1,1),Expense_Input!$H$4:$H$500,"Personal Expense",Expense_Input!$G$4:$G$500,"Discretionary") -> 0 | F39: =SUMIFS(Expense_Input!$D$4:$D$500,Expense_Input!$B$4:$B$500,">="&DATE(VALUE(LEFT($A39,4)),VALUE(RIGHT($A39,2)),1),Expense_Input!$B$4:$B$500,"<"&DATE(VALUE(LEFT($A39,4)),VALUE(RIGHT($A39,2))+1,1),Expense_Input!$H$4:$H$500,"Personal Expense",Expense_Input!$F$4:$F$500,"Fixed") -> 0 | G39: =SUMIFS(Expense_Input!$D$4:$D$500,Expense_Input!$B$4:$B$500,">="&DATE(VALUE(LEFT($A39,4)),VALUE(RIGHT($A39,2)),1),Expense_Input!$B$4:$B$500,"<"&DATE(VALUE(LEFT($A39,4)),VALUE(RIGHT($A39,2))+1,1),Expense_Input!$H$4:$H$500,"Personal Expense",Expense_Input!$F$4:$F$500,"Variable") -> 0 | H39: =SUMIFS(Expense_Input!$D$4:$D$500,Expense_Input!$B$4:$B$500,">="&DATE(VALUE(LEFT($A39,4)),VALUE(RIGHT($A39,2)),1),Expense_Input!$B$4:$B$500,"<"&DATE(VALUE(LEFT($A39,4)),VALUE(RIGHT($A39,2))+1,1),Expense_Input!$H$4:$H$500,"Personal Expense",Expense_Input!$F$4:$F$500,"One-time") -> 0 | I39: =SUMIFS(Expense_Input!$D$4:$D$500,Expense_Input!$B$4:$B$500,">="&DATE(VALUE(LEFT($A39,4)),VALUE(RIGHT($A39,2)),1),Expense_Input!$B$4:$B$500,"<"&DATE(VALUE(LEFT($A39,4)),VALUE(RIGHT($A39,2))+1,1),Expense_Input!$H$4:$H$500,"Personal Expense",Expense_Input!$E$4:$E$500,"Housing") -> 0 | J39: =B39-C39 -> 0 | K39: =IF(C39>0,1,0) -> 0 | L39: =SUMIFS(Expense_Input!$D$4:$D$500,Expense_Input!$B$4:$B$500,">="&DATE(VALUE(LEFT($A39,4)),VALUE(RIGHT($A39,2)),1),Expense_Input!$B$4:$B$500,"<"&DATE(VALUE(LEFT($A39,4)),VALUE(RIGHT($A39,2))+1,1),Expense_Input!$H$4:$H$500,"Property Expense") -> 0 | M39: =SUMIFS(Expense_Input!$D$4:$D$500,Expense_Input!$B$4:$B$500,">="&DATE(VALUE(LEFT($A39,4)),VALUE(RIGHT($A39,2)),1),Expense_Input!$B$4:$B$500,"<"&DATE(VALUE(LEFT($A39,4)),VALUE(RIGHT($A39,2))+1,1),Expense_Input!$H$4:$H$500,"Investment Transfer") -> 0 | N39: =SUMIFS(Expense_Input!$D$4:$D$500,Expense_Input!$B$4:$B$500,">="&DATE(VALUE(LEFT($A39,4)),VALUE(RIGHT($A39,2)),1),Expense_Input!$B$4:$B$500,"<"&DATE(VALUE(LEFT($A39,4)),VALUE(RIGHT($A39,2))+1,1),Expense_Input!$H$4:$H$500,"Internal Transfer") -> 0 | O39: =SUMIFS(Sales_Tax_Detail!$S$4:$S$500,Sales_Tax_Detail!$C$4:$C$500,$A39) -> 0
A44: Main Category | B44: 2026-01 | C44: 2026-02 | D44: 2026-03 | E44: 2026-04 | F44: 2026-05 | G44: 2026-06 | H44: 2026-07 | I44: 2026-08 | J44: 2026-09 | K44: 2026-10 | L44: 2026-11 | M44: 2026-12 | N44: Monthly Avg | O44: Annualized | P44: Share of Personal Monthly Expense
A45: Housing | B45: =SUMIFS(Expense_Input!$D$4:$D$500,Expense_Input!$B$4:$B$500,">="&DATE(VALUE(LEFT(B$44,4)),VALUE(RIGHT(B$44,2)),1),Expense_Input!$B$4:$B$500,"<"&DATE(VALUE(LEFT(B$44,4)),VALUE(RIGHT(B$44,2))+1,1),Expense_Input!$H$4:$H$500,"Personal Expense",Expense_Input!$E$4:$E$500,$A45) -> 3000 | C45: =SUMIFS(Expense_Input!$D$4:$D$500,Expense_Input!$B$4:$B$500,">="&DATE(VALUE(LEFT(C$44,4)),VALUE(RIGHT(C$44,2)),1),Expense_Input!$B$4:$B$500,"<"&DATE(VALUE(LEFT(C$44,4)),VALUE(RIGHT(C$44,2))+1,1),Expense_Input!$H$4:$H$500,"Personal Expense",Expense_Input!$E$4:$E$500,$A45) -> 3000 | D45: =SUMIFS(Expense_Input!$D$4:$D$500,Expense_Input!$B$4:$B$500,">="&DATE(VALUE(LEFT(D$44,4)),VALUE(RIGHT(D$44,2)),1),Expense_Input!$B$4:$B$500,"<"&DATE(VALUE(LEFT(D$44,4)),VALUE(RIGHT(D$44,2))+1,1),Expense_Input!$H$4:$H$500,"Personal Expense",Expense_Input!$E$4:$E$500,$A45) -> 0 | E45: =SUMIFS(Expense_Input!$D$4:$D$500,Expense_Input!$B$4:$B$500,">="&DATE(VALUE(LEFT(E$44,4)),VALUE(RIGHT(E$44,2)),1),Expense_Input!$B$4:$B$500,"<"&DATE(VALUE(LEFT(E$44,4)),VALUE(RIGHT(E$44,2))+1,1),Expense_Input!$H$4:$H$500,"Personal Expense",Expense_Input!$E$4:$E$500,$A45) -> 0 | F45: =SUMIFS(Expense_Input!$D$4:$D$500,Expense_Input!$B$4:$B$500,">="&DATE(VALUE(LEFT(F$44,4)),VALUE(RIGHT(F$44,2)),1),Expense_Input!$B$4:$B$500,"<"&DATE(VALUE(LEFT(F$44,4)),VALUE(RIGHT(F$44,2))+1,1),Expense_Input!$H$4:$H$500,"Personal Expense",Expense_Input!$E$4:$E$500,$A45) -> 0 | G45: =SUMIFS(Expense_Input!$D$4:$D$500,Expense_Input!$B$4:$B$500,">="&DATE(VALUE(LEFT(G$44,4)),VALUE(RIGHT(G$44,2)),1),Expense_Input!$B$4:$B$500,"<"&DATE(VALUE(LEFT(G$44,4)),VALUE(RIGHT(G$44,2))+1,1),Expense_Input!$H$4:$H$500,"Personal Expense",Expense_Input!$E$4:$E$500,$A45) -> 0 | H45: =SUMIFS(Expense_Input!$D$4:$D$500,Expense_Input!$B$4:$B$500,">="&DATE(VALUE(LEFT(H$44,4)),VALUE(RIGHT(H$44,2)),1),Expense_Input!$B$4:$B$500,"<"&DATE(VALUE(LEFT(H$44,4)),VALUE(RIGHT(H$44,2))+1,1),Expense_Input!$H$4:$H$500,"Personal Expense",Expense_Input!$E$4:$E$500,$A45) -> 0 | I45: =SUMIFS(Expense_Input!$D$4:$D$500,Expense_Input!$B$4:$B$500,">="&DATE(VALUE(LEFT(I$44,4)),VALUE(RIGHT(I$44,2)),1),Expense_Input!$B$4:$B$500,"<"&DATE(VALUE(LEFT(I$44,4)),VALUE(RIGHT(I$44,2))+1,1),Expense_Input!$H$4:$H$500,"Personal Expense",Expense_Input!$E$4:$E$500,$A45) -> 0 | ... M45: =SUMIFS(Expense_Input!$D$4:$D$500,Expense_Input!$B$4:$B$500,">="&DATE(VALUE(LEFT(M$44,4)),VALUE(RIGHT(M$44,2)),1),Expense_Input!$B$4:$B$500,"<"&DATE(VALUE(LEFT(M$44,4)),VALUE(RIGHT(M$44,2))+1,1),Expense_Input!$H$4:$H$500,"Personal Expense",Expense_Input!$E$4:$E$500,$A45) -> 0 | N45: =IF($B$4=0,0,SUM(B45:M45)/$B$4) -> 3000 | O45: =N45*12 -> 36000 | P45: =IFERROR(N45/$B$7,0) -> 0.58252427
A46: Food & Dining | B46: =SUMIFS(Expense_Input!$D$4:$D$500,Expense_Input!$B$4:$B$500,">="&DATE(VALUE(LEFT(B$44,4)),VALUE(RIGHT(B$44,2)),1),Expense_Input!$B$4:$B$500,"<"&DATE(VALUE(LEFT(B$44,4)),VALUE(RIGHT(B$44,2))+1,1),Expense_Input!$H$4:$H$500,"Personal Expense",Expense_Input!$E$4:$E$500,$A46) -> 770 | C46: =SUMIFS(Expense_Input!$D$4:$D$500,Expense_Input!$B$4:$B$500,">="&DATE(VALUE(LEFT(C$44,4)),VALUE(RIGHT(C$44,2)),1),Expense_Input!$B$4:$B$500,"<"&DATE(VALUE(LEFT(C$44,4)),VALUE(RIGHT(C$44,2))+1,1),Expense_Input!$H$4:$H$500,"Personal Expense",Expense_Input!$E$4:$E$500,$A46) -> 870 | D46: =SUMIFS(Expense_Input!$D$4:$D$500,Expense_Input!$B$4:$B$500,">="&DATE(VALUE(LEFT(D$44,4)),VALUE(RIGHT(D$44,2)),1),Expense_Input!$B$4:$B$500,"<"&DATE(VALUE(LEFT(D$44,4)),VALUE(RIGHT(D$44,2))+1,1),Expense_Input!$H$4:$H$500,"Personal Expense",Expense_Input!$E$4:$E$500,$A46) -> 0 | E46: =SUMIFS(Expense_Input!$D$4:$D$500,Expense_Input!$B$4:$B$500,">="&DATE(VALUE(LEFT(E$44,4)),VALUE(RIGHT(E$44,2)),1),Expense_Input!$B$4:$B$500,"<"&DATE(VALUE(LEFT(E$44,4)),VALUE(RIGHT(E$44,2))+1,1),Expense_Input!$H$4:$H$500,"Personal Expense",Expense_Input!$E$4:$E$500,$A46) -> 0 | F46: =SUMIFS(Expense_Input!$D$4:$D$500,Expense_Input!$B$4:$B$500,">="&DATE(VALUE(LEFT(F$44,4)),VALUE(RIGHT(F$44,2)),1),Expense_Input!$B$4:$B$500,"<"&DATE(VALUE(LEFT(F$44,4)),VALUE(RIGHT(F$44,2))+1,1),Expense_Input!$H$4:$H$500,"Personal Expense",Expense_Input!$E$4:$E$500,$A46) -> 0 | G46: =SUMIFS(Expense_Input!$D$4:$D$500,Expense_Input!$B$4:$B$500,">="&DATE(VALUE(LEFT(G$44,4)),VALUE(RIGHT(G$44,2)),1),Expense_Input!$B$4:$B$500,"<"&DATE(VALUE(LEFT(G$44,4)),VALUE(RIGHT(G$44,2))+1,1),Expense_Input!$H$4:$H$500,"Personal Expense",Expense_Input!$E$4:$E$500,$A46) -> 0 | H46: =SUMIFS(Expense_Input!$D$4:$D$500,Expense_Input!$B$4:$B$500,">="&DATE(VALUE(LEFT(H$44,4)),VALUE(RIGHT(H$44,2)),1),Expense_Input!$B$4:$B$500,"<"&DATE(VALUE(LEFT(H$44,4)),VALUE(RIGHT(H$44,2))+1,1),Expense_Input!$H$4:$H$500,"Personal Expense",Expense_Input!$E$4:$E$500,$A46) -> 0 | I46: =SUMIFS(Expense_Input!$D$4:$D$500,Expense_Input!$B$4:$B$500,">="&DATE(VALUE(LEFT(I$44,4)),VALUE(RIGHT(I$44,2)),1),Expense_Input!$B$4:$B$500,"<"&DATE(VALUE(LEFT(I$44,4)),VALUE(RIGHT(I$44,2))+1,1),Expense_Input!$H$4:$H$500,"Personal Expense",Expense_Input!$E$4:$E$500,$A46) -> 0 | ... M46: =SUMIFS(Expense_Input!$D$4:$D$500,Expense_Input!$B$4:$B$500,">="&DATE(VALUE(LEFT(M$44,4)),VALUE(RIGHT(M$44,2)),1),Expense_Input!$B$4:$B$500,"<"&DATE(VALUE(LEFT(M$44,4)),VALUE(RIGHT(M$44,2))+1,1),Expense_Input!$H$4:$H$500,"Personal Expense",Expense_Input!$E$4:$E$500,$A46) -> 0 | N46: =IF($B$4=0,0,SUM(B46:M46)/$B$4) -> 820 | O46: =N46*12 -> 9840 | P46: =IFERROR(N46/$B$7,0) -> 0.1592233
A47: Transportation | B47: =SUMIFS(Expense_Input!$D$4:$D$500,Expense_Input!$B$4:$B$500,">="&DATE(VALUE(LEFT(B$44,4)),VALUE(RIGHT(B$44,2)),1),Expense_Input!$B$4:$B$500,"<"&DATE(VALUE(LEFT(B$44,4)),VALUE(RIGHT(B$44,2))+1,1),Expense_Input!$H$4:$H$500,"Personal Expense",Expense_Input!$E$4:$E$500,$A47) -> 220 | C47: =SUMIFS(Expense_Input!$D$4:$D$500,Expense_Input!$B$4:$B$500,">="&DATE(VALUE(LEFT(C$44,4)),VALUE(RIGHT(C$44,2)),1),Expense_Input!$B$4:$B$500,"<"&DATE(VALUE(LEFT(C$44,4)),VALUE(RIGHT(C$44,2))+1,1),Expense_Input!$H$4:$H$500,"Personal Expense",Expense_Input!$E$4:$E$500,$A47) -> 260 | D47: =SUMIFS(Expense_Input!$D$4:$D$500,Expense_Input!$B$4:$B$500,">="&DATE(VALUE(LEFT(D$44,4)),VALUE(RIGHT(D$44,2)),1),Expense_Input!$B$4:$B$500,"<"&DATE(VALUE(LEFT(D$44,4)),VALUE(RIGHT(D$44,2))+1,1),Expense_Input!$H$4:$H$500,"Personal Expense",Expense_Input!$E$4:$E$500,$A47) -> 0 | E47: =SUMIFS(Expense_Input!$D$4:$D$500,Expense_Input!$B$4:$B$500,">="&DATE(VALUE(LEFT(E$44,4)),VALUE(RIGHT(E$44,2)),1),Expense_Input!$B$4:$B$500,"<"&DATE(VALUE(LEFT(E$44,4)),VALUE(RIGHT(E$44,2))+1,1),Expense_Input!$H$4:$H$500,"Personal Expense",Expense_Input!$E$4:$E$500,$A47) -> 0 | F47: =SUMIFS(Expense_Input!$D$4:$D$500,Expense_Input!$B$4:$B$500,">="&DATE(VALUE(LEFT(F$44,4)),VALUE(RIGHT(F$44,2)),1),Expense_Input!$B$4:$B$500,"<"&DATE(VALUE(LEFT(F$44,4)),VALUE(RIGHT(F$44,2))+1,1),Expense_Input!$H$4:$H$500,"Personal Expense",Expense_Input!$E$4:$E$500,$A47) -> 0 | G47: =SUMIFS(Expense_Input!$D$4:$D$500,Expense_Input!$B$4:$B$500,">="&DATE(VALUE(LEFT(G$44,4)),VALUE(RIGHT(G$44,2)),1),Expense_Input!$B$4:$B$500,"<"&DATE(VALUE(LEFT(G$44,4)),VALUE(RIGHT(G$44,2))+1,1),Expense_Input!$H$4:$H$500,"Personal Expense",Expense_Input!$E$4:$E$500,$A47) -> 0 | H47: =SUMIFS(Expense_Input!$D$4:$D$500,Expense_Input!$B$4:$B$500,">="&DATE(VALUE(LEFT(H$44,4)),VALUE(RIGHT(H$44,2)),1),Expense_Input!$B$4:$B$500,"<"&DATE(VALUE(LEFT(H$44,4)),VALUE(RIGHT(H$44,2))+1,1),Expense_Input!$H$4:$H$500,"Personal Expense",Expense_Input!$E$4:$E$500,$A47) -> 0 | I47: =SUMIFS(Expense_Input!$D$4:$D$500,Expense_Input!$B$4:$B$500,">="&DATE(VALUE(LEFT(I$44,4)),VALUE(RIGHT(I$44,2)),1),Expense_Input!$B$4:$B$500,"<"&DATE(VALUE(LEFT(I$44,4)),VALUE(RIGHT(I$44,2))+1,1),Expense_Input!$H$4:$H$500,"Personal Expense",Expense_Input!$E$4:$E$500,$A47) -> 0 | ... M47: =SUMIFS(Expense_Input!$D$4:$D$500,Expense_Input!$B$4:$B$500,">="&DATE(VALUE(LEFT(M$44,4)),VALUE(RIGHT(M$44,2)),1),Expense_Input!$B$4:$B$500,"<"&DATE(VALUE(LEFT(M$44,4)),VALUE(RIGHT(M$44,2))+1,1),Expense_Input!$H$4:$H$500,"Personal Expense",Expense_Input!$E$4:$E$500,$A47) -> 0 | N47: =IF($B$4=0,0,SUM(B47:M47)/$B$4) -> 240 | O47: =N47*12 -> 2880 | P47: =IFERROR(N47/$B$7,0) -> 0.046601942
A48: Telecom | B48: =SUMIFS(Expense_Input!$D$4:$D$500,Expense_Input!$B$4:$B$500,">="&DATE(VALUE(LEFT(B$44,4)),VALUE(RIGHT(B$44,2)),1),Expense_Input!$B$4:$B$500,"<"&DATE(VALUE(LEFT(B$44,4)),VALUE(RIGHT(B$44,2))+1,1),Expense_Input!$H$4:$H$500,"Personal Expense",Expense_Input!$E$4:$E$500,$A48) -> 60 | C48: =SUMIFS(Expense_Input!$D$4:$D$500,Expense_Input!$B$4:$B$500,">="&DATE(VALUE(LEFT(C$44,4)),VALUE(RIGHT(C$44,2)),1),Expense_Input!$B$4:$B$500,"<"&DATE(VALUE(LEFT(C$44,4)),VALUE(RIGHT(C$44,2))+1,1),Expense_Input!$H$4:$H$500,"Personal Expense",Expense_Input!$E$4:$E$500,$A48) -> 60 | D48: =SUMIFS(Expense_Input!$D$4:$D$500,Expense_Input!$B$4:$B$500,">="&DATE(VALUE(LEFT(D$44,4)),VALUE(RIGHT(D$44,2)),1),Expense_Input!$B$4:$B$500,"<"&DATE(VALUE(LEFT(D$44,4)),VALUE(RIGHT(D$44,2))+1,1),Expense_Input!$H$4:$H$500,"Personal Expense",Expense_Input!$E$4:$E$500,$A48) -> 0 | E48: =SUMIFS(Expense_Input!$D$4:$D$500,Expense_Input!$B$4:$B$500,">="&DATE(VALUE(LEFT(E$44,4)),VALUE(RIGHT(E$44,2)),1),Expense_Input!$B$4:$B$500,"<"&DATE(VALUE(LEFT(E$44,4)),VALUE(RIGHT(E$44,2))+1,1),Expense_Input!$H$4:$H$500,"Personal Expense",Expense_Input!$E$4:$E$500,$A48) -> 0 | F48: =SUMIFS(Expense_Input!$D$4:$D$500,Expense_Input!$B$4:$B$500,">="&DATE(VALUE(LEFT(F$44,4)),VALUE(RIGHT(F$44,2)),1),Expense_Input!$B$4:$B$500,"<"&DATE(VALUE(LEFT(F$44,4)),VALUE(RIGHT(F$44,2))+1,1),Expense_Input!$H$4:$H$500,"Personal Expense",Expense_Input!$E$4:$E$500,$A48) -> 0 | G48: =SUMIFS(Expense_Input!$D$4:$D$500,Expense_Input!$B$4:$B$500,">="&DATE(VALUE(LEFT(G$44,4)),VALUE(RIGHT(G$44,2)),1),Expense_Input!$B$4:$B$500,"<"&DATE(VALUE(LEFT(G$44,4)),VALUE(RIGHT(G$44,2))+1,1),Expense_Input!$H$4:$H$500,"Personal Expense",Expense_Input!$E$4:$E$500,$A48) -> 0 | H48: =SUMIFS(Expense_Input!$D$4:$D$500,Expense_Input!$B$4:$B$500,">="&DATE(VALUE(LEFT(H$44,4)),VALUE(RIGHT(H$44,2)),1),Expense_Input!$B$4:$B$500,"<"&DATE(VALUE(LEFT(H$44,4)),VALUE(RIGHT(H$44,2))+1,1),Expense_Input!$H$4:$H$500,"Personal Expense",Expense_Input!$E$4:$E$500,$A48) -> 0 | I48: =SUMIFS(Expense_Input!$D$4:$D$500,Expense_Input!$B$4:$B$500,">="&DATE(VALUE(LEFT(I$44,4)),VALUE(RIGHT(I$44,2)),1),Expense_Input!$B$4:$B$500,"<"&DATE(VALUE(LEFT(I$44,4)),VALUE(RIGHT(I$44,2))+1,1),Expense_Input!$H$4:$H$500,"Personal Expense",Expense_Input!$E$4:$E$500,$A48) -> 0 | ... M48: =SUMIFS(Expense_Input!$D$4:$D$500,Expense_Input!$B$4:$B$500,">="&DATE(VALUE(LEFT(M$44,4)),VALUE(RIGHT(M$44,2)),1),Expense_Input!$B$4:$B$500,"<"&DATE(VALUE(LEFT(M$44,4)),VALUE(RIGHT(M$44,2))+1,1),Expense_Input!$H$4:$H$500,"Personal Expense",Expense_Input!$E$4:$E$500,$A48) -> 0 | N48: =IF($B$4=0,0,SUM(B48:M48)/$B$4) -> 60 | O48: =N48*12 -> 720 | P48: =IFERROR(N48/$B$7,0) -> 0.011650485
A49: Subscriptions | B49: =SUMIFS(Expense_Input!$D$4:$D$500,Expense_Input!$B$4:$B$500,">="&DATE(VALUE(LEFT(B$44,4)),VALUE(RIGHT(B$44,2)),1),Expense_Input!$B$4:$B$500,"<"&DATE(VALUE(LEFT(B$44,4)),VALUE(RIGHT(B$44,2))+1,1),Expense_Input!$H$4:$H$500,"Personal Expense",Expense_Input!$E$4:$E$500,$A49) -> 30 | C49: =SUMIFS(Expense_Input!$D$4:$D$500,Expense_Input!$B$4:$B$500,">="&DATE(VALUE(LEFT(C$44,4)),VALUE(RIGHT(C$44,2)),1),Expense_Input!$B$4:$B$500,"<"&DATE(VALUE(LEFT(C$44,4)),VALUE(RIGHT(C$44,2))+1,1),Expense_Input!$H$4:$H$500,"Personal Expense",Expense_Input!$E$4:$E$500,$A49) -> 45 | D49: =SUMIFS(Expense_Input!$D$4:$D$500,Expense_Input!$B$4:$B$500,">="&DATE(VALUE(LEFT(D$44,4)),VALUE(RIGHT(D$44,2)),1),Expense_Input!$B$4:$B$500,"<"&DATE(VALUE(LEFT(D$44,4)),VALUE(RIGHT(D$44,2))+1,1),Expense_Input!$H$4:$H$500,"Personal Expense",Expense_Input!$E$4:$E$500,$A49) -> 0 | E49: =SUMIFS(Expense_Input!$D$4:$D$500,Expense_Input!$B$4:$B$500,">="&DATE(VALUE(LEFT(E$44,4)),VALUE(RIGHT(E$44,2)),1),Expense_Input!$B$4:$B$500,"<"&DATE(VALUE(LEFT(E$44,4)),VALUE(RIGHT(E$44,2))+1,1),Expense_Input!$H$4:$H$500,"Personal Expense",Expense_Input!$E$4:$E$500,$A49) -> 0 | F49: =SUMIFS(Expense_Input!$D$4:$D$500,Expense_Input!$B$4:$B$500,">="&DATE(VALUE(LEFT(F$44,4)),VALUE(RIGHT(F$44,2)),1),Expense_Input!$B$4:$B$500,"<"&DATE(VALUE(LEFT(F$44,4)),VALUE(RIGHT(F$44,2))+1,1),Expense_Input!$H$4:$H$500,"Personal Expense",Expense_Input!$E$4:$E$500,$A49) -> 0 | G49: =SUMIFS(Expense_Input!$D$4:$D$500,Expense_Input!$B$4:$B$500,">="&DATE(VALUE(LEFT(G$44,4)),VALUE(RIGHT(G$44,2)),1),Expense_Input!$B$4:$B$500,"<"&DATE(VALUE(LEFT(G$44,4)),VALUE(RIGHT(G$44,2))+1,1),Expense_Input!$H$4:$H$500,"Personal Expense",Expense_Input!$E$4:$E$500,$A49) -> 0 | H49: =SUMIFS(Expense_Input!$D$4:$D$500,Expense_Input!$B$4:$B$500,">="&DATE(VALUE(LEFT(H$44,4)),VALUE(RIGHT(H$44,2)),1),Expense_Input!$B$4:$B$500,"<"&DATE(VALUE(LEFT(H$44,4)),VALUE(RIGHT(H$44,2))+1,1),Expense_Input!$H$4:$H$500,"Personal Expense",Expense_Input!$E$4:$E$500,$A49) -> 0 | I49: =SUMIFS(Expense_Input!$D$4:$D$500,Expense_Input!$B$4:$B$500,">="&DATE(VALUE(LEFT(I$44,4)),VALUE(RIGHT(I$44,2)),1),Expense_Input!$B$4:$B$500,"<"&DATE(VALUE(LEFT(I$44,4)),VALUE(RIGHT(I$44,2))+1,1),Expense_Input!$H$4:$H$500,"Personal Expense",Expense_Input!$E$4:$E$500,$A49) -> 0 | ... M49: =SUMIFS(Expense_Input!$D$4:$D$500,Expense_Input!$B$4:$B$500,">="&DATE(VALUE(LEFT(M$44,4)),VALUE(RIGHT(M$44,2)),1),Expense_Input!$B$4:$B$500,"<"&DATE(VALUE(LEFT(M$44,4)),VALUE(RIGHT(M$44,2))+1,1),Expense_Input!$H$4:$H$500,"Personal Expense",Expense_Input!$E$4:$E$500,$A49) -> 0 | N49: =IF($B$4=0,0,SUM(B49:M49)/$B$4) -> 37.5 | O49: =N49*12 -> 450 | P49: =IFERROR(N49/$B$7,0) -> 0.0072815534
A50: Shopping | B50: =SUMIFS(Expense_Input!$D$4:$D$500,Expense_Input!$B$4:$B$500,">="&DATE(VALUE(LEFT(B$44,4)),VALUE(RIGHT(B$44,2)),1),Expense_Input!$B$4:$B$500,"<"&DATE(VALUE(LEFT(B$44,4)),VALUE(RIGHT(B$44,2))+1,1),Expense_Input!$H$4:$H$500,"Personal Expense",Expense_Input!$E$4:$E$500,$A50) -> 250 | C50: =SUMIFS(Expense_Input!$D$4:$D$500,Expense_Input!$B$4:$B$500,">="&DATE(VALUE(LEFT(C$44,4)),VALUE(RIGHT(C$44,2)),1),Expense_Input!$B$4:$B$500,"<"&DATE(VALUE(LEFT(C$44,4)),VALUE(RIGHT(C$44,2))+1,1),Expense_Input!$H$4:$H$500,"Personal Expense",Expense_Input!$E$4:$E$500,$A50) -> 300 | D50: =SUMIFS(Expense_Input!$D$4:$D$500,Expense_Input!$B$4:$B$500,">="&DATE(VALUE(LEFT(D$44,4)),VALUE(RIGHT(D$44,2)),1),Expense_Input!$B$4:$B$500,"<"&DATE(VALUE(LEFT(D$44,4)),VALUE(RIGHT(D$44,2))+1,1),Expense_Input!$H$4:$H$500,"Personal Expense",Expense_Input!$E$4:$E$500,$A50) -> 0 | E50: =SUMIFS(Expense_Input!$D$4:$D$500,Expense_Input!$B$4:$B$500,">="&DATE(VALUE(LEFT(E$44,4)),VALUE(RIGHT(E$44,2)),1),Expense_Input!$B$4:$B$500,"<"&DATE(VALUE(LEFT(E$44,4)),VALUE(RIGHT(E$44,2))+1,1),Expense_Input!$H$4:$H$500,"Personal Expense",Expense_Input!$E$4:$E$500,$A50) -> 0 | F50: =SUMIFS(Expense_Input!$D$4:$D$500,Expense_Input!$B$4:$B$500,">="&DATE(VALUE(LEFT(F$44,4)),VALUE(RIGHT(F$44,2)),1),Expense_Input!$B$4:$B$500,"<"&DATE(VALUE(LEFT(F$44,4)),VALUE(RIGHT(F$44,2))+1,1),Expense_Input!$H$4:$H$500,"Personal Expense",Expense_Input!$E$4:$E$500,$A50) -> 0 | G50: =SUMIFS(Expense_Input!$D$4:$D$500,Expense_Input!$B$4:$B$500,">="&DATE(VALUE(LEFT(G$44,4)),VALUE(RIGHT(G$44,2)),1),Expense_Input!$B$4:$B$500,"<"&DATE(VALUE(LEFT(G$44,4)),VALUE(RIGHT(G$44,2))+1,1),Expense_Input!$H$4:$H$500,"Personal Expense",Expense_Input!$E$4:$E$500,$A50) -> 0 | H50: =SUMIFS(Expense_Input!$D$4:$D$500,Expense_Input!$B$4:$B$500,">="&DATE(VALUE(LEFT(H$44,4)),VALUE(RIGHT(H$44,2)),1),Expense_Input!$B$4:$B$500,"<"&DATE(VALUE(LEFT(H$44,4)),VALUE(RIGHT(H$44,2))+1,1),Expense_Input!$H$4:$H$500,"Personal Expense",Expense_Input!$E$4:$E$500,$A50) -> 0 | I50: =SUMIFS(Expense_Input!$D$4:$D$500,Expense_Input!$B$4:$B$500,">="&DATE(VALUE(LEFT(I$44,4)),VALUE(RIGHT(I$44,2)),1),Expense_Input!$B$4:$B$500,"<"&DATE(VALUE(LEFT(I$44,4)),VALUE(RIGHT(I$44,2))+1,1),Expense_Input!$H$4:$H$500,"Personal Expense",Expense_Input!$E$4:$E$500,$A50) -> 0 | ... M50: =SUMIFS(Expense_Input!$D$4:$D$500,Expense_Input!$B$4:$B$500,">="&DATE(VALUE(LEFT(M$44,4)),VALUE(RIGHT(M$44,2)),1),Expense_Input!$B$4:$B$500,"<"&DATE(VALUE(LEFT(M$44,4)),VALUE(RIGHT(M$44,2))+1,1),Expense_Input!$H$4:$H$500,"Personal Expense",Expense_Input!$E$4:$E$500,$A50) -> 0 | N50: =IF($B$4=0,0,SUM(B50:M50)/$B$4) -> 275 | O50: =N50*12 -> 3300 | P50: =IFERROR(N50/$B$7,0) -> 0.053398058
A51: Medical | B51: =SUMIFS(Expense_Input!$D$4:$D$500,Expense_Input!$B$4:$B$500,">="&DATE(VALUE(LEFT(B$44,4)),VALUE(RIGHT(B$44,2)),1),Expense_Input!$B$4:$B$500,"<"&DATE(VALUE(LEFT(B$44,4)),VALUE(RIGHT(B$44,2))+1,1),Expense_Input!$H$4:$H$500,"Personal Expense",Expense_Input!$E$4:$E$500,$A51) -> 80 | C51: =SUMIFS(Expense_Input!$D$4:$D$500,Expense_Input!$B$4:$B$500,">="&DATE(VALUE(LEFT(C$44,4)),VALUE(RIGHT(C$44,2)),1),Expense_Input!$B$4:$B$500,"<"&DATE(VALUE(LEFT(C$44,4)),VALUE(RIGHT(C$44,2))+1,1),Expense_Input!$H$4:$H$500,"Personal Expense",Expense_Input!$E$4:$E$500,$A51) -> 100 | D51: =SUMIFS(Expense_Input!$D$4:$D$500,Expense_Input!$B$4:$B$500,">="&DATE(VALUE(LEFT(D$44,4)),VALUE(RIGHT(D$44,2)),1),Expense_Input!$B$4:$B$500,"<"&DATE(VALUE(LEFT(D$44,4)),VALUE(RIGHT(D$44,2))+1,1),Expense_Input!$H$4:$H$500,"Personal Expense",Expense_Input!$E$4:$E$500,$A51) -> 0 | E51: =SUMIFS(Expense_Input!$D$4:$D$500,Expense_Input!$B$4:$B$500,">="&DATE(VALUE(LEFT(E$44,4)),VALUE(RIGHT(E$44,2)),1),Expense_Input!$B$4:$B$500,"<"&DATE(VALUE(LEFT(E$44,4)),VALUE(RIGHT(E$44,2))+1,1),Expense_Input!$H$4:$H$500,"Personal Expense",Expense_Input!$E$4:$E$500,$A51) -> 0 | F51: =SUMIFS(Expense_Input!$D$4:$D$500,Expense_Input!$B$4:$B$500,">="&DATE(VALUE(LEFT(F$44,4)),VALUE(RIGHT(F$44,2)),1),Expense_Input!$B$4:$B$500,"<"&DATE(VALUE(LEFT(F$44,4)),VALUE(RIGHT(F$44,2))+1,1),Expense_Input!$H$4:$H$500,"Personal Expense",Expense_Input!$E$4:$E$500,$A51) -> 0 | G51: =SUMIFS(Expense_Input!$D$4:$D$500,Expense_Input!$B$4:$B$500,">="&DATE(VALUE(LEFT(G$44,4)),VALUE(RIGHT(G$44,2)),1),Expense_Input!$B$4:$B$500,"<"&DATE(VALUE(LEFT(G$44,4)),VALUE(RIGHT(G$44,2))+1,1),Expense_Input!$H$4:$H$500,"Personal Expense",Expense_Input!$E$4:$E$500,$A51) -> 0 | H51: =SUMIFS(Expense_Input!$D$4:$D$500,Expense_Input!$B$4:$B$500,">="&DATE(VALUE(LEFT(H$44,4)),VALUE(RIGHT(H$44,2)),1),Expense_Input!$B$4:$B$500,"<"&DATE(VALUE(LEFT(H$44,4)),VALUE(RIGHT(H$44,2))+1,1),Expense_Input!$H$4:$H$500,"Personal Expense",Expense_Input!$E$4:$E$500,$A51) -> 0 | I51: =SUMIFS(Expense_Input!$D$4:$D$500,Expense_Input!$B$4:$B$500,">="&DATE(VALUE(LEFT(I$44,4)),VALUE(RIGHT(I$44,2)),1),Expense_Input!$B$4:$B$500,"<"&DATE(VALUE(LEFT(I$44,4)),VALUE(RIGHT(I$44,2))+1,1),Expense_Input!$H$4:$H$500,"Personal Expense",Expense_Input!$E$4:$E$500,$A51) -> 0 | ... M51: =SUMIFS(Expense_Input!$D$4:$D$500,Expense_Input!$B$4:$B$500,">="&DATE(VALUE(LEFT(M$44,4)),VALUE(RIGHT(M$44,2)),1),Expense_Input!$B$4:$B$500,"<"&DATE(VALUE(LEFT(M$44,4)),VALUE(RIGHT(M$44,2))+1,1),Expense_Input!$H$4:$H$500,"Personal Expense",Expense_Input!$E$4:$E$500,$A51) -> 0 | N51: =IF($B$4=0,0,SUM(B51:M51)/$B$4) -> 90 | O51: =N51*12 -> 1080 | P51: =IFERROR(N51/$B$7,0) -> 0.017475728
A52: Fitness | B52: =SUMIFS(Expense_Input!$D$4:$D$500,Expense_Input!$B$4:$B$500,">="&DATE(VALUE(LEFT(B$44,4)),VALUE(RIGHT(B$44,2)),1),Expense_Input!$B$4:$B$500,"<"&DATE(VALUE(LEFT(B$44,4)),VALUE(RIGHT(B$44,2))+1,1),Expense_Input!$H$4:$H$500,"Personal Expense",Expense_Input!$E$4:$E$500,$A52) -> 70 | C52: =SUMIFS(Expense_Input!$D$4:$D$500,Expense_Input!$B$4:$B$500,">="&DATE(VALUE(LEFT(C$44,4)),VALUE(RIGHT(C$44,2)),1),Expense_Input!$B$4:$B$500,"<"&DATE(VALUE(LEFT(C$44,4)),VALUE(RIGHT(C$44,2))+1,1),Expense_Input!$H$4:$H$500,"Personal Expense",Expense_Input!$E$4:$E$500,$A52) -> 70 | D52: =SUMIFS(Expense_Input!$D$4:$D$500,Expense_Input!$B$4:$B$500,">="&DATE(VALUE(LEFT(D$44,4)),VALUE(RIGHT(D$44,2)),1),Expense_Input!$B$4:$B$500,"<"&DATE(VALUE(LEFT(D$44,4)),VALUE(RIGHT(D$44,2))+1,1),Expense_Input!$H$4:$H$500,"Personal Expense",Expense_Input!$E$4:$E$500,$A52) -> 0 | E52: =SUMIFS(Expense_Input!$D$4:$D$500,Expense_Input!$B$4:$B$500,">="&DATE(VALUE(LEFT(E$44,4)),VALUE(RIGHT(E$44,2)),1),Expense_Input!$B$4:$B$500,"<"&DATE(VALUE(LEFT(E$44,4)),VALUE(RIGHT(E$44,2))+1,1),Expense_Input!$H$4:$H$500,"Personal Expense",Expense_Input!$E$4:$E$500,$A52) -> 0 | F52: =SUMIFS(Expense_Input!$D$4:$D$500,Expense_Input!$B$4:$B$500,">="&DATE(VALUE(LEFT(F$44,4)),VALUE(RIGHT(F$44,2)),1),Expense_Input!$B$4:$B$500,"<"&DATE(VALUE(LEFT(F$44,4)),VALUE(RIGHT(F$44,2))+1,1),Expense_Input!$H$4:$H$500,"Personal Expense",Expense_Input!$E$4:$E$500,$A52) -> 0 | G52: =SUMIFS(Expense_Input!$D$4:$D$500,Expense_Input!$B$4:$B$500,">="&DATE(VALUE(LEFT(G$44,4)),VALUE(RIGHT(G$44,2)),1),Expense_Input!$B$4:$B$500,"<"&DATE(VALUE(LEFT(G$44,4)),VALUE(RIGHT(G$44,2))+1,1),Expense_Input!$H$4:$H$500,"Personal Expense",Expense_Input!$E$4:$E$500,$A52) -> 0 | H52: =SUMIFS(Expense_Input!$D$4:$D$500,Expense_Input!$B$4:$B$500,">="&DATE(VALUE(LEFT(H$44,4)),VALUE(RIGHT(H$44,2)),1),Expense_Input!$B$4:$B$500,"<"&DATE(VALUE(LEFT(H$44,4)),VALUE(RIGHT(H$44,2))+1,1),Expense_Input!$H$4:$H$500,"Personal Expense",Expense_Input!$E$4:$E$500,$A52) -> 0 | I52: =SUMIFS(Expense_Input!$D$4:$D$500,Expense_Input!$B$4:$B$500,">="&DATE(VALUE(LEFT(I$44,4)),VALUE(RIGHT(I$44,2)),1),Expense_Input!$B$4:$B$500,"<"&DATE(VALUE(LEFT(I$44,4)),VALUE(RIGHT(I$44,2))+1,1),Expense_Input!$H$4:$H$500,"Personal Expense",Expense_Input!$E$4:$E$500,$A52) -> 0 | ... M52: =SUMIFS(Expense_Input!$D$4:$D$500,Expense_Input!$B$4:$B$500,">="&DATE(VALUE(LEFT(M$44,4)),VALUE(RIGHT(M$44,2)),1),Expense_Input!$B$4:$B$500,"<"&DATE(VALUE(LEFT(M$44,4)),VALUE(RIGHT(M$44,2))+1,1),Expense_Input!$H$4:$H$500,"Personal Expense",Expense_Input!$E$4:$E$500,$A52) -> 0 | N52: =IF($B$4=0,0,SUM(B52:M52)/$B$4) -> 70 | O52: =N52*12 -> 840 | P52: =IFERROR(N52/$B$7,0) -> 0.013592233
A53: Education | B53: =SUMIFS(Expense_Input!$D$4:$D$500,Expense_Input!$B$4:$B$500,">="&DATE(VALUE(LEFT(B$44,4)),VALUE(RIGHT(B$44,2)),1),Expense_Input!$B$4:$B$500,"<"&DATE(VALUE(LEFT(B$44,4)),VALUE(RIGHT(B$44,2))+1,1),Expense_Input!$H$4:$H$500,"Personal Expense",Expense_Input!$E$4:$E$500,$A53) -> 120 | C53: =SUMIFS(Expense_Input!$D$4:$D$500,Expense_Input!$B$4:$B$500,">="&DATE(VALUE(LEFT(C$44,4)),VALUE(RIGHT(C$44,2)),1),Expense_Input!$B$4:$B$500,"<"&DATE(VALUE(LEFT(C$44,4)),VALUE(RIGHT(C$44,2))+1,1),Expense_Input!$H$4:$H$500,"Personal Expense",Expense_Input!$E$4:$E$500,$A53) -> 140 | D53: =SUMIFS(Expense_Input!$D$4:$D$500,Expense_Input!$B$4:$B$500,">="&DATE(VALUE(LEFT(D$44,4)),VALUE(RIGHT(D$44,2)),1),Expense_Input!$B$4:$B$500,"<"&DATE(VALUE(LEFT(D$44,4)),VALUE(RIGHT(D$44,2))+1,1),Expense_Input!$H$4:$H$500,"Personal Expense",Expense_Input!$E$4:$E$500,$A53) -> 0 | E53: =SUMIFS(Expense_Input!$D$4:$D$500,Expense_Input!$B$4:$B$500,">="&DATE(VALUE(LEFT(E$44,4)),VALUE(RIGHT(E$44,2)),1),Expense_Input!$B$4:$B$500,"<"&DATE(VALUE(LEFT(E$44,4)),VALUE(RIGHT(E$44,2))+1,1),Expense_Input!$H$4:$H$500,"Personal Expense",Expense_Input!$E$4:$E$500,$A53) -> 0 | F53: =SUMIFS(Expense_Input!$D$4:$D$500,Expense_Input!$B$4:$B$500,">="&DATE(VALUE(LEFT(F$44,4)),VALUE(RIGHT(F$44,2)),1),Expense_Input!$B$4:$B$500,"<"&DATE(VALUE(LEFT(F$44,4)),VALUE(RIGHT(F$44,2))+1,1),Expense_Input!$H$4:$H$500,"Personal Expense",Expense_Input!$E$4:$E$500,$A53) -> 0 | G53: =SUMIFS(Expense_Input!$D$4:$D$500,Expense_Input!$B$4:$B$500,">="&DATE(VALUE(LEFT(G$44,4)),VALUE(RIGHT(G$44,2)),1),Expense_Input!$B$4:$B$500,"<"&DATE(VALUE(LEFT(G$44,4)),VALUE(RIGHT(G$44,2))+1,1),Expense_Input!$H$4:$H$500,"Personal Expense",Expense_Input!$E$4:$E$500,$A53) -> 0 | H53: =SUMIFS(Expense_Input!$D$4:$D$500,Expense_Input!$B$4:$B$500,">="&DATE(VALUE(LEFT(H$44,4)),VALUE(RIGHT(H$44,2)),1),Expense_Input!$B$4:$B$500,"<"&DATE(VALUE(LEFT(H$44,4)),VALUE(RIGHT(H$44,2))+1,1),Expense_Input!$H$4:$H$500,"Personal Expense",Expense_Input!$E$4:$E$500,$A53) -> 0 | I53: =SUMIFS(Expense_Input!$D$4:$D$500,Expense_Input!$B$4:$B$500,">="&DATE(VALUE(LEFT(I$44,4)),VALUE(RIGHT(I$44,2)),1),Expense_Input!$B$4:$B$500,"<"&DATE(VALUE(LEFT(I$44,4)),VALUE(RIGHT(I$44,2))+1,1),Expense_Input!$H$4:$H$500,"Personal Expense",Expense_Input!$E$4:$E$500,$A53) -> 0 | ... M53: =SUMIFS(Expense_Input!$D$4:$D$500,Expense_Input!$B$4:$B$500,">="&DATE(VALUE(LEFT(M$44,4)),VALUE(RIGHT(M$44,2)),1),Expense_Input!$B$4:$B$500,"<"&DATE(VALUE(LEFT(M$44,4)),VALUE(RIGHT(M$44,2))+1,1),Expense_Input!$H$4:$H$500,"Personal Expense",Expense_Input!$E$4:$E$500,$A53) -> 0 | N53: =IF($B$4=0,0,SUM(B53:M53)/$B$4) -> 130 | O53: =N53*12 -> 1560 | P53: =IFERROR(N53/$B$7,0) -> 0.025242718
A54: Pet | B54: =SUMIFS(Expense_Input!$D$4:$D$500,Expense_Input!$B$4:$B$500,">="&DATE(VALUE(LEFT(B$44,4)),VALUE(RIGHT(B$44,2)),1),Expense_Input!$B$4:$B$500,"<"&DATE(VALUE(LEFT(B$44,4)),VALUE(RIGHT(B$44,2))+1,1),Expense_Input!$H$4:$H$500,"Personal Expense",Expense_Input!$E$4:$E$500,$A54) -> 90 | C54: =SUMIFS(Expense_Input!$D$4:$D$500,Expense_Input!$B$4:$B$500,">="&DATE(VALUE(LEFT(C$44,4)),VALUE(RIGHT(C$44,2)),1),Expense_Input!$B$4:$B$500,"<"&DATE(VALUE(LEFT(C$44,4)),VALUE(RIGHT(C$44,2))+1,1),Expense_Input!$H$4:$H$500,"Personal Expense",Expense_Input!$E$4:$E$500,$A54) -> 100 | D54: =SUMIFS(Expense_Input!$D$4:$D$500,Expense_Input!$B$4:$B$500,">="&DATE(VALUE(LEFT(D$44,4)),VALUE(RIGHT(D$44,2)),1),Expense_Input!$B$4:$B$500,"<"&DATE(VALUE(LEFT(D$44,4)),VALUE(RIGHT(D$44,2))+1,1),Expense_Input!$H$4:$H$500,"Personal Expense",Expense_Input!$E$4:$E$500,$A54) -> 0 | E54: =SUMIFS(Expense_Input!$D$4:$D$500,Expense_Input!$B$4:$B$500,">="&DATE(VALUE(LEFT(E$44,4)),VALUE(RIGHT(E$44,2)),1),Expense_Input!$B$4:$B$500,"<"&DATE(VALUE(LEFT(E$44,4)),VALUE(RIGHT(E$44,2))+1,1),Expense_Input!$H$4:$H$500,"Personal Expense",Expense_Input!$E$4:$E$500,$A54) -> 0 | F54: =SUMIFS(Expense_Input!$D$4:$D$500,Expense_Input!$B$4:$B$500,">="&DATE(VALUE(LEFT(F$44,4)),VALUE(RIGHT(F$44,2)),1),Expense_Input!$B$4:$B$500,"<"&DATE(VALUE(LEFT(F$44,4)),VALUE(RIGHT(F$44,2))+1,1),Expense_Input!$H$4:$H$500,"Personal Expense",Expense_Input!$E$4:$E$500,$A54) -> 0 | G54: =SUMIFS(Expense_Input!$D$4:$D$500,Expense_Input!$B$4:$B$500,">="&DATE(VALUE(LEFT(G$44,4)),VALUE(RIGHT(G$44,2)),1),Expense_Input!$B$4:$B$500,"<"&DATE(VALUE(LEFT(G$44,4)),VALUE(RIGHT(G$44,2))+1,1),Expense_Input!$H$4:$H$500,"Personal Expense",Expense_Input!$E$4:$E$500,$A54) -> 0 | H54: =SUMIFS(Expense_Input!$D$4:$D$500,Expense_Input!$B$4:$B$500,">="&DATE(VALUE(LEFT(H$44,4)),VALUE(RIGHT(H$44,2)),1),Expense_Input!$B$4:$B$500,"<"&DATE(VALUE(LEFT(H$44,4)),VALUE(RIGHT(H$44,2))+1,1),Expense_Input!$H$4:$H$500,"Personal Expense",Expense_Input!$E$4:$E$500,$A54) -> 0 | I54: =SUMIFS(Expense_Input!$D$4:$D$500,Expense_Input!$B$4:$B$500,">="&DATE(VALUE(LEFT(I$44,4)),VALUE(RIGHT(I$44,2)),1),Expense_Input!$B$4:$B$500,"<"&DATE(VALUE(LEFT(I$44,4)),VALUE(RIGHT(I$44,2))+1,1),Expense_Input!$H$4:$H$500,"Personal Expense",Expense_Input!$E$4:$E$500,$A54) -> 0 | ... M54: =SUMIFS(Expense_Input!$D$4:$D$500,Expense_Input!$B$4:$B$500,">="&DATE(VALUE(LEFT(M$44,4)),VALUE(RIGHT(M$44,2)),1),Expense_Input!$B$4:$B$500,"<"&DATE(VALUE(LEFT(M$44,4)),VALUE(RIGHT(M$44,2))+1,1),Expense_Input!$H$4:$H$500,"Personal Expense",Expense_Input!$E$4:$E$500,$A54) -> 0 | N54: =IF($B$4=0,0,SUM(B54:M54)/$B$4) -> 95 | O54: =N54*12 -> 1140 | P54: =IFERROR(N54/$B$7,0) -> 0.018446602
A55: Entertainment | B55: =SUMIFS(Expense_Input!$D$4:$D$500,Expense_Input!$B$4:$B$500,">="&DATE(VALUE(LEFT(B$44,4)),VALUE(RIGHT(B$44,2)),1),Expense_Input!$B$4:$B$500,"<"&DATE(VALUE(LEFT(B$44,4)),VALUE(RIGHT(B$44,2))+1,1),Expense_Input!$H$4:$H$500,"Personal Expense",Expense_Input!$E$4:$E$500,$A55) -> 100 | C55: =SUMIFS(Expense_Input!$D$4:$D$500,Expense_Input!$B$4:$B$500,">="&DATE(VALUE(LEFT(C$44,4)),VALUE(RIGHT(C$44,2)),1),Expense_Input!$B$4:$B$500,"<"&DATE(VALUE(LEFT(C$44,4)),VALUE(RIGHT(C$44,2))+1,1),Expense_Input!$H$4:$H$500,"Personal Expense",Expense_Input!$E$4:$E$500,$A55) -> 120 | D55: =SUMIFS(Expense_Input!$D$4:$D$500,Expense_Input!$B$4:$B$500,">="&DATE(VALUE(LEFT(D$44,4)),VALUE(RIGHT(D$44,2)),1),Expense_Input!$B$4:$B$500,"<"&DATE(VALUE(LEFT(D$44,4)),VALUE(RIGHT(D$44,2))+1,1),Expense_Input!$H$4:$H$500,"Personal Expense",Expense_Input!$E$4:$E$500,$A55) -> 0 | E55: =SUMIFS(Expense_Input!$D$4:$D$500,Expense_Input!$B$4:$B$500,">="&DATE(VALUE(LEFT(E$44,4)),VALUE(RIGHT(E$44,2)),1),Expense_Input!$B$4:$B$500,"<"&DATE(VALUE(LEFT(E$44,4)),VALUE(RIGHT(E$44,2))+1,1),Expense_Input!$H$4:$H$500,"Personal Expense",Expense_Input!$E$4:$E$500,$A55) -> 0 | F55: =SUMIFS(Expense_Input!$D$4:$D$500,Expense_Input!$B$4:$B$500,">="&DATE(VALUE(LEFT(F$44,4)),VALUE(RIGHT(F$44,2)),1),Expense_Input!$B$4:$B$500,"<"&DATE(VALUE(LEFT(F$44,4)),VALUE(RIGHT(F$44,2))+1,1),Expense_Input!$H$4:$H$500,"Personal Expense",Expense_Input!$E$4:$E$500,$A55) -> 0 | G55: =SUMIFS(Expense_Input!$D$4:$D$500,Expense_Input!$B$4:$B$500,">="&DATE(VALUE(LEFT(G$44,4)),VALUE(RIGHT(G$44,2)),1),Expense_Input!$B$4:$B$500,"<"&DATE(VALUE(LEFT(G$44,4)),VALUE(RIGHT(G$44,2))+1,1),Expense_Input!$H$4:$H$500,"Personal Expense",Expense_Input!$E$4:$E$500,$A55) -> 0 | H55: =SUMIFS(Expense_Input!$D$4:$D$500,Expense_Input!$B$4:$B$500,">="&DATE(VALUE(LEFT(H$44,4)),VALUE(RIGHT(H$44,2)),1),Expense_Input!$B$4:$B$500,"<"&DATE(VALUE(LEFT(H$44,4)),VALUE(RIGHT(H$44,2))+1,1),Expense_Input!$H$4:$H$500,"Personal Expense",Expense_Input!$E$4:$E$500,$A55) -> 0 | I55: =SUMIFS(Expense_Input!$D$4:$D$500,Expense_Input!$B$4:$B$500,">="&DATE(VALUE(LEFT(I$44,4)),VALUE(RIGHT(I$44,2)),1),Expense_Input!$B$4:$B$500,"<"&DATE(VALUE(LEFT(I$44,4)),VALUE(RIGHT(I$44,2))+1,1),Expense_Input!$H$4:$H$500,"Personal Expense",Expense_Input!$E$4:$E$500,$A55) -> 0 | ... M55: =SUMIFS(Expense_Input!$D$4:$D$500,Expense_Input!$B$4:$B$500,">="&DATE(VALUE(LEFT(M$44,4)),VALUE(RIGHT(M$44,2)),1),Expense_Input!$B$4:$B$500,"<"&DATE(VALUE(LEFT(M$44,4)),VALUE(RIGHT(M$44,2))+1,1),Expense_Input!$H$4:$H$500,"Personal Expense",Expense_Input!$E$4:$E$500,$A55) -> 0 | N55: =IF($B$4=0,0,SUM(B55:M55)/$B$4) -> 110 | O55: =N55*12 -> 1320 | P55: =IFERROR(N55/$B$7,0) -> 0.021359223
A56: Taxes & Gov Fees | B56: =SUMIFS(Expense_Input!$D$4:$D$500,Expense_Input!$B$4:$B$500,">="&DATE(VALUE(LEFT(B$44,4)),VALUE(RIGHT(B$44,2)),1),Expense_Input!$B$4:$B$500,"<"&DATE(VALUE(LEFT(B$44,4)),VALUE(RIGHT(B$44,2))+1,1),Expense_Input!$H$4:$H$500,"Personal Expense",Expense_Input!$E$4:$E$500,$A56) -> 100 | C56: =SUMIFS(Expense_Input!$D$4:$D$500,Expense_Input!$B$4:$B$500,">="&DATE(VALUE(LEFT(C$44,4)),VALUE(RIGHT(C$44,2)),1),Expense_Input!$B$4:$B$500,"<"&DATE(VALUE(LEFT(C$44,4)),VALUE(RIGHT(C$44,2))+1,1),Expense_Input!$H$4:$H$500,"Personal Expense",Expense_Input!$E$4:$E$500,$A56) -> 150 | D56: =SUMIFS(Expense_Input!$D$4:$D$500,Expense_Input!$B$4:$B$500,">="&DATE(VALUE(LEFT(D$44,4)),VALUE(RIGHT(D$44,2)),1),Expense_Input!$B$4:$B$500,"<"&DATE(VALUE(LEFT(D$44,4)),VALUE(RIGHT(D$44,2))+1,1),Expense_Input!$H$4:$H$500,"Personal Expense",Expense_Input!$E$4:$E$500,$A56) -> 0 | E56: =SUMIFS(Expense_Input!$D$4:$D$500,Expense_Input!$B$4:$B$500,">="&DATE(VALUE(LEFT(E$44,4)),VALUE(RIGHT(E$44,2)),1),Expense_Input!$B$4:$B$500,"<"&DATE(VALUE(LEFT(E$44,4)),VALUE(RIGHT(E$44,2))+1,1),Expense_Input!$H$4:$H$500,"Personal Expense",Expense_Input!$E$4:$E$500,$A56) -> 0 | F56: =SUMIFS(Expense_Input!$D$4:$D$500,Expense_Input!$B$4:$B$500,">="&DATE(VALUE(LEFT(F$44,4)),VALUE(RIGHT(F$44,2)),1),Expense_Input!$B$4:$B$500,"<"&DATE(VALUE(LEFT(F$44,4)),VALUE(RIGHT(F$44,2))+1,1),Expense_Input!$H$4:$H$500,"Personal Expense",Expense_Input!$E$4:$E$500,$A56) -> 0 | G56: =SUMIFS(Expense_Input!$D$4:$D$500,Expense_Input!$B$4:$B$500,">="&DATE(VALUE(LEFT(G$44,4)),VALUE(RIGHT(G$44,2)),1),Expense_Input!$B$4:$B$500,"<"&DATE(VALUE(LEFT(G$44,4)),VALUE(RIGHT(G$44,2))+1,1),Expense_Input!$H$4:$H$500,"Personal Expense",Expense_Input!$E$4:$E$500,$A56) -> 0 | H56: =SUMIFS(Expense_Input!$D$4:$D$500,Expense_Input!$B$4:$B$500,">="&DATE(VALUE(LEFT(H$44,4)),VALUE(RIGHT(H$44,2)),1),Expense_Input!$B$4:$B$500,"<"&DATE(VALUE(LEFT(H$44,4)),VALUE(RIGHT(H$44,2))+1,1),Expense_Input!$H$4:$H$500,"Personal Expense",Expense_Input!$E$4:$E$500,$A56) -> 0 | I56: =SUMIFS(Expense_Input!$D$4:$D$500,Expense_Input!$B$4:$B$500,">="&DATE(VALUE(LEFT(I$44,4)),VALUE(RIGHT(I$44,2)),1),Expense_Input!$B$4:$B$500,"<"&DATE(VALUE(LEFT(I$44,4)),VALUE(RIGHT(I$44,2))+1,1),Expense_Input!$H$4:$H$500,"Personal Expense",Expense_Input!$E$4:$E$500,$A56) -> 0 | ... M56: =SUMIFS(Expense_Input!$D$4:$D$500,Expense_Input!$B$4:$B$500,">="&DATE(VALUE(LEFT(M$44,4)),VALUE(RIGHT(M$44,2)),1),Expense_Input!$B$4:$B$500,"<"&DATE(VALUE(LEFT(M$44,4)),VALUE(RIGHT(M$44,2))+1,1),Expense_Input!$H$4:$H$500,"Personal Expense",Expense_Input!$E$4:$E$500,$A56) -> 0 | N56: =IF($B$4=0,0,SUM(B56:M56)/$B$4) -> 125 | O56: =N56*12 -> 1500 | P56: =IFERROR(N56/$B$7,0) -> 0.024271845
A57: Other | B57: =SUMIFS(Expense_Input!$D$4:$D$500,Expense_Input!$B$4:$B$500,">="&DATE(VALUE(LEFT(B$44,4)),VALUE(RIGHT(B$44,2)),1),Expense_Input!$B$4:$B$500,"<"&DATE(VALUE(LEFT(B$44,4)),VALUE(RIGHT(B$44,2))+1,1),Expense_Input!$H$4:$H$500,"Personal Expense",Expense_Input!$E$4:$E$500,$A57) -> 110 | C57: =SUMIFS(Expense_Input!$D$4:$D$500,Expense_Input!$B$4:$B$500,">="&DATE(VALUE(LEFT(C$44,4)),VALUE(RIGHT(C$44,2)),1),Expense_Input!$B$4:$B$500,"<"&DATE(VALUE(LEFT(C$44,4)),VALUE(RIGHT(C$44,2))+1,1),Expense_Input!$H$4:$H$500,"Personal Expense",Expense_Input!$E$4:$E$500,$A57) -> 85 | D57: =SUMIFS(Expense_Input!$D$4:$D$500,Expense_Input!$B$4:$B$500,">="&DATE(VALUE(LEFT(D$44,4)),VALUE(RIGHT(D$44,2)),1),Expense_Input!$B$4:$B$500,"<"&DATE(VALUE(LEFT(D$44,4)),VALUE(RIGHT(D$44,2))+1,1),Expense_Input!$H$4:$H$500,"Personal Expense",Expense_Input!$E$4:$E$500,$A57) -> 0 | E57: =SUMIFS(Expense_Input!$D$4:$D$500,Expense_Input!$B$4:$B$500,">="&DATE(VALUE(LEFT(E$44,4)),VALUE(RIGHT(E$44,2)),1),Expense_Input!$B$4:$B$500,"<"&DATE(VALUE(LEFT(E$44,4)),VALUE(RIGHT(E$44,2))+1,1),Expense_Input!$H$4:$H$500,"Personal Expense",Expense_Input!$E$4:$E$500,$A57) -> 0 | F57: =SUMIFS(Expense_Input!$D$4:$D$500,Expense_Input!$B$4:$B$500,">="&DATE(VALUE(LEFT(F$44,4)),VALUE(RIGHT(F$44,2)),1),Expense_Input!$B$4:$B$500,"<"&DATE(VALUE(LEFT(F$44,4)),VALUE(RIGHT(F$44,2))+1,1),Expense_Input!$H$4:$H$500,"Personal Expense",Expense_Input!$E$4:$E$500,$A57) -> 0 | G57: =SUMIFS(Expense_Input!$D$4:$D$500,Expense_Input!$B$4:$B$500,">="&DATE(VALUE(LEFT(G$44,4)),VALUE(RIGHT(G$44,2)),1),Expense_Input!$B$4:$B$500,"<"&DATE(VALUE(LEFT(G$44,4)),VALUE(RIGHT(G$44,2))+1,1),Expense_Input!$H$4:$H$500,"Personal Expense",Expense_Input!$E$4:$E$500,$A57) -> 0 | H57: =SUMIFS(Expense_Input!$D$4:$D$500,Expense_Input!$B$4:$B$500,">="&DATE(VALUE(LEFT(H$44,4)),VALUE(RIGHT(H$44,2)),1),Expense_Input!$B$4:$B$500,"<"&DATE(VALUE(LEFT(H$44,4)),VALUE(RIGHT(H$44,2))+1,1),Expense_Input!$H$4:$H$500,"Personal Expense",Expense_Input!$E$4:$E$500,$A57) -> 0 | I57: =SUMIFS(Expense_Input!$D$4:$D$500,Expense_Input!$B$4:$B$500,">="&DATE(VALUE(LEFT(I$44,4)),VALUE(RIGHT(I$44,2)),1),Expense_Input!$B$4:$B$500,"<"&DATE(VALUE(LEFT(I$44,4)),VALUE(RIGHT(I$44,2))+1,1),Expense_Input!$H$4:$H$500,"Personal Expense",Expense_Input!$E$4:$E$500,$A57) -> 0 | ... M57: =SUMIFS(Expense_Input!$D$4:$D$500,Expense_Input!$B$4:$B$500,">="&DATE(VALUE(LEFT(M$44,4)),VALUE(RIGHT(M$44,2)),1),Expense_Input!$B$4:$B$500,"<"&DATE(VALUE(LEFT(M$44,4)),VALUE(RIGHT(M$44,2))+1,1),Expense_Input!$H$4:$H$500,"Personal Expense",Expense_Input!$E$4:$E$500,$A57) -> 0 | N57: =IF($B$4=0,0,SUM(B57:M57)/$B$4) -> 97.5 | O57: =N57*12 -> 1170 | P57: =IFERROR(N57/$B$7,0) -> 0.018932039
A63: Scenario | B63: Monthly Baseline | C63: Annual Baseline | D63: Description
A64: Lean Essential Living | B64: =B8 -> 4000 | C64: =B64*12 -> 48000 | D64: Minimum living floor based only on essential expenses
A65: Normal Current Lifestyle | B65: =B7 -> 5150 | C65: =B65*12 -> 61800 | D65: Based on current average personal expense
A66: Conservative Stress Case | B66: =MAX($C$28:$C$39) -> 5300 | C66: =B66*12 -> 63600 | D66: Uses the highest monthly spending level as a stress test

Sheet Sales_Tax_Detail
A1: Sales Tax Calculation Detail
A2: Reads Expense_Input and estimates GST/QST by tax type.
A3: Record ID | B3: Date | C3: Month | D3: Expense Description | E3: Expense Amount | F3: Main Category | G3: Analysis Scope | H3: Tax Type Input | I3: Default Tax Type | J3: Final Tax Type | K3: Taxable? | L3: Taxable Spending | M3: Zero-rated Spending | N3: Exempt Spending | O3: Other / N.A. | P3: Pre-tax Amount | Q3: Federal Tax Estimate | R3: Provincial Tax Estimate | S3: Estimated Sales Tax
A4: =IF(Expense_Input!A4="","",Expense_Input!A4) -> EXP-0001 | B4: =IF(Expense_Input!B4="","",Expense_Input!B4) -> 46023 | C4: =IF(B4="","",TEXT(B4,"yyyy-mm")) -> 2026-01 | D4: =IF(Expense_Input!C4="","",Expense_Input!C4) -> Rent | E4: =IF(Expense_Input!D4="","",Expense_Input!D4) -> 3000 | F4: =IF(Expense_Input!E4="","",Expense_Input!E4) -> Housing | G4: =IF(Expense_Input!H4="","",Expense_Input!H4) -> Personal Expense | H4: =IF(Expense_Input!I4="","Auto",Expense_Input!I4) -> Exempt | I4: =IF(F4="","",IFERROR(VLOOKUP(F4,Sales_Tax_Settings!$A$15:$B$27,2,FALSE),"Tax Unknown")) -> Exempt | J4: =IF(D4="","",IF(H4="Auto",I4,H4)) -> Exempt | K4: =IF(AND(Sales_Tax_Settings!$B$5="Yes",G4="Personal Expense",J4="Taxable"),"Yes","No") -> No | L4: =IF(K4="Yes",E4,0) -> 0 | M4: =IF(AND(G4="Personal Expense",J4="Zero-rated"),E4,0) -> 0 | N4: =IF(AND(G4="Personal Expense",J4="Exempt"),E4,0) -> 3000 | O4: =IF(AND(G4="Personal Expense",OR(J4="Tax Unknown",J4="Not Applicable")),E4,0) -> 0 | P4: =IF(K4<>"Yes",0,IF(Sales_Tax_Settings!$B$6="Yes",E4/(1+Sales_Tax_Settings!$B$10),E4)) -> 0 | Q4: =IF(K4<>"Yes",0,P4*Sales_Tax_Settings!$B$8) -> 0 | R4: =IF(K4<>"Yes",0,P4*Sales_Tax_Settings!$B$9) -> 0 | S4: =Q4+R4 -> 0
A5: =IF(Expense_Input!A5="","",Expense_Input!A5) -> EXP-0002 | B5: =IF(Expense_Input!B5="","",Expense_Input!B5) -> 46025 | C5: =IF(B5="","",TEXT(B5,"yyyy-mm")) -> 2026-01 | D5: =IF(Expense_Input!C5="","",Expense_Input!C5) -> Basic groceries | E5: =IF(Expense_Input!D5="","",Expense_Input!D5) -> 450 | F5: =IF(Expense_Input!E5="","",Expense_Input!E5) -> Food & Dining | G5: =IF(Expense_Input!H5="","",Expense_Input!H5) -> Personal Expense | H5: =IF(Expense_Input!I5="","Auto",Expense_Input!I5) -> Zero-rated | I5: =IF(F5="","",IFERROR(VLOOKUP(F5,Sales_Tax_Settings!$A$15:$B$27,2,FALSE),"Tax Unknown")) -> Taxable | J5: =IF(D5="","",IF(H5="Auto",I5,H5)) -> Zero-rated | K5: =IF(AND(Sales_Tax_Settings!$B$5="Yes",G5="Personal Expense",J5="Taxable"),"Yes","No") -> No | L5: =IF(K5="Yes",E5,0) -> 0 | M5: =IF(AND(G5="Personal Expense",J5="Zero-rated"),E5,0) -> 450 | N5: =IF(AND(G5="Personal Expense",J5="Exempt"),E5,0) -> 0 | O5: =IF(AND(G5="Personal Expense",OR(J5="Tax Unknown",J5="Not Applicable")),E5,0) -> 0 | P5: =IF(K5<>"Yes",0,IF(Sales_Tax_Settings!$B$6="Yes",E5/(1+Sales_Tax_Settings!$B$10),E5)) -> 0 | Q5: =IF(K5<>"Yes",0,P5*Sales_Tax_Settings!$B$8) -> 0 | R5: =IF(K5<>"Yes",0,P5*Sales_Tax_Settings!$B$9) -> 0 | S5: =Q5+R5 -> 0
A6: =IF(Expense_Input!A6="","",Expense_Input!A6) -> EXP-0003 | B6: =IF(Expense_Input!B6="","",Expense_Input!B6) -> 46027 | C6: =IF(B6="","",TEXT(B6,"yyyy-mm")) -> 2026-01 | D6: =IF(Expense_Input!C6="","",Expense_Input!C6) -> Restaurant dining | E6: =IF(Expense_Input!D6="","",Expense_Input!D6) -> 320 | F6: =IF(Expense_Input!E6="","",Expense_Input!E6) -> Food & Dining | G6: =IF(Expense_Input!H6="","",Expense_Input!H6) -> Personal Expense | H6: =IF(Expense_Input!I6="","Auto",Expense_Input!I6) -> Taxable | I6: =IF(F6="","",IFERROR(VLOOKUP(F6,Sales_Tax_Settings!$A$15:$B$27,2,FALSE),"Tax Unknown")) -> Taxable | J6: =IF(D6="","",IF(H6="Auto",I6,H6)) -> Taxable | K6: =IF(AND(Sales_Tax_Settings!$B$5="Yes",G6="Personal Expense",J6="Taxable"),"Yes","No") -> Yes | L6: =IF(K6="Yes",E6,0) -> 320 | M6: =IF(AND(G6="Personal Expense",J6="Zero-rated"),E6,0) -> 0 | N6: =IF(AND(G6="Personal Expense",J6="Exempt"),E6,0) -> 0 | O6: =IF(AND(G6="Personal Expense",OR(J6="Tax Unknown",J6="Not Applicable")),E6,0) -> 0 | P6: =IF(K6<>"Yes",0,IF(Sales_Tax_Settings!$B$6="Yes",E6/(1+Sales_Tax_Settings!$B$10),E6)) -> 278.32137 | Q6: =IF(K6<>"Yes",0,P6*Sales_Tax_Settings!$B$8) -> 13.916069 | R6: =IF(K6<>"Yes",0,P6*Sales_Tax_Settings!$B$9) -> 27.762557 | S6: =Q6+R6 -> 41.678626
A7: =IF(Expense_Input!A7="","",Expense_Input!A7) -> EXP-0004 | B7: =IF(Expense_Input!B7="","",Expense_Input!B7) -> 46029 | C7: =IF(B7="","",TEXT(B7,"yyyy-mm")) -> 2026-01 | D7: =IF(Expense_Input!C7="","",Expense_Input!C7) -> Gas | E7: =IF(Expense_Input!D7="","",Expense_Input!D7) -> 220 | F7: =IF(Expense_Input!E7="","",Expense_Input!E7) -> Transportation | G7: =IF(Expense_Input!H7="","",Expense_Input!H7) -> Personal Expense | H7: =IF(Expense_Input!I7="","Auto",Expense_Input!I7) -> Taxable | I7: =IF(F7="","",IFERROR(VLOOKUP(F7,Sales_Tax_Settings!$A$15:$B$27,2,FALSE),"Tax Unknown")) -> Taxable | J7: =IF(D7="","",IF(H7="Auto",I7,H7)) -> Taxable | K7: =IF(AND(Sales_Tax_Settings!$B$5="Yes",G7="Personal Expense",J7="Taxable"),"Yes","No") -> Yes | L7: =IF(K7="Yes",E7,0) -> 220 | M7: =IF(AND(G7="Personal Expense",J7="Zero-rated"),E7,0) -> 0 | N7: =IF(AND(G7="Personal Expense",J7="Exempt"),E7,0) -> 0 | O7: =IF(AND(G7="Personal Expense",OR(J7="Tax Unknown",J7="Not Applicable")),E7,0) -> 0 | P7: =IF(K7<>"Yes",0,IF(Sales_Tax_Settings!$B$6="Yes",E7/(1+Sales_Tax_Settings!$B$10),E7)) -> 191.34594 | Q7: =IF(K7<>"Yes",0,P7*Sales_Tax_Settings!$B$8) -> 9.5672972 | R7: =IF(K7<>"Yes",0,P7*Sales_Tax_Settings!$B$9) -> 19.086758 | S7: =Q7+R7 -> 28.654055
A8: =IF(Expense_Input!A8="","",Expense_Input!A8) -> EXP-0005 | B8: =IF(Expense_Input!B8="","",Expense_Input!B8) -> 46030 | C8: =IF(B8="","",TEXT(B8,"yyyy-mm")) -> 2026-01 | D8: =IF(Expense_Input!C8="","",Expense_Input!C8) -> Mobile phone plan | E8: =IF(Expense_Input!D8="","",Expense_Input!D8) -> 60 | F8: =IF(Expense_Input!E8="","",Expense_Input!E8) -> Telecom | G8: =IF(Expense_Input!H8="","",Expense_Input!H8) -> Personal Expense | H8: =IF(Expense_Input!I8="","Auto",Expense_Input!I8) -> Taxable | I8: =IF(F8="","",IFERROR(VLOOKUP(F8,Sales_Tax_Settings!$A$15:$B$27,2,FALSE),"Tax Unknown")) -> Taxable | J8: =IF(D8="","",IF(H8="Auto",I8,H8)) -> Taxable | K8: =IF(AND(Sales_Tax_Settings!$B$5="Yes",G8="Personal Expense",J8="Taxable"),"Yes","No") -> Yes | L8: =IF(K8="Yes",E8,0) -> 60 | M8: =IF(AND(G8="Personal Expense",J8="Zero-rated"),E8,0) -> 0 | N8: =IF(AND(G8="Personal Expense",J8="Exempt"),E8,0) -> 0 | O8: =IF(AND(G8="Personal Expense",OR(J8="Tax Unknown",J8="Not Applicable")),E8,0) -> 0 | P8: =IF(K8<>"Yes",0,IF(Sales_Tax_Settings!$B$6="Yes",E8/(1+Sales_Tax_Settings!$B$10),E8)) -> 52.185258 | Q8: =IF(K8<>"Yes",0,P8*Sales_Tax_Settings!$B$8) -> 2.6092629 | R8: =IF(K8<>"Yes",0,P8*Sales_Tax_Settings!$B$9) -> 5.2054795 | S8: =Q8+R8 -> 7.8147423
A9: =IF(Expense_Input!A9="","",Expense_Input!A9) -> EXP-0006 | B9: =IF(Expense_Input!B9="","",Expense_Input!B9) -> 46031 | C9: =IF(B9="","",TEXT(B9,"yyyy-mm")) -> 2026-01 | D9: =IF(Expense_Input!C9="","",Expense_Input!C9) -> Cloud subscription | E9: =IF(Expense_Input!D9="","",Expense_Input!D9) -> 30 | F9: =IF(Expense_Input!E9="","",Expense_Input!E9) -> Subscriptions | G9: =IF(Expense_Input!H9="","",Expense_Input!H9) -> Personal Expense | H9: =IF(Expense_Input!I9="","Auto",Expense_Input!I9) -> Taxable | I9: =IF(F9="","",IFERROR(VLOOKUP(F9,Sales_Tax_Settings!$A$15:$B$27,2,FALSE),"Tax Unknown")) -> Taxable | J9: =IF(D9="","",IF(H9="Auto",I9,H9)) -> Taxable | K9: =IF(AND(Sales_Tax_Settings!$B$5="Yes",G9="Personal Expense",J9="Taxable"),"Yes","No") -> Yes | L9: =IF(K9="Yes",E9,0) -> 30 | M9: =IF(AND(G9="Personal Expense",J9="Zero-rated"),E9,0) -> 0 | N9: =IF(AND(G9="Personal Expense",J9="Exempt"),E9,0) -> 0 | O9: =IF(AND(G9="Personal Expense",OR(J9="Tax Unknown",J9="Not Applicable")),E9,0) -> 0 | P9: =IF(K9<>"Yes",0,IF(Sales_Tax_Settings!$B$6="Yes",E9/(1+Sales_Tax_Settings!$B$10),E9)) -> 26.092629 | Q9: =IF(K9<>"Yes",0,P9*Sales_Tax_Settings!$B$8) -> 1.3046314 | R9: =IF(K9<>"Yes",0,P9*Sales_Tax_Settings!$B$9) -> 2.6027397 | S9: =Q9+R9 -> 3.9073712
A10: =IF(Expense_Input!A10="","",Expense_Input!A10) -> EXP-0007 | B10: =IF(Expense_Input!B10="","",Expense_Input!B10) -> 46032 | C10: =IF(B10="","",TEXT(B10,"yyyy-mm")) -> 2026-01 | D10: =IF(Expense_Input!C10="","",Expense_Input!C10) -> Shopping | E10: =IF(Expense_Input!D10="","",Expense_Input!D10) -> 250 | F10: =IF(Expense_Input!E10="","",Expense_Input!E10) -> Shopping | G10: =IF(Expense_Input!H10="","",Expense_Input!H10) -> Personal Expense | H10: =IF(Expense_Input!I10="","Auto",Expense_Input!I10) -> Taxable | I10: =IF(F10="","",IFERROR(VLOOKUP(F10,Sales_Tax_Settings!$A$15:$B$27,2,FALSE),"Tax Unknown")) -> Taxable | J10: =IF(D10="","",IF(H10="Auto",I10,H10)) -> Taxable | K10: =IF(AND(Sales_Tax_Settings!$B$5="Yes",G10="Personal Expense",J10="Taxable"),"Yes","No") -> Yes | L10: =IF(K10="Yes",E10,0) -> 250 | M10: =IF(AND(G10="Personal Expense",J10="Zero-rated"),E10,0) -> 0 | N10: =IF(AND(G10="Personal Expense",J10="Exempt"),E10,0) -> 0 | O10: =IF(AND(G10="Personal Expense",OR(J10="Tax Unknown",J10="Not Applicable")),E10,0) -> 0 | P10: =IF(K10<>"Yes",0,IF(Sales_Tax_Settings!$B$6="Yes",E10/(1+Sales_Tax_Settings!$B$10),E10)) -> 217.43857 | Q10: =IF(K10<>"Yes",0,P10*Sales_Tax_Settings!$B$8) -> 10.871929 | R10: =IF(K10<>"Yes",0,P10*Sales_Tax_Settings!$B$9) -> 21.689498 | S10: =Q10+R10 -> 32.561426
A11: =IF(Expense_Input!A11="","",Expense_Input!A11) -> EXP-0008 | B11: =IF(Expense_Input!B11="","",Expense_Input!B11) -> 46034 | C11: =IF(B11="","",TEXT(B11,"yyyy-mm")) -> 2026-01 | D11: =IF(Expense_Input!C11="","",Expense_Input!C11) -> Medical supplies | E11: =IF(Expense_Input!D11="","",Expense_Input!D11) -> 80 | F11: =IF(Expense_Input!E11="","",Expense_Input!E11) -> Medical | G11: =IF(Expense_Input!H11="","",Expense_Input!H11) -> Personal Expense | H11: =IF(Expense_Input!I11="","Auto",Expense_Input!I11) -> Exempt | I11: =IF(F11="","",IFERROR(VLOOKUP(F11,Sales_Tax_Settings!$A$15:$B$27,2,FALSE),"Tax Unknown")) -> Exempt | J11: =IF(D11="","",IF(H11="Auto",I11,H11)) -> Exempt | K11: =IF(AND(Sales_Tax_Settings!$B$5="Yes",G11="Personal Expense",J11="Taxable"),"Yes","No") -> No | L11: =IF(K11="Yes",E11,0) -> 0 | M11: =IF(AND(G11="Personal Expense",J11="Zero-rated"),E11,0) -> 0 | N11: =IF(AND(G11="Personal Expense",J11="Exempt"),E11,0) -> 80 | O11: =IF(AND(G11="Personal Expense",OR(J11="Tax Unknown",J11="Not Applicable")),E11,0) -> 0 | P11: =IF(K11<>"Yes",0,IF(Sales_Tax_Settings!$B$6="Yes",E11/(1+Sales_Tax_Settings!$B$10),E11)) -> 0 | Q11: =IF(K11<>"Yes",0,P11*Sales_Tax_Settings!$B$8) -> 0 | R11: =IF(K11<>"Yes",0,P11*Sales_Tax_Settings!$B$9) -> 0 | S11: =Q11+R11 -> 0
A12: =IF(Expense_Input!A12="","",Expense_Input!A12) -> EXP-0009 | B12: =IF(Expense_Input!B12="","",Expense_Input!B12) -> 46037 | C12: =IF(B12="","",TEXT(B12,"yyyy-mm")) -> 2026-01 | D12: =IF(Expense_Input!C12="","",Expense_Input!C12) -> Gym membership | E12: =IF(Expense_Input!D12="","",Expense_Input!D12) -> 70 | F12: =IF(Expense_Input!E12="","",Expense_Input!E12) -> Fitness | G12: =IF(Expense_Input!H12="","",Expense_Input!H12) -> Personal Expense | H12: =IF(Expense_Input!I12="","Auto",Expense_Input!I12) -> Taxable | I12: =IF(F12="","",IFERROR(VLOOKUP(F12,Sales_Tax_Settings!$A$15:$B$27,2,FALSE),"Tax Unknown")) -> Taxable | J12: =IF(D12="","",IF(H12="Auto",I12,H12)) -> Taxable | K12: =IF(AND(Sales_Tax_Settings!$B$5="Yes",G12="Personal Expense",J12="Taxable"),"Yes","No") -> Yes | L12: =IF(K12="Yes",E12,0) -> 70 | M12: =IF(AND(G12="Personal Expense",J12="Zero-rated"),E12,0) -> 0 | N12: =IF(AND(G12="Personal Expense",J12="Exempt"),E12,0) -> 0 | O12: =IF(AND(G12="Personal Expense",OR(J12="Tax Unknown",J12="Not Applicable")),E12,0) -> 0 | P12: =IF(K12<>"Yes",0,IF(Sales_Tax_Settings!$B$6="Yes",E12/(1+Sales_Tax_Settings!$B$10),E12)) -> 60.882801 | Q12: =IF(K12<>"Yes",0,P12*Sales_Tax_Settings!$B$8) -> 3.04414 | R12: =IF(K12<>"Yes",0,P12*Sales_Tax_Settings!$B$9) -> 6.0730594 | S12: =Q12+R12 -> 9.1171994
A13: =IF(Expense_Input!A13="","",Expense_Input!A13) -> EXP-0010 | B13: =IF(Expense_Input!B13="","",Expense_Input!B13) -> 46038 | C13: =IF(B13="","",TEXT(B13,"yyyy-mm")) -> 2026-01 | D13: =IF(Expense_Input!C13="","",Expense_Input!C13) -> Courses and books | E13: =IF(Expense_Input!D13="","",Expense_Input!D13) -> 120 | F13: =IF(Expense_Input!E13="","",Expense_Input!E13) -> Education | G13: =IF(Expense_Input!H13="","",Expense_Input!H13) -> Personal Expense | H13: =IF(Expense_Input!I13="","Auto",Expense_Input!I13) -> Tax Unknown | I13: =IF(F13="","",IFERROR(VLOOKUP(F13,Sales_Tax_Settings!$A$15:$B$27,2,FALSE),"Tax Unknown")) -> Tax Unknown | J13: =IF(D13="","",IF(H13="Auto",I13,H13)) -> Tax Unknown | K13: =IF(AND(Sales_Tax_Settings!$B$5="Yes",G13="Personal Expense",J13="Taxable"),"Yes","No") -> No | L13: =IF(K13="Yes",E13,0) -> 0 | M13: =IF(AND(G13="Personal Expense",J13="Zero-rated"),E13,0) -> 0 | N13: =IF(AND(G13="Personal Expense",J13="Exempt"),E13,0) -> 0 | O13: =IF(AND(G13="Personal Expense",OR(J13="Tax Unknown",J13="Not Applicable")),E13,0) -> 120 | P13: =IF(K13<>"Yes",0,IF(Sales_Tax_Settings!$B$6="Yes",E13/(1+Sales_Tax_Settings!$B$10),E13)) -> 0 | Q13: =IF(K13<>"Yes",0,P13*Sales_Tax_Settings!$B$8) -> 0 | R13: =IF(K13<>"Yes",0,P13*Sales_Tax_Settings!$B$9) -> 0 | S13: =Q13+R13 -> 0
A14: =IF(Expense_Input!A14="","",Expense_Input!A14) -> EXP-0011 | B14: =IF(Expense_Input!B14="","",Expense_Input!B14) -> 46040 | C14: =IF(B14="","",TEXT(B14,"yyyy-mm")) -> 2026-01 | D14: =IF(Expense_Input!C14="","",Expense_Input!C14) -> Pet supplies | E14: =IF(Expense_Input!D14="","",Expense_Input!D14) -> 90 | F14: =IF(Expense_Input!E14="","",Expense_Input!E14) -> Pet | G14: =IF(Expense_Input!H14="","",Expense_Input!H14) -> Personal Expense | H14: =IF(Expense_Input!I14="","Auto",Expense_Input!I14) -> Taxable | I14: =IF(F14="","",IFERROR(VLOOKUP(F14,Sales_Tax_Settings!$A$15:$B$27,2,FALSE),"Tax Unknown")) -> Taxable | J14: =IF(D14="","",IF(H14="Auto",I14,H14)) -> Taxable | K14: =IF(AND(Sales_Tax_Settings!$B$5="Yes",G14="Personal Expense",J14="Taxable"),"Yes","No") -> Yes | L14: =IF(K14="Yes",E14,0) -> 90 | M14: =IF(AND(G14="Personal Expense",J14="Zero-rated"),E14,0) -> 0 | N14: =IF(AND(G14="Personal Expense",J14="Exempt"),E14,0) -> 0 | O14: =IF(AND(G14="Personal Expense",OR(J14="Tax Unknown",J14="Not Applicable")),E14,0) -> 0 | P14: =IF(K14<>"Yes",0,IF(Sales_Tax_Settings!$B$6="Yes",E14/(1+Sales_Tax_Settings!$B$10),E14)) -> 78.277886 | Q14: =IF(K14<>"Yes",0,P14*Sales_Tax_Settings!$B$8) -> 3.9138943 | R14: =IF(K14<>"Yes",0,P14*Sales_Tax_Settings!$B$9) -> 7.8082192 | S14: =Q14+R14 -> 11.722114
A15: =IF(Expense_Input!A15="","",Expense_Input!A15) -> EXP-0012 | B15: =IF(Expense_Input!B15="","",Expense_Input!B15) -> 46042 | C15: =IF(B15="","",TEXT(B15,"yyyy-mm")) -> 2026-01 | D15: =IF(Expense_Input!C15="","",Expense_Input!C15) -> Entertainment | E15: =IF(Expense_Input!D15="","",Expense_Input!D15) -> 100 | F15: =IF(Expense_Input!E15="","",Expense_Input!E15) -> Entertainment | G15: =IF(Expense_Input!H15="","",Expense_Input!H15) -> Personal Expense | H15: =IF(Expense_Input!I15="","Auto",Expense_Input!I15) -> Taxable | I15: =IF(F15="","",IFERROR(VLOOKUP(F15,Sales_Tax_Settings!$A$15:$B$27,2,FALSE),"Tax Unknown")) -> Taxable | J15: =IF(D15="","",IF(H15="Auto",I15,H15)) -> Taxable | K15: =IF(AND(Sales_Tax_Settings!$B$5="Yes",G15="Personal Expense",J15="Taxable"),"Yes","No") -> Yes | L15: =IF(K15="Yes",E15,0) -> 100 | M15: =IF(AND(G15="Personal Expense",J15="Zero-rated"),E15,0) -> 0 | N15: =IF(AND(G15="Personal Expense",J15="Exempt"),E15,0) -> 0 | O15: =IF(AND(G15="Personal Expense",OR(J15="Tax Unknown",J15="Not Applicable")),E15,0) -> 0 | P15: =IF(K15<>"Yes",0,IF(Sales_Tax_Settings!$B$6="Yes",E15/(1+Sales_Tax_Settings!$B$10),E15)) -> 86.975429 | Q15: =IF(K15<>"Yes",0,P15*Sales_Tax_Settings!$B$8) -> 4.3487715 | R15: =IF(K15<>"Yes",0,P15*Sales_Tax_Settings!$B$9) -> 8.6757991 | S15: =Q15+R15 -> 13.024571
... A500: =IF(Expense_Input!A500="","",Expense_Input!A500) | B500: =IF(Expense_Input!B500="","",Expense_Input!B500) | C500: =IF(B500="","",TEXT(B500,"yyyy-mm")) | D500: =IF(Expense_Input!C500="","",Expense_Input!C500) | E500: =IF(Expense_Input!D500="","",Expense_Input!D500) | F500: =IF(Expense_Input!E500="","",Expense_Input!E500) | G500: =IF(Expense_Input!H500="","",Expense_Input!H500) | H500: =IF(Expense_Input!I500="","Auto",Expense_Input!I500) -> Auto | I500: =IF(F500="","",IFERROR(VLOOKUP(F500,Sales_Tax_Settings!$A$15:$B$27,2,FALSE),"Tax Unknown")) | J500: =IF(D500="","",IF(H500="Auto",I500,H500)) | K500: =IF(AND(Sales_Tax_Settings!$B$5="Yes",G500="Personal Expense",J500="Taxable"),"Yes","No") -> No | L500: =IF(K500="Yes",E500,0) -> 0 | M500: =IF(AND(G500="Personal Expense",J500="Zero-rated"),E500,0) -> 0 | N500: =IF(AND(G500="Personal Expense",J500="Exempt"),E500,0) -> 0 | O500: =IF(AND(G500="Personal Expense",OR(J500="Tax Unknown",J500="Not Applicable")),E500,0) -> 0 | P500: =IF(K500<>"Yes",0,IF(Sales_Tax_Settings!$B$6="Yes",E500/(1+Sales_Tax_Settings!$B$10),E500)) -> 0 | Q500: =IF(K500<>"Yes",0,P500*Sales_Tax_Settings!$B$8) -> 0 | R500: =IF(K500<>"Yes",0,P500*Sales_Tax_Settings!$B$9) -> 0 | S500: =Q500+R500 -> 0

Sheet Annual_Projection
A1: Annual Spending Projection
A2: Display sheet: scenarios.
A3: Scenario | B3: Monthly Baseline | C3: Annual Baseline | D3: Description
A4: =Formula_Hub!A64 -> Lean Essential Living | B4: =Formula_Hub!B64 -> 4000 | C4: =Formula_Hub!C64 -> 48000 | D4: =Formula_Hub!D64 -> Minimum living floor based only on essential expenses
A5: =Formula_Hub!A65 -> Normal Current Lifestyle | B5: =Formula_Hub!B65 -> 5150 | C5: =Formula_Hub!C65 -> 61800 | D5: =Formula_Hub!D65 -> Based on current average personal expense
A6: =Formula_Hub!A66 -> Conservative Stress Case | B6: =Formula_Hub!B66 -> 5300 | C6: =Formula_Hub!C66 -> 63600 | D6: =Formula_Hub!D66 -> Uses the highest monthly spending level as a stress test

Sheet Emergency_Fund
A1: Emergency Fund Analysis
A2: Reserve needs based on spending scenarios.
A3: Baseline | B3: Monthly Expense | C3: 3 Months | D3: 6 Months | E3: 12 Months | F3: Custom Months
A4: Essential Living | B4: =Formula_Hub!$B$8 -> 4000 | C4: =B4*3 -> 12000 | D4: =B4*6 -> 24000 | E4: =B4*12 -> 48000 | F4: =B4*Input_Settings!$B$8 -> 48000
A5: Current Lifestyle | B5: =Formula_Hub!$B$7 -> 5150 | C5: =B5*3 -> 15450 | D5: =B5*6 -> 30900 | E5: =B5*12 -> 61800 | F5: =B5*Input_Settings!$B$8 -> 61800
A6: Conservative Stress | B6: =MAX(Formula_Hub!$C$28:$C$39) -> 5300 | C6: =B6*3 -> 15900 | D6: =B6*6 -> 31800 | E6: =B6*12 -> 63600 | F6: =B6*Input_Settings!$B$8 -> 63600

Sheet Investable_Cash
A1: Investable Cash
A2: Estimate investable cash from current cash and reserve.
A3: Item | B3: Value | C3: Description
A4: Current Available Cash | B4: =Input_Settings!$B$5 -> 30000 | C4: From Input_Settings
A5: Recommended Cash Reserve | B5: =Formula_Hub!$B$20 -> 62800 | C5: Based on reserve rules
A6: Suggested Investable Cash | B6: =Formula_Hub!$B$21 -> 0 | C6: Cash above reserve
A7: Cash Shortfall | B7: =Formula_Hub!$B$22 -> 32800 | C7: Reserve gap
A8: Cash Coverage Months | B8: =Formula_Hub!$B$16 -> 5.8252427 | C8: Current cash / average monthly expense
A9: Cash Safety Level | B9: =Formula_Hub!$B$23 -> Tight | C9: Based on coverage months
A10: Cash Allocation Note | B10: =IF(B7>0,"Build the cash reserve first, then consider investing",IF(B4>0,"Consider investing the amount above the reserve gradually for long-term goals","Enter current cash in Input_Settings first")) -> Build the cash reserve first, then consider investing | C10: Rule-of-thumb note

Sheet Formula_Notes
A1: Formula Notes and Maintenance Rules
A2: This sheet explains how to maintain the template.
A4: Sheet | B4: Cell / Area | C4: Formula / Logic | D4: Meaning | E4: Manual Update? | F4: Notes
A5: Expense_Input | B5: A:J | C5: User input | D5: Records all expenses. | E5: Yes | F5: Append monthly
A6: Income_Input | B6: A:F | C6: User input | D6: Records all income. | E6: Yes | F6: Append monthly
A7: Input_Settings | B7: B5:B9 | C7: User input | D7: Cash and reserve assumptions. | E7: Yes | F7: Update when assumptions change
A8: Sales_Tax_Settings | B8: B5:B10 | C8: User input + formulas | D8: Sales tax settings. | E8: Optional | F8: Adjust by province
A9: Sales_Tax_Settings | B9: A15:C27 | C9: Rule table | D9: Default tax type by category. | E9: Optional | F9: Adjust by receipt
A10: Sales_Tax_Detail | B10: A:S rows 4:500 | C10: Formulas | D10: Calculates final tax type and estimated tax. | E10: No | F10: Review only
A11: Sales_Tax_Analysis | B11: A:I | C11: SUMIFS | D11: Monthly tax summary. | E11: No | F11: Display layer
A12: Formula_Hub | B12: B4:B25 | C12: Core formulas | D12: Central calculation hub. | E12: No | F12: Display sheets reference this
A13: Formula_Hub | B13: A28:O39 | C13: SUMIFS + date window | D13: Monthly summary. | E13: No | F13: Rows 4:500
A14: Formula_Hub | B14: A44:P57 | C14: SUMIFS | D14: Category summary. | E14: No | F14: Extend if adding categories
A15: Monthly_Summary | B15: Full sheet | C15: References Formula_Hub | D15: Monthly display. | E15: No | F15: Display
... A20: Dashboard | B20: Full sheet | C20: References Formula_Hub | D20: Main dashboard. | E20: No | F20: Display
A24: Core Formula Dictionary
A25: Formula | B25: Purpose | C25: Use in this template
A26: SUMIFS | B26: Conditional aggregation | C26: Summarizes by date, scope, category, and type
A27: IF | B27: Rule logic | C27: Tax toggle, data checks, safety levels
A28: IFERROR | B28: Error handling | C28: Avoids divide-by-zero display issues
A29: VLOOKUP | B29: Default tax type lookup | C29: Finds default tax type by category
A30: MAX | B30: Larger-value selection | C30: Cash reserve and stress test
A31: DATE / LEFT / RIGHT | B31: Build date windows | C31: Generates month windows from YYYY-MM text

Sheet Lists
A1: Options and Drop-down Lists
A2: This sheet feeds data validation lists.
A4: Main Category | B4: Expense Nature | C4: Necessity | D4: Analysis Scope | E4: Tax Type | F4: Income Type | G4: Yes/No | H4: Region
A5: Housing | B5: Fixed | C5: Essential | D5: Personal Expense | E5: Auto | F5: Salary | G5: Yes | H5: Quebec
A6: Food & Dining | B6: Variable | C6: Discretionary | D6: Investment Transfer | E6: Zero-rated | F6: Scholarship | G6: No | H6: Ontario
A7: Transportation | B7: One-time | D7: Internal Transfer | E7: Taxable | F7: Government Benefit | H7: British Columbia
A8: Telecom | D8: Property Expense | E8: Exempt | F8: Investment Income | H8: Alberta
A9: Subscriptions | D9: Excluded | E9: Tax Unknown | F9: Refund | H9: Custom
A10: Shopping | E10: Not Applicable | F10: Rental Income
A11: Medical | F11: Other
A12: Fitness
A13: Education
A14: Pet
A15: Entertainment
A16: Taxes & Gov Fees
A17: Other
