Workbook

Sheet 使用说明
A1: 个人财务分析模板：极简输入 + 加拿大消费税估算版
A2: 只填写总支出、总收入、输入设置、税费设置；其他页面自动计算。
A3: 项目 | B3: 说明
A4: 使用目标 | B4: 用最少输入列记录个人收支，并自动生成月度现金流、类别占比、年度消费预测、备用金、可投资资金与消费税估算。
A5: 每月维护 | B5: 只追加新支出、新收入；必要时更新当前现金、备用金月数、税率或是否启用消费税估算。
A6: 金额规则 | B6: 支出页与收入页均填正数。
A7: 税费规则 | B7: 税费类型可选“自动”，也可手动选择零税率、应税、免税、含税不明、不适用。
A8: 示例数据 | B8: 内置2026年1月与2月示例样本；1月总支出5000，房租3000，占本月支出60%。
A10: 日常维护流程
A11: 1. 在“总支出”追加支出记录，金额填正数。
A12: 2. 在“总收入”追加收入记录，金额填正数。
A13: 3. 如现金余额、备用金月数或税率变化，更新“输入设置”和“税费设置”。
A14: 4. 查看“总览”；若需要排查，再看“公式枢纽”“税费计算明细”。
A15: 5. 消费税估算是近似分析，不等于实际退税、抵扣或福利金额。

Sheet 总览
A1: 个人财务分析总览
A2: 本页是主要查看页面；所有数字均引用公式枢纽。
A3: 平均月支出 | D3: 必要月支出 | G3: 弹性月支出 | J3: 正常一年储备
A4: =公式枢纽!$B$7 -> 5150 | D4: =公式枢纽!$B$8 -> 4000 | G4: =公式枢纽!$B$9 -> 1150 | J4: =公式枢纽!$B$17 -> 61800
A7: 现金覆盖月数 | D7: 建议可投资资金 | G7: 全年估算消费税 | J7: 消费税估算状态
A8: =公式枢纽!$B$16 -> 5.8252427 | D8: =公式枢纽!$B$21 -> 0 | G8: =公式枢纽!$B$24 -> 318.45075 | J8: =公式枢纽!$B$25 -> 已启用
A12: 判断摘要
A13: 现金安全等级 | B13: =公式枢纽!$B$23 -> 偏紧张
A14: 资金建议 | B14: =IF(公式枢纽!$B$22>0,"当前现金储备仍有缺口，优先补足备用金",IF(公式枢纽!$B$21>0,"有可考虑分批投资的资金区间","请先在输入设置填入当前现金")) -> 当前现金储备仍有缺口，优先补足备用金
A15: 消费税说明 | B15: =IF(税费设置!$B$5="是","消费税估算已启用；请注意该估算不等于实际退税或抵扣金额","消费税估算未启用") -> 消费税估算已启用；请注意该估算不等于实际退税或抵扣金额
A19: 图表数据索引：月度收支与消费税 | G19: 图表数据索引：类别月均与占比
A20: 月份 | B20: 收入 | C20: 个人支出 | D20: 估算消费税 | E20: 净现金流 | G20: 类别 | H20: 月均 | I20: 占比
A21: =每月总结!A4 -> 2026-01 | B21: =每月总结!B4 -> 6000 | C21: =每月总结!C4 -> 5000 | D21: =公式枢纽!O28 -> 148.4801 | E21: =公式枢纽!J28 -> 1000 | G21: =各类别总结!A4 -> 住房 | H21: =各类别总结!N4 -> 3000 | I21: =各类别总结!P4 -> 0.58252427
A22: =每月总结!A5 -> 2026-02 | B22: =每月总结!B5 -> 6900 | C22: =每月总结!C5 -> 5300 | D22: =公式枢纽!O29 -> 169.97065 | E22: =公式枢纽!J29 -> 1600 | G22: =各类别总结!A5 -> 餐饮 | H22: =各类别总结!N5 -> 820 | I22: =各类别总结!P5 -> 0.1592233
A23: =每月总结!A6 -> 2026-03 | B23: =每月总结!B6 -> 0 | C23: =每月总结!C6 -> 0 | D23: =公式枢纽!O30 -> 0 | E23: =公式枢纽!J30 -> 0 | G23: =各类别总结!A6 -> 交通 | H23: =各类别总结!N6 -> 240 | I23: =各类别总结!P6 -> 0.046601942
A24: =每月总结!A7 -> 2026-04 | B24: =每月总结!B7 -> 0 | C24: =每月总结!C7 -> 0 | D24: =公式枢纽!O31 -> 0 | E24: =公式枢纽!J31 -> 0 | G24: =各类别总结!A7 -> 通讯 | H24: =各类别总结!N7 -> 60 | I24: =各类别总结!P7 -> 0.011650485
A25: =每月总结!A8 -> 2026-05 | B25: =每月总结!B8 -> 0 | C25: =每月总结!C8 -> 0 | D25: =公式枢纽!O32 -> 0 | E25: =公式枢纽!J32 -> 0 | G25: =各类别总结!A8 -> 订阅 | H25: =各类别总结!N8 -> 37.5 | I25: =各类别总结!P8 -> 0.0072815534
A26: =每月总结!A9 -> 2026-06 | B26: =每月总结!B9 -> 0 | C26: =每月总结!C9 -> 0 | D26: =公式枢纽!O33 -> 0 | E26: =公式枢纽!J33 -> 0 | G26: =各类别总结!A9 -> 购物 | H26: =各类别总结!N9 -> 275 | I26: =各类别总结!P9 -> 0.053398058
A27: =每月总结!A10 -> 2026-07 | B27: =每月总结!B10 -> 0 | C27: =每月总结!C10 -> 0 | D27: =公式枢纽!O34 -> 0 | E27: =公式枢纽!J34 -> 0 | G27: =各类别总结!A10 -> 医疗 | H27: =各类别总结!N10 -> 90 | I27: =各类别总结!P10 -> 0.017475728
A28: =每月总结!A11 -> 2026-08 | B28: =每月总结!B11 -> 0 | C28: =每月总结!C11 -> 0 | D28: =公式枢纽!O35 -> 0 | E28: =公式枢纽!J35 -> 0 | G28: =各类别总结!A11 -> 运动 | H28: =各类别总结!N11 -> 70 | I28: =各类别总结!P11 -> 0.013592233
A29: =每月总结!A12 -> 2026-09 | B29: =每月总结!B12 -> 0 | C29: =每月总结!C12 -> 0 | D29: =公式枢纽!O36 -> 0 | E29: =公式枢纽!J36 -> 0 | G29: =各类别总结!A12 -> 学习 | H29: =各类别总结!N12 -> 130 | I29: =各类别总结!P12 -> 0.025242718
A30: =每月总结!A13 -> 2026-10 | B30: =每月总结!B13 -> 0 | C30: =每月总结!C13 -> 0 | D30: =公式枢纽!O37 -> 0 | E30: =公式枢纽!J37 -> 0 | G30: =各类别总结!A13 -> 宠物 | H30: =各类别总结!N13 -> 95 | I30: =各类别总结!P13 -> 0.018446602
A31: =每月总结!A14 -> 2026-11 | B31: =每月总结!B14 -> 0 | C31: =每月总结!C14 -> 0 | D31: =公式枢纽!O38 -> 0 | E31: =公式枢纽!J38 -> 0 | G31: =各类别总结!A14 -> 娱乐 | H31: =各类别总结!N14 -> 110 | I31: =各类别总结!P14 -> 0.021359223
A32: =每月总结!A15 -> 2026-12 | B32: =每月总结!B15 -> 0 | C32: =每月总结!C15 -> 0 | D32: =公式枢纽!O39 -> 0 | E32: =公式枢纽!J39 -> 0 | G32: =各类别总结!A15 -> 税费 | H32: =各类别总结!N15 -> 125 | I32: =各类别总结!P15 -> 0.024271845
G33: =各类别总结!A16 -> 其他 | H33: =各类别总结!N16 -> 97.5 | I33: =各类别总结!P16 -> 0.018932039

Sheet 总支出
A1: 总支出
A2: 用户只需要填写本页作为支出页。支出金额请输入正数；依据分析口径、类别和税费类型完成统计。
A3: 记录编号 | B3: 日期 | C3: 支出内容 | D3: 支出金额 | E3: 主类别 | F3: 支出性质 | G3: 必要程度 | H3: 分析口径 | I3: 税费类型 | J3: 备注
A4: 支出-0001 | B4: 46023 | C4: 房租 | D4: 3000 | E4: 住房 | F4: 固定 | G4: 必要 | H4: 个人支出 | I4: 免税 | J4: 示例：1月总支出约5000，房租占60%
A5: 支出-0002 | B5: 46025 | C5: 超市基础食品：鸡蛋、蔬菜、牛奶 | D5: 450 | E5: 餐饮 | F5: 可变 | G5: 必要 | H5: 个人支出 | I5: 零税率 | J5: 基础食品通常按零税率演示
A6: 支出-0003 | B6: 46027 | C6: 餐厅外食 | D6: 320 | E6: 餐饮 | F6: 可变 | G6: 弹性 | H6: 个人支出 | I6: 应税 | J6: 餐厅和外卖通常应税
A7: 支出-0004 | B7: 46029 | C7: 加油 | D7: 220 | E7: 交通 | F7: 可变 | G7: 必要 | H7: 个人支出 | I7: 应税 | J7: 交通相关应税示例
A8: 支出-0005 | B8: 46030 | C8: 手机通讯费 | D8: 60 | E8: 通讯 | F8: 固定 | G8: 必要 | H8: 个人支出 | I8: 应税
A9: 支出-0006 | B9: 46031 | C9: 云服务订阅 | D9: 30 | E9: 订阅 | F9: 固定 | G9: 弹性 | H9: 个人支出 | I9: 应税
A10: 支出-0007 | B10: 46032 | C10: 衣物与日用品购物 | D10: 250 | E10: 购物 | F10: 可变 | G10: 弹性 | H10: 个人支出 | I10: 应税
A11: 支出-0008 | B11: 46034 | C11: 药品和医疗用品 | D11: 80 | E11: 医疗 | F11: 可变 | G11: 必要 | H11: 个人支出 | I11: 免税 | J11: 仅作模板示例，实际以收据为准
A12: 支出-0009 | B12: 46037 | C12: 健身房月费 | D12: 70 | E12: 运动 | F12: 固定 | G12: 弹性 | H12: 个人支出 | I12: 应税
A13: 支出-0010 | B13: 46038 | C13: 课程与书籍 | D13: 120 | E13: 学习 | F13: 一次性 | G13: 弹性 | H13: 个人支出 | I13: 含税不明 | J13: 学习类税费取决于具体项目
A14: 支出-0011 | B14: 46040 | C14: 宠物食品和用品 | D14: 90 | E14: 宠物 | F14: 可变 | G14: 弹性 | H14: 个人支出 | I14: 应税
A15: 支出-0012 | B15: 46042 | C15: 电影和游戏娱乐 | D15: 100 | E15: 娱乐 | F15: 可变 | G15: 弹性 | H15: 个人支出 | I15: 应税
A16: 支出-0013 | B16: 46047 | C16: 政府费用 | D16: 100 | E16: 税费 | F16: 一次性 | G16: 必要 | H16: 个人支出 | I16: 不适用 | J16: 政府收费不纳入消费税估算
A17: 支出-0014 | B17: 46050 | C17: 其他杂项 | D17: 110 | E17: 其他 | F17: 可变 | G17: 弹性 | H17: 个人支出 | I17: 含税不明
A18: 支出-0015 | B18: 46054 | C18: 房租 | D18: 3000 | E18: 住房 | F18: 固定 | G18: 必要 | H18: 个人支出 | I18: 免税 | J18: 示例：2月有一定波动
A19: 支出-0016 | B19: 46056 | C19: 超市基础食品：水果、蔬菜、面包 | D19: 520 | E19: 餐饮 | F19: 可变 | G19: 必要 | H19: 个人支出 | I19: 零税率
A20: 支出-0017 | B20: 46058 | C20: 餐厅聚餐 | D20: 350 | E20: 餐饮 | F20: 可变 | G20: 弹性 | H20: 个人支出 | I20: 应税
A21: 支出-0018 | B21: 46059 | C21: 车辆加油与停车 | D21: 260 | E21: 交通 | F21: 可变 | G21: 必要 | H21: 个人支出 | I21: 应税
A22: 支出-0019 | B22: 46061 | C22: 手机通讯费 | D22: 60 | E22: 通讯 | F22: 固定 | G22: 必要 | H22: 个人支出 | I22: 应税
A23: 支出-0020 | B23: 46063 | C23: 软件订阅 | D23: 45 | E23: 订阅 | F23: 固定 | G23: 弹性 | H23: 个人支出 | I23: 应税
A24: 支出-0021 | B24: 46064 | C24: 衣物购物 | D24: 300 | E24: 购物 | F24: 可变 | G24: 弹性 | H24: 个人支出 | I24: 应税
A25: 支出-0022 | B25: 46066 | C25: 医疗用品 | D25: 100 | E25: 医疗 | F25: 可变 | G25: 必要 | H25: 个人支出 | I25: 免税
A26: 支出-0023 | B26: 46068 | C26: 健身房月费 | D26: 70 | E26: 运动 | F26: 固定 | G26: 弹性 | H26: 个人支出 | I26: 应税
A27: 支出-0024 | B27: 46070 | C27: 线上课程 | D27: 140 | E27: 学习 | F27: 一次性 | G27: 弹性 | H27: 个人支出 | I27: 含税不明
A28: 支出-0025 | B28: 46072 | C28: 宠物用品 | D28: 100 | E28: 宠物 | F28: 可变 | G28: 弹性 | H28: 个人支出 | I28: 应税
A29: 支出-0026 | B29: 46074 | C29: 娱乐活动 | D29: 120 | E29: 娱乐 | F29: 可变 | G29: 弹性 | H29: 个人支出 | I29: 应税
A30: 支出-0027 | B30: 46076 | C30: 政府费用 | D30: 150 | E30: 税费 | F30: 一次性 | G30: 必要 | H30: 个人支出 | I30: 不适用
A31: 支出-0028 | B31: 46079 | C31: 其他杂项 | D31: 85 | E31: 其他 | F31: 可变 | G31: 弹性 | H31: 个人支出 | I31: 含税不明
I32: 自动

Sheet 总收入
A1: 总收入
A2: 用户只需要填写本页作为收入页。收入金额请输入正数；
A3: 记录编号 | B3: 日期 | C3: 收入来源 | D3: 收入金额 | E3: 收入类型 | F3: 备注
A4: 收入-0001 | B4: 46030 | C4: 工资 | D4: 6000 | E4: 工资 | F4: 示例收入
A5: 收入-0002 | B5: 46061 | C5: 工资 | D5: 6700 | E5: 工资 | F5: 示例收入
A6: 收入-0003 | B6: 46073 | C6: 退款 | D6: 200 | E6: 退款 | F6: 示例：退款收入

Sheet 输入设置
A1: 输入设置
A2: 手动变量区。日常使用时主要更新当前可动用现金、额外缓冲、备用金月数等。
A4: 设置项 | B4: 当前值 | C4: 说明
A5: 当前可动用现金 | B5: 30000 | C5: 用于计算现金覆盖月数与可投资资金
A6: 额外安全缓冲 | B6: 1000 | C6: 在推荐现金储备之外额外保留的现金
A7: 风险偏好 | B7: 平衡 | C7: 仅用于说明；可填写保守、平衡、成长
A8: 备用金月数 | B8: 12 | C8: 推荐现金储备 = 月均支出 × 备用金月数，再考虑最低下限与额外缓冲
A9: 最低现金储备下限 | B9: 15000 | C9: 即使公式算出较低储备，也保留此下限
A12: 可选：每月住房底盘
B13: 2026-01 | C13: 2026-02 | D13: 2026-03 | E13: 2026-04 | F13: 2026-05 | G13: 2026-06 | H13: 2026-07 | I13: 2026-08 | J13: 2026-09 | K13: 2026-10 | L13: 2026-11 | M13: 2026-12
A14: 住房底盘 | B14: 3000 | C14: 3000 | D14: 3000 | E14: 3000 | F14: 3000 | G14: 3000 | H14: 3000 | I14: 3000 | J14: 3000 | K14: 3000 | L14: 3000 | M14: 3000

Sheet 税费设置
A1: 税费设置
A2: 消费税估算为近似分析。用户可选择是否启用，并可自行调整税率、地区和分类规则。
A4: 设置项 | B4: 当前值 | C4: 说明
A5: 是否启用消费税估算 | B5: 是 | C5: 选择“否”后，所有估算税额显示为0
A6: 支出金额是否为含税价 | B6: 是 | C6: 多数个人记账记录的是信用卡实际扣款，通常视为含税价
A7: 所在地区 | B7: 魁北克 | C7: 默认以魁北克消费税做示例，可手动修改税率
A8: 联邦消费税率 | B8: 0.05 | C8: 示例：5%
A9: 省级消费税率 | B9: 0.09975 | C9: 示例：魁北克省级销售税9.975%
A10: 合计消费税率 | B10: =B8+B9 -> 0.14975 | C10: 用于含税价倒推税额
A13: 主类别默认税费类型
A14: 主类别 | B14: 默认税费类型 | C14: 说明
A15: 住房 | B15: 免税 | C15: 居住租金等通常不纳入消费税估算
A16: 餐饮 | B16: 应税 | C16: 餐厅、外卖、热食通常应税；基础食品请手动改为零税率
A17: 交通 | B17: 应税 | C17: 加油、停车、维修等通常应税；公共交通请按实际情况调整
A18: 通讯 | B18: 应税 | C18: 手机、网络、通信服务通常应税
A19: 订阅 | B19: 应税 | C19: 软件、流媒体等订阅通常应税
A20: 购物 | B20: 应税 | C20: 衣物、日用品、电子产品等通常应税
A21: 医疗 | B21: 免税 | C21: 医疗类项目差异较大，示例按免税处理
A22: 运动 | B22: 应税 | C22: 健身房、运动服务通常应税
A23: 学习 | B23: 含税不明 | C23: 书籍、课程、学费等差异较大
A24: 宠物 | B24: 应税 | C24: 宠物食品和用品通常应税
A25: 娱乐 | B25: 应税 | C25: 电影、游戏、活动等通常应税
... A27: 其他 | B27: 含税不明 | C27: 未知项目需按收据判断
A30: 资料来源
A31: 主题 | B31: 链接
A32: 魁北克消费税计算规则 | B32: https://www.revenuquebec.ca/en/businesses/consumption-taxes/gsthst-and-qst/collecting-gst-and-qst/calculating-the-taxes/
A33: 魁北克消费税税率表 | B33: https://www.revenuquebec.ca/en/businesses/consumption-taxes/gsthst-and-qst/basic-rules-for-applying-the-gsthst-and-qst/tables-of-gst-and-qst-rates/
A34: 应税供应示例 | B34: https://www.revenuquebec.ca/en/businesses/consumption-taxes/gsthst-and-qst/basic-rules-for-applying-the-gsthst-and-qst/types-of-supplies/taxable-supplies/
A35: 联邦消费税抵免说明 | B35: https://www.canada.ca/en/revenue-agency/services/child-family-benefits/gst-hst-credit.html

Sheet 每月总结
A1: 每月总结
A2: 展示页：引用公式枢纽的月度汇总。
A3: 月份 | B3: 总收入 | C3: 个人支出 | D3: 必要支出 | E3: 弹性支出 | F3: 固定支出 | G3: 可变支出 | H3: 一次性支出 | I3: 住房支出 | J3: 净现金流 | K3: 是否纳入平均 | L3: 房产支出 | M3: 投资转账 | N3: 内部转账 | O3: 估算消费税
A4: =公式枢纽!A28 -> 2026-01 | B4: =公式枢纽!B28 -> 6000 | C4: =公式枢纽!C28 -> 5000 | D4: =公式枢纽!D28 -> 3910 | E4: =公式枢纽!E28 -> 1090 | F4: =公式枢纽!F28 -> 3160 | G4: =公式枢纽!G28 -> 1620 | H4: =公式枢纽!H28 -> 220 | ... O4: =公式枢纽!O28 -> 148.4801
A5: =公式枢纽!A29 -> 2026-02 | B5: =公式枢纽!B29 -> 6900 | C5: =公式枢纽!C29 -> 5300 | D5: =公式枢纽!D29 -> 4090 | E5: =公式枢纽!E29 -> 1210 | F5: =公式枢纽!F29 -> 3175 | G5: =公式枢纽!G29 -> 1835 | H5: =公式枢纽!H29 -> 290 | ... O5: =公式枢纽!O29 -> 169.97065
A6: =公式枢纽!A30 -> 2026-03 | B6: =公式枢纽!B30 -> 0 | C6: =公式枢纽!C30 -> 0 | D6: =公式枢纽!D30 -> 0 | E6: =公式枢纽!E30 -> 0 | F6: =公式枢纽!F30 -> 0 | G6: =公式枢纽!G30 -> 0 | H6: =公式枢纽!H30 -> 0 | ... O6: =公式枢纽!O30 -> 0
A7: =公式枢纽!A31 -> 2026-04 | B7: =公式枢纽!B31 -> 0 | C7: =公式枢纽!C31 -> 0 | D7: =公式枢纽!D31 -> 0 | E7: =公式枢纽!E31 -> 0 | F7: =公式枢纽!F31 -> 0 | G7: =公式枢纽!G31 -> 0 | H7: =公式枢纽!H31 -> 0 | ... O7: =公式枢纽!O31 -> 0
A8: =公式枢纽!A32 -> 2026-05 | B8: =公式枢纽!B32 -> 0 | C8: =公式枢纽!C32 -> 0 | D8: =公式枢纽!D32 -> 0 | E8: =公式枢纽!E32 -> 0 | F8: =公式枢纽!F32 -> 0 | G8: =公式枢纽!G32 -> 0 | H8: =公式枢纽!H32 -> 0 | ... O8: =公式枢纽!O32 -> 0
A9: =公式枢纽!A33 -> 2026-06 | B9: =公式枢纽!B33 -> 0 | C9: =公式枢纽!C33 -> 0 | D9: =公式枢纽!D33 -> 0 | E9: =公式枢纽!E33 -> 0 | F9: =公式枢纽!F33 -> 0 | G9: =公式枢纽!G33 -> 0 | H9: =公式枢纽!H33 -> 0 | ... O9: =公式枢纽!O33 -> 0
A10: =公式枢纽!A34 -> 2026-07 | B10: =公式枢纽!B34 -> 0 | C10: =公式枢纽!C34 -> 0 | D10: =公式枢纽!D34 -> 0 | E10: =公式枢纽!E34 -> 0 | F10: =公式枢纽!F34 -> 0 | G10: =公式枢纽!G34 -> 0 | H10: =公式枢纽!H34 -> 0 | ... O10: =公式枢纽!O34 -> 0
A11: =公式枢纽!A35 -> 2026-08 | B11: =公式枢纽!B35 -> 0 | C11: =公式枢纽!C35 -> 0 | D11: =公式枢纽!D35 -> 0 | E11: =公式枢纽!E35 -> 0 | F11: =公式枢纽!F35 -> 0 | G11: =公式枢纽!G35 -> 0 | H11: =公式枢纽!H35 -> 0 | ... O11: =公式枢纽!O35 -> 0
A12: =公式枢纽!A36 -> 2026-09 | B12: =公式枢纽!B36 -> 0 | C12: =公式枢纽!C36 -> 0 | D12: =公式枢纽!D36 -> 0 | E12: =公式枢纽!E36 -> 0 | F12: =公式枢纽!F36 -> 0 | G12: =公式枢纽!G36 -> 0 | H12: =公式枢纽!H36 -> 0 | ... O12: =公式枢纽!O36 -> 0
A13: =公式枢纽!A37 -> 2026-10 | B13: =公式枢纽!B37 -> 0 | C13: =公式枢纽!C37 -> 0 | D13: =公式枢纽!D37 -> 0 | E13: =公式枢纽!E37 -> 0 | F13: =公式枢纽!F37 -> 0 | G13: =公式枢纽!G37 -> 0 | H13: =公式枢纽!H37 -> 0 | ... O13: =公式枢纽!O37 -> 0
A14: =公式枢纽!A38 -> 2026-11 | B14: =公式枢纽!B38 -> 0 | C14: =公式枢纽!C38 -> 0 | D14: =公式枢纽!D38 -> 0 | E14: =公式枢纽!E38 -> 0 | F14: =公式枢纽!F38 -> 0 | G14: =公式枢纽!G38 -> 0 | H14: =公式枢纽!H38 -> 0 | ... O14: =公式枢纽!O38 -> 0
A15: =公式枢纽!A39 -> 2026-12 | B15: =公式枢纽!B39 -> 0 | C15: =公式枢纽!C39 -> 0 | D15: =公式枢纽!D39 -> 0 | E15: =公式枢纽!E39 -> 0 | F15: =公式枢纽!F39 -> 0 | G15: =公式枢纽!G39 -> 0 | H15: =公式枢纽!H39 -> 0 | ... O15: =公式枢纽!O39 -> 0

Sheet 各类别总结
A1: 各类别总结
A2: 展示页：按主类别汇总月均、年化金额和占比。
A3: 主类别 | B3: 2026-01 | C3: 2026-02 | D3: 2026-03 | E3: 2026-04 | F3: 2026-05 | G3: 2026-06 | H3: 2026-07 | I3: 2026-08 | J3: 2026-09 | K3: 2026-10 | L3: 2026-11 | M3: 2026-12 | N3: 月均 | O3: 年化 | P3: 占个人月支出比例
A4: =公式枢纽!A45 -> 住房 | B4: =公式枢纽!B45 -> 3000 | C4: =公式枢纽!C45 -> 3000 | D4: =公式枢纽!D45 -> 0 | E4: =公式枢纽!E45 -> 0 | F4: =公式枢纽!F45 -> 0 | G4: =公式枢纽!G45 -> 0 | H4: =公式枢纽!H45 -> 0 | ... P4: =公式枢纽!P45 -> 0.58252427
A5: =公式枢纽!A46 -> 餐饮 | B5: =公式枢纽!B46 -> 770 | C5: =公式枢纽!C46 -> 870 | D5: =公式枢纽!D46 -> 0 | E5: =公式枢纽!E46 -> 0 | F5: =公式枢纽!F46 -> 0 | G5: =公式枢纽!G46 -> 0 | H5: =公式枢纽!H46 -> 0 | ... P5: =公式枢纽!P46 -> 0.1592233
A6: =公式枢纽!A47 -> 交通 | B6: =公式枢纽!B47 -> 220 | C6: =公式枢纽!C47 -> 260 | D6: =公式枢纽!D47 -> 0 | E6: =公式枢纽!E47 -> 0 | F6: =公式枢纽!F47 -> 0 | G6: =公式枢纽!G47 -> 0 | H6: =公式枢纽!H47 -> 0 | ... P6: =公式枢纽!P47 -> 0.046601942
A7: =公式枢纽!A48 -> 通讯 | B7: =公式枢纽!B48 -> 60 | C7: =公式枢纽!C48 -> 60 | D7: =公式枢纽!D48 -> 0 | E7: =公式枢纽!E48 -> 0 | F7: =公式枢纽!F48 -> 0 | G7: =公式枢纽!G48 -> 0 | H7: =公式枢纽!H48 -> 0 | ... P7: =公式枢纽!P48 -> 0.011650485
A8: =公式枢纽!A49 -> 订阅 | B8: =公式枢纽!B49 -> 30 | C8: =公式枢纽!C49 -> 45 | D8: =公式枢纽!D49 -> 0 | E8: =公式枢纽!E49 -> 0 | F8: =公式枢纽!F49 -> 0 | G8: =公式枢纽!G49 -> 0 | H8: =公式枢纽!H49 -> 0 | ... P8: =公式枢纽!P49 -> 0.0072815534
A9: =公式枢纽!A50 -> 购物 | B9: =公式枢纽!B50 -> 250 | C9: =公式枢纽!C50 -> 300 | D9: =公式枢纽!D50 -> 0 | E9: =公式枢纽!E50 -> 0 | F9: =公式枢纽!F50 -> 0 | G9: =公式枢纽!G50 -> 0 | H9: =公式枢纽!H50 -> 0 | ... P9: =公式枢纽!P50 -> 0.053398058
A10: =公式枢纽!A51 -> 医疗 | B10: =公式枢纽!B51 -> 80 | C10: =公式枢纽!C51 -> 100 | D10: =公式枢纽!D51 -> 0 | E10: =公式枢纽!E51 -> 0 | F10: =公式枢纽!F51 -> 0 | G10: =公式枢纽!G51 -> 0 | H10: =公式枢纽!H51 -> 0 | ... P10: =公式枢纽!P51 -> 0.017475728
A11: =公式枢纽!A52 -> 运动 | B11: =公式枢纽!B52 -> 70 | C11: =公式枢纽!C52 -> 70 | D11: =公式枢纽!D52 -> 0 | E11: =公式枢纽!E52 -> 0 | F11: =公式枢纽!F52 -> 0 | G11: =公式枢纽!G52 -> 0 | H11: =公式枢纽!H52 -> 0 | ... P11: =公式枢纽!P52 -> 0.013592233
A12: =公式枢纽!A53 -> 学习 | B12: =公式枢纽!B53 -> 120 | C12: =公式枢纽!C53 -> 140 | D12: =公式枢纽!D53 -> 0 | E12: =公式枢纽!E53 -> 0 | F12: =公式枢纽!F53 -> 0 | G12: =公式枢纽!G53 -> 0 | H12: =公式枢纽!H53 -> 0 | ... P12: =公式枢纽!P53 -> 0.025242718
A13: =公式枢纽!A54 -> 宠物 | B13: =公式枢纽!B54 -> 90 | C13: =公式枢纽!C54 -> 100 | D13: =公式枢纽!D54 -> 0 | E13: =公式枢纽!E54 -> 0 | F13: =公式枢纽!F54 -> 0 | G13: =公式枢纽!G54 -> 0 | H13: =公式枢纽!H54 -> 0 | ... P13: =公式枢纽!P54 -> 0.018446602
A14: =公式枢纽!A55 -> 娱乐 | B14: =公式枢纽!B55 -> 100 | C14: =公式枢纽!C55 -> 120 | D14: =公式枢纽!D55 -> 0 | E14: =公式枢纽!E55 -> 0 | F14: =公式枢纽!F55 -> 0 | G14: =公式枢纽!G55 -> 0 | H14: =公式枢纽!H55 -> 0 | ... P14: =公式枢纽!P55 -> 0.021359223
A15: =公式枢纽!A56 -> 税费 | B15: =公式枢纽!B56 -> 100 | C15: =公式枢纽!C56 -> 150 | D15: =公式枢纽!D56 -> 0 | E15: =公式枢纽!E56 -> 0 | F15: =公式枢纽!F56 -> 0 | G15: =公式枢纽!G56 -> 0 | H15: =公式枢纽!H56 -> 0 | ... P15: =公式枢纽!P56 -> 0.024271845
A16: =公式枢纽!A57 -> 其他 | B16: =公式枢纽!B57 -> 110 | C16: =公式枢纽!C57 -> 85 | D16: =公式枢纽!D57 -> 0 | E16: =公式枢纽!E57 -> 0 | F16: =公式枢纽!F57 -> 0 | G16: =公式枢纽!G57 -> 0 | H16: =公式枢纽!H57 -> 0 | ... P16: =公式枢纽!P57 -> 0.018932039

Sheet 消费税分析
A1: 消费税分析
A2: 按月份汇总估算消费税。该页是估算工具，不等同于实际可抵扣或可退税金额。
A3: 月份 | B3: 应税消费 | C3: 零税率消费 | D3: 免税消费 | E3: 其他/不适用 | F3: 税前金额 | G3: 联邦税估算 | H3: 省级税估算 | I3: 消费税合计 | J3: 说明
A4: 2026-01 | B4: =SUMIFS(税费计算明细!$L$4:$L$5000,税费计算明细!$C$4:$C$5000,$A4) -> 1140 | C4: =SUMIFS(税费计算明细!$M$4:$M$5000,税费计算明细!$C$4:$C$5000,$A4) -> 450 | D4: =SUMIFS(税费计算明细!$N$4:$N$5000,税费计算明细!$C$4:$C$5000,$A4) -> 3080 | E4: =SUMIFS(税费计算明细!$O$4:$O$5000,税费计算明细!$C$4:$C$5000,$A4) -> 330 | F4: =SUMIFS(税费计算明细!$P$4:$P$5000,税费计算明细!$C$4:$C$5000,$A4) -> 991.5199 | G4: =SUMIFS(税费计算明细!$Q$4:$Q$5000,税费计算明细!$C$4:$C$5000,$A4) -> 49.575995 | H4: =SUMIFS(税费计算明细!$R$4:$R$5000,税费计算明细!$C$4:$C$5000,$A4) -> 98.90411 | I4: =SUMIFS(税费计算明细!$S$4:$S$5000,税费计算明细!$C$4:$C$5000,$A4) -> 148.4801 | J4: =IF($I4=0,"无估算税额","已估算") -> 已估算
A5: 2026-02 | B5: =SUMIFS(税费计算明细!$L$4:$L$5000,税费计算明细!$C$4:$C$5000,$A5) -> 1305 | C5: =SUMIFS(税费计算明细!$M$4:$M$5000,税费计算明细!$C$4:$C$5000,$A5) -> 520 | D5: =SUMIFS(税费计算明细!$N$4:$N$5000,税费计算明细!$C$4:$C$5000,$A5) -> 3100 | E5: =SUMIFS(税费计算明细!$O$4:$O$5000,税费计算明细!$C$4:$C$5000,$A5) -> 375 | F5: =SUMIFS(税费计算明细!$P$4:$P$5000,税费计算明细!$C$4:$C$5000,$A5) -> 1135.0294 | G5: =SUMIFS(税费计算明细!$Q$4:$Q$5000,税费计算明细!$C$4:$C$5000,$A5) -> 56.751468 | H5: =SUMIFS(税费计算明细!$R$4:$R$5000,税费计算明细!$C$4:$C$5000,$A5) -> 113.21918 | I5: =SUMIFS(税费计算明细!$S$4:$S$5000,税费计算明细!$C$4:$C$5000,$A5) -> 169.97065 | J5: =IF($I5=0,"无估算税额","已估算") -> 已估算
A6: 2026-03 | B6: =SUMIFS(税费计算明细!$L$4:$L$5000,税费计算明细!$C$4:$C$5000,$A6) -> 0 | C6: =SUMIFS(税费计算明细!$M$4:$M$5000,税费计算明细!$C$4:$C$5000,$A6) -> 0 | D6: =SUMIFS(税费计算明细!$N$4:$N$5000,税费计算明细!$C$4:$C$5000,$A6) -> 0 | E6: =SUMIFS(税费计算明细!$O$4:$O$5000,税费计算明细!$C$4:$C$5000,$A6) -> 0 | F6: =SUMIFS(税费计算明细!$P$4:$P$5000,税费计算明细!$C$4:$C$5000,$A6) -> 0 | G6: =SUMIFS(税费计算明细!$Q$4:$Q$5000,税费计算明细!$C$4:$C$5000,$A6) -> 0 | H6: =SUMIFS(税费计算明细!$R$4:$R$5000,税费计算明细!$C$4:$C$5000,$A6) -> 0 | I6: =SUMIFS(税费计算明细!$S$4:$S$5000,税费计算明细!$C$4:$C$5000,$A6) -> 0 | J6: =IF($I6=0,"无估算税额","已估算") -> 无估算税额
A7: 2026-04 | B7: =SUMIFS(税费计算明细!$L$4:$L$5000,税费计算明细!$C$4:$C$5000,$A7) -> 0 | C7: =SUMIFS(税费计算明细!$M$4:$M$5000,税费计算明细!$C$4:$C$5000,$A7) -> 0 | D7: =SUMIFS(税费计算明细!$N$4:$N$5000,税费计算明细!$C$4:$C$5000,$A7) -> 0 | E7: =SUMIFS(税费计算明细!$O$4:$O$5000,税费计算明细!$C$4:$C$5000,$A7) -> 0 | F7: =SUMIFS(税费计算明细!$P$4:$P$5000,税费计算明细!$C$4:$C$5000,$A7) -> 0 | G7: =SUMIFS(税费计算明细!$Q$4:$Q$5000,税费计算明细!$C$4:$C$5000,$A7) -> 0 | H7: =SUMIFS(税费计算明细!$R$4:$R$5000,税费计算明细!$C$4:$C$5000,$A7) -> 0 | I7: =SUMIFS(税费计算明细!$S$4:$S$5000,税费计算明细!$C$4:$C$5000,$A7) -> 0 | J7: =IF($I7=0,"无估算税额","已估算") -> 无估算税额
A8: 2026-05 | B8: =SUMIFS(税费计算明细!$L$4:$L$5000,税费计算明细!$C$4:$C$5000,$A8) -> 0 | C8: =SUMIFS(税费计算明细!$M$4:$M$5000,税费计算明细!$C$4:$C$5000,$A8) -> 0 | D8: =SUMIFS(税费计算明细!$N$4:$N$5000,税费计算明细!$C$4:$C$5000,$A8) -> 0 | E8: =SUMIFS(税费计算明细!$O$4:$O$5000,税费计算明细!$C$4:$C$5000,$A8) -> 0 | F8: =SUMIFS(税费计算明细!$P$4:$P$5000,税费计算明细!$C$4:$C$5000,$A8) -> 0 | G8: =SUMIFS(税费计算明细!$Q$4:$Q$5000,税费计算明细!$C$4:$C$5000,$A8) -> 0 | H8: =SUMIFS(税费计算明细!$R$4:$R$5000,税费计算明细!$C$4:$C$5000,$A8) -> 0 | I8: =SUMIFS(税费计算明细!$S$4:$S$5000,税费计算明细!$C$4:$C$5000,$A8) -> 0 | J8: =IF($I8=0,"无估算税额","已估算") -> 无估算税额
A9: 2026-06 | B9: =SUMIFS(税费计算明细!$L$4:$L$5000,税费计算明细!$C$4:$C$5000,$A9) -> 0 | C9: =SUMIFS(税费计算明细!$M$4:$M$5000,税费计算明细!$C$4:$C$5000,$A9) -> 0 | D9: =SUMIFS(税费计算明细!$N$4:$N$5000,税费计算明细!$C$4:$C$5000,$A9) -> 0 | E9: =SUMIFS(税费计算明细!$O$4:$O$5000,税费计算明细!$C$4:$C$5000,$A9) -> 0 | F9: =SUMIFS(税费计算明细!$P$4:$P$5000,税费计算明细!$C$4:$C$5000,$A9) -> 0 | G9: =SUMIFS(税费计算明细!$Q$4:$Q$5000,税费计算明细!$C$4:$C$5000,$A9) -> 0 | H9: =SUMIFS(税费计算明细!$R$4:$R$5000,税费计算明细!$C$4:$C$5000,$A9) -> 0 | I9: =SUMIFS(税费计算明细!$S$4:$S$5000,税费计算明细!$C$4:$C$5000,$A9) -> 0 | J9: =IF($I9=0,"无估算税额","已估算") -> 无估算税额
A10: 2026-07 | B10: =SUMIFS(税费计算明细!$L$4:$L$5000,税费计算明细!$C$4:$C$5000,$A10) -> 0 | C10: =SUMIFS(税费计算明细!$M$4:$M$5000,税费计算明细!$C$4:$C$5000,$A10) -> 0 | D10: =SUMIFS(税费计算明细!$N$4:$N$5000,税费计算明细!$C$4:$C$5000,$A10) -> 0 | E10: =SUMIFS(税费计算明细!$O$4:$O$5000,税费计算明细!$C$4:$C$5000,$A10) -> 0 | F10: =SUMIFS(税费计算明细!$P$4:$P$5000,税费计算明细!$C$4:$C$5000,$A10) -> 0 | G10: =SUMIFS(税费计算明细!$Q$4:$Q$5000,税费计算明细!$C$4:$C$5000,$A10) -> 0 | H10: =SUMIFS(税费计算明细!$R$4:$R$5000,税费计算明细!$C$4:$C$5000,$A10) -> 0 | I10: =SUMIFS(税费计算明细!$S$4:$S$5000,税费计算明细!$C$4:$C$5000,$A10) -> 0 | J10: =IF($I10=0,"无估算税额","已估算") -> 无估算税额
A11: 2026-08 | B11: =SUMIFS(税费计算明细!$L$4:$L$5000,税费计算明细!$C$4:$C$5000,$A11) -> 0 | C11: =SUMIFS(税费计算明细!$M$4:$M$5000,税费计算明细!$C$4:$C$5000,$A11) -> 0 | D11: =SUMIFS(税费计算明细!$N$4:$N$5000,税费计算明细!$C$4:$C$5000,$A11) -> 0 | E11: =SUMIFS(税费计算明细!$O$4:$O$5000,税费计算明细!$C$4:$C$5000,$A11) -> 0 | F11: =SUMIFS(税费计算明细!$P$4:$P$5000,税费计算明细!$C$4:$C$5000,$A11) -> 0 | G11: =SUMIFS(税费计算明细!$Q$4:$Q$5000,税费计算明细!$C$4:$C$5000,$A11) -> 0 | H11: =SUMIFS(税费计算明细!$R$4:$R$5000,税费计算明细!$C$4:$C$5000,$A11) -> 0 | I11: =SUMIFS(税费计算明细!$S$4:$S$5000,税费计算明细!$C$4:$C$5000,$A11) -> 0 | J11: =IF($I11=0,"无估算税额","已估算") -> 无估算税额
A12: 2026-09 | B12: =SUMIFS(税费计算明细!$L$4:$L$5000,税费计算明细!$C$4:$C$5000,$A12) -> 0 | C12: =SUMIFS(税费计算明细!$M$4:$M$5000,税费计算明细!$C$4:$C$5000,$A12) -> 0 | D12: =SUMIFS(税费计算明细!$N$4:$N$5000,税费计算明细!$C$4:$C$5000,$A12) -> 0 | E12: =SUMIFS(税费计算明细!$O$4:$O$5000,税费计算明细!$C$4:$C$5000,$A12) -> 0 | F12: =SUMIFS(税费计算明细!$P$4:$P$5000,税费计算明细!$C$4:$C$5000,$A12) -> 0 | G12: =SUMIFS(税费计算明细!$Q$4:$Q$5000,税费计算明细!$C$4:$C$5000,$A12) -> 0 | H12: =SUMIFS(税费计算明细!$R$4:$R$5000,税费计算明细!$C$4:$C$5000,$A12) -> 0 | I12: =SUMIFS(税费计算明细!$S$4:$S$5000,税费计算明细!$C$4:$C$5000,$A12) -> 0 | J12: =IF($I12=0,"无估算税额","已估算") -> 无估算税额
A13: 2026-10 | B13: =SUMIFS(税费计算明细!$L$4:$L$5000,税费计算明细!$C$4:$C$5000,$A13) -> 0 | C13: =SUMIFS(税费计算明细!$M$4:$M$5000,税费计算明细!$C$4:$C$5000,$A13) -> 0 | D13: =SUMIFS(税费计算明细!$N$4:$N$5000,税费计算明细!$C$4:$C$5000,$A13) -> 0 | E13: =SUMIFS(税费计算明细!$O$4:$O$5000,税费计算明细!$C$4:$C$5000,$A13) -> 0 | F13: =SUMIFS(税费计算明细!$P$4:$P$5000,税费计算明细!$C$4:$C$5000,$A13) -> 0 | G13: =SUMIFS(税费计算明细!$Q$4:$Q$5000,税费计算明细!$C$4:$C$5000,$A13) -> 0 | H13: =SUMIFS(税费计算明细!$R$4:$R$5000,税费计算明细!$C$4:$C$5000,$A13) -> 0 | I13: =SUMIFS(税费计算明细!$S$4:$S$5000,税费计算明细!$C$4:$C$5000,$A13) -> 0 | J13: =IF($I13=0,"无估算税额","已估算") -> 无估算税额
A14: 2026-11 | B14: =SUMIFS(税费计算明细!$L$4:$L$5000,税费计算明细!$C$4:$C$5000,$A14) -> 0 | C14: =SUMIFS(税费计算明细!$M$4:$M$5000,税费计算明细!$C$4:$C$5000,$A14) -> 0 | D14: =SUMIFS(税费计算明细!$N$4:$N$5000,税费计算明细!$C$4:$C$5000,$A14) -> 0 | E14: =SUMIFS(税费计算明细!$O$4:$O$5000,税费计算明细!$C$4:$C$5000,$A14) -> 0 | F14: =SUMIFS(税费计算明细!$P$4:$P$5000,税费计算明细!$C$4:$C$5000,$A14) -> 0 | G14: =SUMIFS(税费计算明细!$Q$4:$Q$5000,税费计算明细!$C$4:$C$5000,$A14) -> 0 | H14: =SUMIFS(税费计算明细!$R$4:$R$5000,税费计算明细!$C$4:$C$5000,$A14) -> 0 | I14: =SUMIFS(税费计算明细!$S$4:$S$5000,税费计算明细!$C$4:$C$5000,$A14) -> 0 | J14: =IF($I14=0,"无估算税额","已估算") -> 无估算税额
A15: 2026-12 | B15: =SUMIFS(税费计算明细!$L$4:$L$5000,税费计算明细!$C$4:$C$5000,$A15) -> 0 | C15: =SUMIFS(税费计算明细!$M$4:$M$5000,税费计算明细!$C$4:$C$5000,$A15) -> 0 | D15: =SUMIFS(税费计算明细!$N$4:$N$5000,税费计算明细!$C$4:$C$5000,$A15) -> 0 | E15: =SUMIFS(税费计算明细!$O$4:$O$5000,税费计算明细!$C$4:$C$5000,$A15) -> 0 | F15: =SUMIFS(税费计算明细!$P$4:$P$5000,税费计算明细!$C$4:$C$5000,$A15) -> 0 | G15: =SUMIFS(税费计算明细!$Q$4:$Q$5000,税费计算明细!$C$4:$C$5000,$A15) -> 0 | H15: =SUMIFS(税费计算明细!$R$4:$R$5000,税费计算明细!$C$4:$C$5000,$A15) -> 0 | I15: =SUMIFS(税费计算明细!$S$4:$S$5000,税费计算明细!$C$4:$C$5000,$A15) -> 0 | J15: =IF($I15=0,"无估算税额","已估算") -> 无估算税额
A17: 全年合计 | B17: =SUM(B4:B15) -> 2445 | C17: =SUM(C4:C15) -> 970 | D17: =SUM(D4:D15) -> 6180 | E17: =SUM(E4:E15) -> 705 | F17: =SUM(F4:F15) -> 2126.5492 | G17: =SUM(G4:G15) -> 106.32746 | H17: =SUM(H4:H15) -> 212.12329 | I17: =SUM(I4:I15) -> 318.45075
A18: 消费税占个人支出比例 | B18: =IFERROR(I17/公式枢纽!$B$6,0) -> 0.030917549

Sheet 公式枢纽
A1: 公式枢纽
A2: 所有核心计算集中在本页。展示页只引用本页，用户通常不需要修改。
A4: 已纳入分析月份数 | B4: =SUM($K$28:$K$39) -> 2
A5: 总收入 | B5: =SUM($B$28:$B$39) -> 12900
A6: 个人支出合计 | B6: =SUM($C$28:$C$39) -> 10300
A7: 平均每月个人支出 | B7: =IF($B$4=0,0,$B$6/$B$4) -> 5150
A8: 平均每月必要支出 | B8: =IF($B$4=0,0,SUM($D$28:$D$39)/$B$4) -> 4000
A9: 平均每月弹性支出 | B9: =IF($B$4=0,0,SUM($E$28:$E$39)/$B$4) -> 1150
A10: 平均每月固定支出 | B10: =IF($B$4=0,0,SUM($F$28:$F$39)/$B$4) -> 3167.5
A11: 平均每月可变支出 | B11: =IF($B$4=0,0,SUM($G$28:$G$39)/$B$4) -> 1727.5
A12: 平均每月一次性支出 | B12: =IF($B$4=0,0,SUM($H$28:$H$39)/$B$4) -> 255
A13: 平均每月住房支出 | B13: =IF($B$4=0,0,SUM($I$28:$I$39)/$B$4) -> 3000
A14: 住房支出占比 | B14: =IFERROR($B$13/$B$7,0) -> 0.58252427
A15: 储蓄率 | B15: =IFERROR(($B$5-$B$6)/$B$5,0) -> 0.20155039
A16: 当前现金可覆盖月数 | B16: =IFERROR(输入设置!$B$5/$B$7,0) -> 5.8252427
A17: 正常一年生活储备 | B17: =$B$7*12 -> 61800
A18: 必要一年生活储备 | B18: =$B$8*12 -> 48000
A19: 保守一年生活储备 | B19: =MAX($C$28:$C$39)*12 -> 63600
A20: 推荐现金储备 | B20: =MAX($B$7*输入设置!$B$8,输入设置!$B$9)+输入设置!$B$6 -> 62800
A21: 建议可投资资金 | B21: =MAX(0,输入设置!$B$5-$B$20) -> 0
A22: 现金缺口 | B22: =MAX(0,$B$20-输入设置!$B$5) -> 32800
A23: 现金安全等级 | B23: =IF($B$16>=12,"较安全",IF($B$16>=6,"中等安全","偏紧张")) -> 偏紧张
A24: 全年估算消费税 | B24: =消费税分析!$I$17 -> 318.45075
A25: 消费税估算状态 | B25: =IF(税费设置!$B$5="是","已启用","未启用") -> 已启用
A27: 月份 | B27: 总收入 | C27: 个人支出 | D27: 必要支出 | E27: 弹性支出 | F27: 固定支出 | G27: 可变支出 | H27: 一次性支出 | I27: 住房支出 | J27: 净现金流 | K27: 是否纳入平均 | L27: 房产支出 | M27: 投资转账 | N27: 内部转账 | O27: 估算消费税
A28: 2026-01 | B28: =SUMIFS(总收入!$D$4:$D$5000,总收入!$B$4:$B$5000,">="&DATE(VALUE(LEFT($A28,4)),VALUE(RIGHT($A28,2)),1),总收入!$B$4:$B$5000,"<"&DATE(VALUE(LEFT($A28,4)),VALUE(RIGHT($A28,2))+1,1)) -> 6000 | C28: =SUMIFS(总支出!$D$4:$D$5000,总支出!$B$4:$B$5000,">="&DATE(VALUE(LEFT($A28,4)),VALUE(RIGHT($A28,2)),1),总支出!$B$4:$B$5000,"<"&DATE(VALUE(LEFT($A28,4)),VALUE(RIGHT($A28,2))+1,1),总支出!$H$4:$H$5000,"个人支出") -> 5000 | D28: =SUMIFS(总支出!$D$4:$D$5000,总支出!$B$4:$B$5000,">="&DATE(VALUE(LEFT($A28,4)),VALUE(RIGHT($A28,2)),1),总支出!$B$4:$B$5000,"<"&DATE(VALUE(LEFT($A28,4)),VALUE(RIGHT($A28,2))+1,1),总支出!$H$4:$H$5000,"个人支出",总支出!$G$4:$G$5000,"必要") -> 3910 | E28: =SUMIFS(总支出!$D$4:$D$5000,总支出!$B$4:$B$5000,">="&DATE(VALUE(LEFT($A28,4)),VALUE(RIGHT($A28,2)),1),总支出!$B$4:$B$5000,"<"&DATE(VALUE(LEFT($A28,4)),VALUE(RIGHT($A28,2))+1,1),总支出!$H$4:$H$5000,"个人支出",总支出!$G$4:$G$5000,"弹性") -> 1090 | F28: =SUMIFS(总支出!$D$4:$D$5000,总支出!$B$4:$B$5000,">="&DATE(VALUE(LEFT($A28,4)),VALUE(RIGHT($A28,2)),1),总支出!$B$4:$B$5000,"<"&DATE(VALUE(LEFT($A28,4)),VALUE(RIGHT($A28,2))+1,1),总支出!$H$4:$H$5000,"个人支出",总支出!$F$4:$F$5000,"固定") -> 3160 | G28: =SUMIFS(总支出!$D$4:$D$5000,总支出!$B$4:$B$5000,">="&DATE(VALUE(LEFT($A28,4)),VALUE(RIGHT($A28,2)),1),总支出!$B$4:$B$5000,"<"&DATE(VALUE(LEFT($A28,4)),VALUE(RIGHT($A28,2))+1,1),总支出!$H$4:$H$5000,"个人支出",总支出!$F$4:$F$5000,"可变") -> 1620 | H28: =SUMIFS(总支出!$D$4:$D$5000,总支出!$B$4:$B$5000,">="&DATE(VALUE(LEFT($A28,4)),VALUE(RIGHT($A28,2)),1),总支出!$B$4:$B$5000,"<"&DATE(VALUE(LEFT($A28,4)),VALUE(RIGHT($A28,2))+1,1),总支出!$H$4:$H$5000,"个人支出",总支出!$F$4:$F$5000,"一次性") -> 220 | I28: =SUMIFS(总支出!$D$4:$D$5000,总支出!$B$4:$B$5000,">="&DATE(VALUE(LEFT($A28,4)),VALUE(RIGHT($A28,2)),1),总支出!$B$4:$B$5000,"<"&DATE(VALUE(LEFT($A28,4)),VALUE(RIGHT($A28,2))+1,1),总支出!$H$4:$H$5000,"个人支出",总支出!$E$4:$E$5000,"住房") -> 3000 | J28: =B28-C28 -> 1000 | K28: =IF(OR(B28>0,C28>0),1,0) -> 1 | L28: =SUMIFS(总支出!$D$4:$D$5000,总支出!$B$4:$B$5000,">="&DATE(VALUE(LEFT($A28,4)),VALUE(RIGHT($A28,2)),1),总支出!$B$4:$B$5000,"<"&DATE(VALUE(LEFT($A28,4)),VALUE(RIGHT($A28,2))+1,1),总支出!$H$4:$H$5000,"房产支出") -> 0 | M28: =SUMIFS(总支出!$D$4:$D$5000,总支出!$B$4:$B$5000,">="&DATE(VALUE(LEFT($A28,4)),VALUE(RIGHT($A28,2)),1),总支出!$B$4:$B$5000,"<"&DATE(VALUE(LEFT($A28,4)),VALUE(RIGHT($A28,2))+1,1),总支出!$H$4:$H$5000,"投资转账") -> 0 | N28: =SUMIFS(总支出!$D$4:$D$5000,总支出!$B$4:$B$5000,">="&DATE(VALUE(LEFT($A28,4)),VALUE(RIGHT($A28,2)),1),总支出!$B$4:$B$5000,"<"&DATE(VALUE(LEFT($A28,4)),VALUE(RIGHT($A28,2))+1,1),总支出!$H$4:$H$5000,"内部转账") -> 0 | O28: =SUMIFS(税费计算明细!$S$4:$S$5000,税费计算明细!$C$4:$C$5000,$A28) -> 148.4801
A29: 2026-02 | B29: =SUMIFS(总收入!$D$4:$D$5000,总收入!$B$4:$B$5000,">="&DATE(VALUE(LEFT($A29,4)),VALUE(RIGHT($A29,2)),1),总收入!$B$4:$B$5000,"<"&DATE(VALUE(LEFT($A29,4)),VALUE(RIGHT($A29,2))+1,1)) -> 6900 | C29: =SUMIFS(总支出!$D$4:$D$5000,总支出!$B$4:$B$5000,">="&DATE(VALUE(LEFT($A29,4)),VALUE(RIGHT($A29,2)),1),总支出!$B$4:$B$5000,"<"&DATE(VALUE(LEFT($A29,4)),VALUE(RIGHT($A29,2))+1,1),总支出!$H$4:$H$5000,"个人支出") -> 5300 | D29: =SUMIFS(总支出!$D$4:$D$5000,总支出!$B$4:$B$5000,">="&DATE(VALUE(LEFT($A29,4)),VALUE(RIGHT($A29,2)),1),总支出!$B$4:$B$5000,"<"&DATE(VALUE(LEFT($A29,4)),VALUE(RIGHT($A29,2))+1,1),总支出!$H$4:$H$5000,"个人支出",总支出!$G$4:$G$5000,"必要") -> 4090 | E29: =SUMIFS(总支出!$D$4:$D$5000,总支出!$B$4:$B$5000,">="&DATE(VALUE(LEFT($A29,4)),VALUE(RIGHT($A29,2)),1),总支出!$B$4:$B$5000,"<"&DATE(VALUE(LEFT($A29,4)),VALUE(RIGHT($A29,2))+1,1),总支出!$H$4:$H$5000,"个人支出",总支出!$G$4:$G$5000,"弹性") -> 1210 | F29: =SUMIFS(总支出!$D$4:$D$5000,总支出!$B$4:$B$5000,">="&DATE(VALUE(LEFT($A29,4)),VALUE(RIGHT($A29,2)),1),总支出!$B$4:$B$5000,"<"&DATE(VALUE(LEFT($A29,4)),VALUE(RIGHT($A29,2))+1,1),总支出!$H$4:$H$5000,"个人支出",总支出!$F$4:$F$5000,"固定") -> 3175 | G29: =SUMIFS(总支出!$D$4:$D$5000,总支出!$B$4:$B$5000,">="&DATE(VALUE(LEFT($A29,4)),VALUE(RIGHT($A29,2)),1),总支出!$B$4:$B$5000,"<"&DATE(VALUE(LEFT($A29,4)),VALUE(RIGHT($A29,2))+1,1),总支出!$H$4:$H$5000,"个人支出",总支出!$F$4:$F$5000,"可变") -> 1835 | H29: =SUMIFS(总支出!$D$4:$D$5000,总支出!$B$4:$B$5000,">="&DATE(VALUE(LEFT($A29,4)),VALUE(RIGHT($A29,2)),1),总支出!$B$4:$B$5000,"<"&DATE(VALUE(LEFT($A29,4)),VALUE(RIGHT($A29,2))+1,1),总支出!$H$4:$H$5000,"个人支出",总支出!$F$4:$F$5000,"一次性") -> 290 | I29: =SUMIFS(总支出!$D$4:$D$5000,总支出!$B$4:$B$5000,">="&DATE(VALUE(LEFT($A29,4)),VALUE(RIGHT($A29,2)),1),总支出!$B$4:$B$5000,"<"&DATE(VALUE(LEFT($A29,4)),VALUE(RIGHT($A29,2))+1,1),总支出!$H$4:$H$5000,"个人支出",总支出!$E$4:$E$5000,"住房") -> 3000 | J29: =B29-C29 -> 1600 | K29: =IF(OR(B29>0,C29>0),1,0) -> 1 | L29: =SUMIFS(总支出!$D$4:$D$5000,总支出!$B$4:$B$5000,">="&DATE(VALUE(LEFT($A29,4)),VALUE(RIGHT($A29,2)),1),总支出!$B$4:$B$5000,"<"&DATE(VALUE(LEFT($A29,4)),VALUE(RIGHT($A29,2))+1,1),总支出!$H$4:$H$5000,"房产支出") -> 0 | M29: =SUMIFS(总支出!$D$4:$D$5000,总支出!$B$4:$B$5000,">="&DATE(VALUE(LEFT($A29,4)),VALUE(RIGHT($A29,2)),1),总支出!$B$4:$B$5000,"<"&DATE(VALUE(LEFT($A29,4)),VALUE(RIGHT($A29,2))+1,1),总支出!$H$4:$H$5000,"投资转账") -> 0 | N29: =SUMIFS(总支出!$D$4:$D$5000,总支出!$B$4:$B$5000,">="&DATE(VALUE(LEFT($A29,4)),VALUE(RIGHT($A29,2)),1),总支出!$B$4:$B$5000,"<"&DATE(VALUE(LEFT($A29,4)),VALUE(RIGHT($A29,2))+1,1),总支出!$H$4:$H$5000,"内部转账") -> 0 | O29: =SUMIFS(税费计算明细!$S$4:$S$5000,税费计算明细!$C$4:$C$5000,$A29) -> 169.97065
A30: 2026-03 | B30: =SUMIFS(总收入!$D$4:$D$5000,总收入!$B$4:$B$5000,">="&DATE(VALUE(LEFT($A30,4)),VALUE(RIGHT($A30,2)),1),总收入!$B$4:$B$5000,"<"&DATE(VALUE(LEFT($A30,4)),VALUE(RIGHT($A30,2))+1,1)) -> 0 | C30: =SUMIFS(总支出!$D$4:$D$5000,总支出!$B$4:$B$5000,">="&DATE(VALUE(LEFT($A30,4)),VALUE(RIGHT($A30,2)),1),总支出!$B$4:$B$5000,"<"&DATE(VALUE(LEFT($A30,4)),VALUE(RIGHT($A30,2))+1,1),总支出!$H$4:$H$5000,"个人支出") -> 0 | D30: =SUMIFS(总支出!$D$4:$D$5000,总支出!$B$4:$B$5000,">="&DATE(VALUE(LEFT($A30,4)),VALUE(RIGHT($A30,2)),1),总支出!$B$4:$B$5000,"<"&DATE(VALUE(LEFT($A30,4)),VALUE(RIGHT($A30,2))+1,1),总支出!$H$4:$H$5000,"个人支出",总支出!$G$4:$G$5000,"必要") -> 0 | E30: =SUMIFS(总支出!$D$4:$D$5000,总支出!$B$4:$B$5000,">="&DATE(VALUE(LEFT($A30,4)),VALUE(RIGHT($A30,2)),1),总支出!$B$4:$B$5000,"<"&DATE(VALUE(LEFT($A30,4)),VALUE(RIGHT($A30,2))+1,1),总支出!$H$4:$H$5000,"个人支出",总支出!$G$4:$G$5000,"弹性") -> 0 | F30: =SUMIFS(总支出!$D$4:$D$5000,总支出!$B$4:$B$5000,">="&DATE(VALUE(LEFT($A30,4)),VALUE(RIGHT($A30,2)),1),总支出!$B$4:$B$5000,"<"&DATE(VALUE(LEFT($A30,4)),VALUE(RIGHT($A30,2))+1,1),总支出!$H$4:$H$5000,"个人支出",总支出!$F$4:$F$5000,"固定") -> 0 | G30: =SUMIFS(总支出!$D$4:$D$5000,总支出!$B$4:$B$5000,">="&DATE(VALUE(LEFT($A30,4)),VALUE(RIGHT($A30,2)),1),总支出!$B$4:$B$5000,"<"&DATE(VALUE(LEFT($A30,4)),VALUE(RIGHT($A30,2))+1,1),总支出!$H$4:$H$5000,"个人支出",总支出!$F$4:$F$5000,"可变") -> 0 | H30: =SUMIFS(总支出!$D$4:$D$5000,总支出!$B$4:$B$5000,">="&DATE(VALUE(LEFT($A30,4)),VALUE(RIGHT($A30,2)),1),总支出!$B$4:$B$5000,"<"&DATE(VALUE(LEFT($A30,4)),VALUE(RIGHT($A30,2))+1,1),总支出!$H$4:$H$5000,"个人支出",总支出!$F$4:$F$5000,"一次性") -> 0 | I30: =SUMIFS(总支出!$D$4:$D$5000,总支出!$B$4:$B$5000,">="&DATE(VALUE(LEFT($A30,4)),VALUE(RIGHT($A30,2)),1),总支出!$B$4:$B$5000,"<"&DATE(VALUE(LEFT($A30,4)),VALUE(RIGHT($A30,2))+1,1),总支出!$H$4:$H$5000,"个人支出",总支出!$E$4:$E$5000,"住房") -> 0 | J30: =B30-C30 -> 0 | K30: =IF(OR(B30>0,C30>0),1,0) -> 0 | L30: =SUMIFS(总支出!$D$4:$D$5000,总支出!$B$4:$B$5000,">="&DATE(VALUE(LEFT($A30,4)),VALUE(RIGHT($A30,2)),1),总支出!$B$4:$B$5000,"<"&DATE(VALUE(LEFT($A30,4)),VALUE(RIGHT($A30,2))+1,1),总支出!$H$4:$H$5000,"房产支出") -> 0 | M30: =SUMIFS(总支出!$D$4:$D$5000,总支出!$B$4:$B$5000,">="&DATE(VALUE(LEFT($A30,4)),VALUE(RIGHT($A30,2)),1),总支出!$B$4:$B$5000,"<"&DATE(VALUE(LEFT($A30,4)),VALUE(RIGHT($A30,2))+1,1),总支出!$H$4:$H$5000,"投资转账") -> 0 | N30: =SUMIFS(总支出!$D$4:$D$5000,总支出!$B$4:$B$5000,">="&DATE(VALUE(LEFT($A30,4)),VALUE(RIGHT($A30,2)),1),总支出!$B$4:$B$5000,"<"&DATE(VALUE(LEFT($A30,4)),VALUE(RIGHT($A30,2))+1,1),总支出!$H$4:$H$5000,"内部转账") -> 0 | O30: =SUMIFS(税费计算明细!$S$4:$S$5000,税费计算明细!$C$4:$C$5000,$A30) -> 0
A31: 2026-04 | B31: =SUMIFS(总收入!$D$4:$D$5000,总收入!$B$4:$B$5000,">="&DATE(VALUE(LEFT($A31,4)),VALUE(RIGHT($A31,2)),1),总收入!$B$4:$B$5000,"<"&DATE(VALUE(LEFT($A31,4)),VALUE(RIGHT($A31,2))+1,1)) -> 0 | C31: =SUMIFS(总支出!$D$4:$D$5000,总支出!$B$4:$B$5000,">="&DATE(VALUE(LEFT($A31,4)),VALUE(RIGHT($A31,2)),1),总支出!$B$4:$B$5000,"<"&DATE(VALUE(LEFT($A31,4)),VALUE(RIGHT($A31,2))+1,1),总支出!$H$4:$H$5000,"个人支出") -> 0 | D31: =SUMIFS(总支出!$D$4:$D$5000,总支出!$B$4:$B$5000,">="&DATE(VALUE(LEFT($A31,4)),VALUE(RIGHT($A31,2)),1),总支出!$B$4:$B$5000,"<"&DATE(VALUE(LEFT($A31,4)),VALUE(RIGHT($A31,2))+1,1),总支出!$H$4:$H$5000,"个人支出",总支出!$G$4:$G$5000,"必要") -> 0 | E31: =SUMIFS(总支出!$D$4:$D$5000,总支出!$B$4:$B$5000,">="&DATE(VALUE(LEFT($A31,4)),VALUE(RIGHT($A31,2)),1),总支出!$B$4:$B$5000,"<"&DATE(VALUE(LEFT($A31,4)),VALUE(RIGHT($A31,2))+1,1),总支出!$H$4:$H$5000,"个人支出",总支出!$G$4:$G$5000,"弹性") -> 0 | F31: =SUMIFS(总支出!$D$4:$D$5000,总支出!$B$4:$B$5000,">="&DATE(VALUE(LEFT($A31,4)),VALUE(RIGHT($A31,2)),1),总支出!$B$4:$B$5000,"<"&DATE(VALUE(LEFT($A31,4)),VALUE(RIGHT($A31,2))+1,1),总支出!$H$4:$H$5000,"个人支出",总支出!$F$4:$F$5000,"固定") -> 0 | G31: =SUMIFS(总支出!$D$4:$D$5000,总支出!$B$4:$B$5000,">="&DATE(VALUE(LEFT($A31,4)),VALUE(RIGHT($A31,2)),1),总支出!$B$4:$B$5000,"<"&DATE(VALUE(LEFT($A31,4)),VALUE(RIGHT($A31,2))+1,1),总支出!$H$4:$H$5000,"个人支出",总支出!$F$4:$F$5000,"可变") -> 0 | H31: =SUMIFS(总支出!$D$4:$D$5000,总支出!$B$4:$B$5000,">="&DATE(VALUE(LEFT($A31,4)),VALUE(RIGHT($A31,2)),1),总支出!$B$4:$B$5000,"<"&DATE(VALUE(LEFT($A31,4)),VALUE(RIGHT($A31,2))+1,1),总支出!$H$4:$H$5000,"个人支出",总支出!$F$4:$F$5000,"一次性") -> 0 | I31: =SUMIFS(总支出!$D$4:$D$5000,总支出!$B$4:$B$5000,">="&DATE(VALUE(LEFT($A31,4)),VALUE(RIGHT($A31,2)),1),总支出!$B$4:$B$5000,"<"&DATE(VALUE(LEFT($A31,4)),VALUE(RIGHT($A31,2))+1,1),总支出!$H$4:$H$5000,"个人支出",总支出!$E$4:$E$5000,"住房") -> 0 | J31: =B31-C31 -> 0 | K31: =IF(OR(B31>0,C31>0),1,0) -> 0 | L31: =SUMIFS(总支出!$D$4:$D$5000,总支出!$B$4:$B$5000,">="&DATE(VALUE(LEFT($A31,4)),VALUE(RIGHT($A31,2)),1),总支出!$B$4:$B$5000,"<"&DATE(VALUE(LEFT($A31,4)),VALUE(RIGHT($A31,2))+1,1),总支出!$H$4:$H$5000,"房产支出") -> 0 | M31: =SUMIFS(总支出!$D$4:$D$5000,总支出!$B$4:$B$5000,">="&DATE(VALUE(LEFT($A31,4)),VALUE(RIGHT($A31,2)),1),总支出!$B$4:$B$5000,"<"&DATE(VALUE(LEFT($A31,4)),VALUE(RIGHT($A31,2))+1,1),总支出!$H$4:$H$5000,"投资转账") -> 0 | N31: =SUMIFS(总支出!$D$4:$D$5000,总支出!$B$4:$B$5000,">="&DATE(VALUE(LEFT($A31,4)),VALUE(RIGHT($A31,2)),1),总支出!$B$4:$B$5000,"<"&DATE(VALUE(LEFT($A31,4)),VALUE(RIGHT($A31,2))+1,1),总支出!$H$4:$H$5000,"内部转账") -> 0 | O31: =SUMIFS(税费计算明细!$S$4:$S$5000,税费计算明细!$C$4:$C$5000,$A31) -> 0
A32: 2026-05 | B32: =SUMIFS(总收入!$D$4:$D$5000,总收入!$B$4:$B$5000,">="&DATE(VALUE(LEFT($A32,4)),VALUE(RIGHT($A32,2)),1),总收入!$B$4:$B$5000,"<"&DATE(VALUE(LEFT($A32,4)),VALUE(RIGHT($A32,2))+1,1)) -> 0 | C32: =SUMIFS(总支出!$D$4:$D$5000,总支出!$B$4:$B$5000,">="&DATE(VALUE(LEFT($A32,4)),VALUE(RIGHT($A32,2)),1),总支出!$B$4:$B$5000,"<"&DATE(VALUE(LEFT($A32,4)),VALUE(RIGHT($A32,2))+1,1),总支出!$H$4:$H$5000,"个人支出") -> 0 | D32: =SUMIFS(总支出!$D$4:$D$5000,总支出!$B$4:$B$5000,">="&DATE(VALUE(LEFT($A32,4)),VALUE(RIGHT($A32,2)),1),总支出!$B$4:$B$5000,"<"&DATE(VALUE(LEFT($A32,4)),VALUE(RIGHT($A32,2))+1,1),总支出!$H$4:$H$5000,"个人支出",总支出!$G$4:$G$5000,"必要") -> 0 | E32: =SUMIFS(总支出!$D$4:$D$5000,总支出!$B$4:$B$5000,">="&DATE(VALUE(LEFT($A32,4)),VALUE(RIGHT($A32,2)),1),总支出!$B$4:$B$5000,"<"&DATE(VALUE(LEFT($A32,4)),VALUE(RIGHT($A32,2))+1,1),总支出!$H$4:$H$5000,"个人支出",总支出!$G$4:$G$5000,"弹性") -> 0 | F32: =SUMIFS(总支出!$D$4:$D$5000,总支出!$B$4:$B$5000,">="&DATE(VALUE(LEFT($A32,4)),VALUE(RIGHT($A32,2)),1),总支出!$B$4:$B$5000,"<"&DATE(VALUE(LEFT($A32,4)),VALUE(RIGHT($A32,2))+1,1),总支出!$H$4:$H$5000,"个人支出",总支出!$F$4:$F$5000,"固定") -> 0 | G32: =SUMIFS(总支出!$D$4:$D$5000,总支出!$B$4:$B$5000,">="&DATE(VALUE(LEFT($A32,4)),VALUE(RIGHT($A32,2)),1),总支出!$B$4:$B$5000,"<"&DATE(VALUE(LEFT($A32,4)),VALUE(RIGHT($A32,2))+1,1),总支出!$H$4:$H$5000,"个人支出",总支出!$F$4:$F$5000,"可变") -> 0 | H32: =SUMIFS(总支出!$D$4:$D$5000,总支出!$B$4:$B$5000,">="&DATE(VALUE(LEFT($A32,4)),VALUE(RIGHT($A32,2)),1),总支出!$B$4:$B$5000,"<"&DATE(VALUE(LEFT($A32,4)),VALUE(RIGHT($A32,2))+1,1),总支出!$H$4:$H$5000,"个人支出",总支出!$F$4:$F$5000,"一次性") -> 0 | I32: =SUMIFS(总支出!$D$4:$D$5000,总支出!$B$4:$B$5000,">="&DATE(VALUE(LEFT($A32,4)),VALUE(RIGHT($A32,2)),1),总支出!$B$4:$B$5000,"<"&DATE(VALUE(LEFT($A32,4)),VALUE(RIGHT($A32,2))+1,1),总支出!$H$4:$H$5000,"个人支出",总支出!$E$4:$E$5000,"住房") -> 0 | J32: =B32-C32 -> 0 | K32: =IF(OR(B32>0,C32>0),1,0) -> 0 | L32: =SUMIFS(总支出!$D$4:$D$5000,总支出!$B$4:$B$5000,">="&DATE(VALUE(LEFT($A32,4)),VALUE(RIGHT($A32,2)),1),总支出!$B$4:$B$5000,"<"&DATE(VALUE(LEFT($A32,4)),VALUE(RIGHT($A32,2))+1,1),总支出!$H$4:$H$5000,"房产支出") -> 0 | M32: =SUMIFS(总支出!$D$4:$D$5000,总支出!$B$4:$B$5000,">="&DATE(VALUE(LEFT($A32,4)),VALUE(RIGHT($A32,2)),1),总支出!$B$4:$B$5000,"<"&DATE(VALUE(LEFT($A32,4)),VALUE(RIGHT($A32,2))+1,1),总支出!$H$4:$H$5000,"投资转账") -> 0 | N32: =SUMIFS(总支出!$D$4:$D$5000,总支出!$B$4:$B$5000,">="&DATE(VALUE(LEFT($A32,4)),VALUE(RIGHT($A32,2)),1),总支出!$B$4:$B$5000,"<"&DATE(VALUE(LEFT($A32,4)),VALUE(RIGHT($A32,2))+1,1),总支出!$H$4:$H$5000,"内部转账") -> 0 | O32: =SUMIFS(税费计算明细!$S$4:$S$5000,税费计算明细!$C$4:$C$5000,$A32) -> 0
A33: 2026-06 | B33: =SUMIFS(总收入!$D$4:$D$5000,总收入!$B$4:$B$5000,">="&DATE(VALUE(LEFT($A33,4)),VALUE(RIGHT($A33,2)),1),总收入!$B$4:$B$5000,"<"&DATE(VALUE(LEFT($A33,4)),VALUE(RIGHT($A33,2))+1,1)) -> 0 | C33: =SUMIFS(总支出!$D$4:$D$5000,总支出!$B$4:$B$5000,">="&DATE(VALUE(LEFT($A33,4)),VALUE(RIGHT($A33,2)),1),总支出!$B$4:$B$5000,"<"&DATE(VALUE(LEFT($A33,4)),VALUE(RIGHT($A33,2))+1,1),总支出!$H$4:$H$5000,"个人支出") -> 0 | D33: =SUMIFS(总支出!$D$4:$D$5000,总支出!$B$4:$B$5000,">="&DATE(VALUE(LEFT($A33,4)),VALUE(RIGHT($A33,2)),1),总支出!$B$4:$B$5000,"<"&DATE(VALUE(LEFT($A33,4)),VALUE(RIGHT($A33,2))+1,1),总支出!$H$4:$H$5000,"个人支出",总支出!$G$4:$G$5000,"必要") -> 0 | E33: =SUMIFS(总支出!$D$4:$D$5000,总支出!$B$4:$B$5000,">="&DATE(VALUE(LEFT($A33,4)),VALUE(RIGHT($A33,2)),1),总支出!$B$4:$B$5000,"<"&DATE(VALUE(LEFT($A33,4)),VALUE(RIGHT($A33,2))+1,1),总支出!$H$4:$H$5000,"个人支出",总支出!$G$4:$G$5000,"弹性") -> 0 | F33: =SUMIFS(总支出!$D$4:$D$5000,总支出!$B$4:$B$5000,">="&DATE(VALUE(LEFT($A33,4)),VALUE(RIGHT($A33,2)),1),总支出!$B$4:$B$5000,"<"&DATE(VALUE(LEFT($A33,4)),VALUE(RIGHT($A33,2))+1,1),总支出!$H$4:$H$5000,"个人支出",总支出!$F$4:$F$5000,"固定") -> 0 | G33: =SUMIFS(总支出!$D$4:$D$5000,总支出!$B$4:$B$5000,">="&DATE(VALUE(LEFT($A33,4)),VALUE(RIGHT($A33,2)),1),总支出!$B$4:$B$5000,"<"&DATE(VALUE(LEFT($A33,4)),VALUE(RIGHT($A33,2))+1,1),总支出!$H$4:$H$5000,"个人支出",总支出!$F$4:$F$5000,"可变") -> 0 | H33: =SUMIFS(总支出!$D$4:$D$5000,总支出!$B$4:$B$5000,">="&DATE(VALUE(LEFT($A33,4)),VALUE(RIGHT($A33,2)),1),总支出!$B$4:$B$5000,"<"&DATE(VALUE(LEFT($A33,4)),VALUE(RIGHT($A33,2))+1,1),总支出!$H$4:$H$5000,"个人支出",总支出!$F$4:$F$5000,"一次性") -> 0 | I33: =SUMIFS(总支出!$D$4:$D$5000,总支出!$B$4:$B$5000,">="&DATE(VALUE(LEFT($A33,4)),VALUE(RIGHT($A33,2)),1),总支出!$B$4:$B$5000,"<"&DATE(VALUE(LEFT($A33,4)),VALUE(RIGHT($A33,2))+1,1),总支出!$H$4:$H$5000,"个人支出",总支出!$E$4:$E$5000,"住房") -> 0 | J33: =B33-C33 -> 0 | K33: =IF(OR(B33>0,C33>0),1,0) -> 0 | L33: =SUMIFS(总支出!$D$4:$D$5000,总支出!$B$4:$B$5000,">="&DATE(VALUE(LEFT($A33,4)),VALUE(RIGHT($A33,2)),1),总支出!$B$4:$B$5000,"<"&DATE(VALUE(LEFT($A33,4)),VALUE(RIGHT($A33,2))+1,1),总支出!$H$4:$H$5000,"房产支出") -> 0 | M33: =SUMIFS(总支出!$D$4:$D$5000,总支出!$B$4:$B$5000,">="&DATE(VALUE(LEFT($A33,4)),VALUE(RIGHT($A33,2)),1),总支出!$B$4:$B$5000,"<"&DATE(VALUE(LEFT($A33,4)),VALUE(RIGHT($A33,2))+1,1),总支出!$H$4:$H$5000,"投资转账") -> 0 | N33: =SUMIFS(总支出!$D$4:$D$5000,总支出!$B$4:$B$5000,">="&DATE(VALUE(LEFT($A33,4)),VALUE(RIGHT($A33,2)),1),总支出!$B$4:$B$5000,"<"&DATE(VALUE(LEFT($A33,4)),VALUE(RIGHT($A33,2))+1,1),总支出!$H$4:$H$5000,"内部转账") -> 0 | O33: =SUMIFS(税费计算明细!$S$4:$S$5000,税费计算明细!$C$4:$C$5000,$A33) -> 0
A34: 2026-07 | B34: =SUMIFS(总收入!$D$4:$D$5000,总收入!$B$4:$B$5000,">="&DATE(VALUE(LEFT($A34,4)),VALUE(RIGHT($A34,2)),1),总收入!$B$4:$B$5000,"<"&DATE(VALUE(LEFT($A34,4)),VALUE(RIGHT($A34,2))+1,1)) -> 0 | C34: =SUMIFS(总支出!$D$4:$D$5000,总支出!$B$4:$B$5000,">="&DATE(VALUE(LEFT($A34,4)),VALUE(RIGHT($A34,2)),1),总支出!$B$4:$B$5000,"<"&DATE(VALUE(LEFT($A34,4)),VALUE(RIGHT($A34,2))+1,1),总支出!$H$4:$H$5000,"个人支出") -> 0 | D34: =SUMIFS(总支出!$D$4:$D$5000,总支出!$B$4:$B$5000,">="&DATE(VALUE(LEFT($A34,4)),VALUE(RIGHT($A34,2)),1),总支出!$B$4:$B$5000,"<"&DATE(VALUE(LEFT($A34,4)),VALUE(RIGHT($A34,2))+1,1),总支出!$H$4:$H$5000,"个人支出",总支出!$G$4:$G$5000,"必要") -> 0 | E34: =SUMIFS(总支出!$D$4:$D$5000,总支出!$B$4:$B$5000,">="&DATE(VALUE(LEFT($A34,4)),VALUE(RIGHT($A34,2)),1),总支出!$B$4:$B$5000,"<"&DATE(VALUE(LEFT($A34,4)),VALUE(RIGHT($A34,2))+1,1),总支出!$H$4:$H$5000,"个人支出",总支出!$G$4:$G$5000,"弹性") -> 0 | F34: =SUMIFS(总支出!$D$4:$D$5000,总支出!$B$4:$B$5000,">="&DATE(VALUE(LEFT($A34,4)),VALUE(RIGHT($A34,2)),1),总支出!$B$4:$B$5000,"<"&DATE(VALUE(LEFT($A34,4)),VALUE(RIGHT($A34,2))+1,1),总支出!$H$4:$H$5000,"个人支出",总支出!$F$4:$F$5000,"固定") -> 0 | G34: =SUMIFS(总支出!$D$4:$D$5000,总支出!$B$4:$B$5000,">="&DATE(VALUE(LEFT($A34,4)),VALUE(RIGHT($A34,2)),1),总支出!$B$4:$B$5000,"<"&DATE(VALUE(LEFT($A34,4)),VALUE(RIGHT($A34,2))+1,1),总支出!$H$4:$H$5000,"个人支出",总支出!$F$4:$F$5000,"可变") -> 0 | H34: =SUMIFS(总支出!$D$4:$D$5000,总支出!$B$4:$B$5000,">="&DATE(VALUE(LEFT($A34,4)),VALUE(RIGHT($A34,2)),1),总支出!$B$4:$B$5000,"<"&DATE(VALUE(LEFT($A34,4)),VALUE(RIGHT($A34,2))+1,1),总支出!$H$4:$H$5000,"个人支出",总支出!$F$4:$F$5000,"一次性") -> 0 | I34: =SUMIFS(总支出!$D$4:$D$5000,总支出!$B$4:$B$5000,">="&DATE(VALUE(LEFT($A34,4)),VALUE(RIGHT($A34,2)),1),总支出!$B$4:$B$5000,"<"&DATE(VALUE(LEFT($A34,4)),VALUE(RIGHT($A34,2))+1,1),总支出!$H$4:$H$5000,"个人支出",总支出!$E$4:$E$5000,"住房") -> 0 | J34: =B34-C34 -> 0 | K34: =IF(OR(B34>0,C34>0),1,0) -> 0 | L34: =SUMIFS(总支出!$D$4:$D$5000,总支出!$B$4:$B$5000,">="&DATE(VALUE(LEFT($A34,4)),VALUE(RIGHT($A34,2)),1),总支出!$B$4:$B$5000,"<"&DATE(VALUE(LEFT($A34,4)),VALUE(RIGHT($A34,2))+1,1),总支出!$H$4:$H$5000,"房产支出") -> 0 | M34: =SUMIFS(总支出!$D$4:$D$5000,总支出!$B$4:$B$5000,">="&DATE(VALUE(LEFT($A34,4)),VALUE(RIGHT($A34,2)),1),总支出!$B$4:$B$5000,"<"&DATE(VALUE(LEFT($A34,4)),VALUE(RIGHT($A34,2))+1,1),总支出!$H$4:$H$5000,"投资转账") -> 0 | N34: =SUMIFS(总支出!$D$4:$D$5000,总支出!$B$4:$B$5000,">="&DATE(VALUE(LEFT($A34,4)),VALUE(RIGHT($A34,2)),1),总支出!$B$4:$B$5000,"<"&DATE(VALUE(LEFT($A34,4)),VALUE(RIGHT($A34,2))+1,1),总支出!$H$4:$H$5000,"内部转账") -> 0 | O34: =SUMIFS(税费计算明细!$S$4:$S$5000,税费计算明细!$C$4:$C$5000,$A34) -> 0
A35: 2026-08 | B35: =SUMIFS(总收入!$D$4:$D$5000,总收入!$B$4:$B$5000,">="&DATE(VALUE(LEFT($A35,4)),VALUE(RIGHT($A35,2)),1),总收入!$B$4:$B$5000,"<"&DATE(VALUE(LEFT($A35,4)),VALUE(RIGHT($A35,2))+1,1)) -> 0 | C35: =SUMIFS(总支出!$D$4:$D$5000,总支出!$B$4:$B$5000,">="&DATE(VALUE(LEFT($A35,4)),VALUE(RIGHT($A35,2)),1),总支出!$B$4:$B$5000,"<"&DATE(VALUE(LEFT($A35,4)),VALUE(RIGHT($A35,2))+1,1),总支出!$H$4:$H$5000,"个人支出") -> 0 | D35: =SUMIFS(总支出!$D$4:$D$5000,总支出!$B$4:$B$5000,">="&DATE(VALUE(LEFT($A35,4)),VALUE(RIGHT($A35,2)),1),总支出!$B$4:$B$5000,"<"&DATE(VALUE(LEFT($A35,4)),VALUE(RIGHT($A35,2))+1,1),总支出!$H$4:$H$5000,"个人支出",总支出!$G$4:$G$5000,"必要") -> 0 | E35: =SUMIFS(总支出!$D$4:$D$5000,总支出!$B$4:$B$5000,">="&DATE(VALUE(LEFT($A35,4)),VALUE(RIGHT($A35,2)),1),总支出!$B$4:$B$5000,"<"&DATE(VALUE(LEFT($A35,4)),VALUE(RIGHT($A35,2))+1,1),总支出!$H$4:$H$5000,"个人支出",总支出!$G$4:$G$5000,"弹性") -> 0 | F35: =SUMIFS(总支出!$D$4:$D$5000,总支出!$B$4:$B$5000,">="&DATE(VALUE(LEFT($A35,4)),VALUE(RIGHT($A35,2)),1),总支出!$B$4:$B$5000,"<"&DATE(VALUE(LEFT($A35,4)),VALUE(RIGHT($A35,2))+1,1),总支出!$H$4:$H$5000,"个人支出",总支出!$F$4:$F$5000,"固定") -> 0 | G35: =SUMIFS(总支出!$D$4:$D$5000,总支出!$B$4:$B$5000,">="&DATE(VALUE(LEFT($A35,4)),VALUE(RIGHT($A35,2)),1),总支出!$B$4:$B$5000,"<"&DATE(VALUE(LEFT($A35,4)),VALUE(RIGHT($A35,2))+1,1),总支出!$H$4:$H$5000,"个人支出",总支出!$F$4:$F$5000,"可变") -> 0 | H35: =SUMIFS(总支出!$D$4:$D$5000,总支出!$B$4:$B$5000,">="&DATE(VALUE(LEFT($A35,4)),VALUE(RIGHT($A35,2)),1),总支出!$B$4:$B$5000,"<"&DATE(VALUE(LEFT($A35,4)),VALUE(RIGHT($A35,2))+1,1),总支出!$H$4:$H$5000,"个人支出",总支出!$F$4:$F$5000,"一次性") -> 0 | I35: =SUMIFS(总支出!$D$4:$D$5000,总支出!$B$4:$B$5000,">="&DATE(VALUE(LEFT($A35,4)),VALUE(RIGHT($A35,2)),1),总支出!$B$4:$B$5000,"<"&DATE(VALUE(LEFT($A35,4)),VALUE(RIGHT($A35,2))+1,1),总支出!$H$4:$H$5000,"个人支出",总支出!$E$4:$E$5000,"住房") -> 0 | J35: =B35-C35 -> 0 | K35: =IF(OR(B35>0,C35>0),1,0) -> 0 | L35: =SUMIFS(总支出!$D$4:$D$5000,总支出!$B$4:$B$5000,">="&DATE(VALUE(LEFT($A35,4)),VALUE(RIGHT($A35,2)),1),总支出!$B$4:$B$5000,"<"&DATE(VALUE(LEFT($A35,4)),VALUE(RIGHT($A35,2))+1,1),总支出!$H$4:$H$5000,"房产支出") -> 0 | M35: =SUMIFS(总支出!$D$4:$D$5000,总支出!$B$4:$B$5000,">="&DATE(VALUE(LEFT($A35,4)),VALUE(RIGHT($A35,2)),1),总支出!$B$4:$B$5000,"<"&DATE(VALUE(LEFT($A35,4)),VALUE(RIGHT($A35,2))+1,1),总支出!$H$4:$H$5000,"投资转账") -> 0 | N35: =SUMIFS(总支出!$D$4:$D$5000,总支出!$B$4:$B$5000,">="&DATE(VALUE(LEFT($A35,4)),VALUE(RIGHT($A35,2)),1),总支出!$B$4:$B$5000,"<"&DATE(VALUE(LEFT($A35,4)),VALUE(RIGHT($A35,2))+1,1),总支出!$H$4:$H$5000,"内部转账") -> 0 | O35: =SUMIFS(税费计算明细!$S$4:$S$5000,税费计算明细!$C$4:$C$5000,$A35) -> 0
A36: 2026-09 | B36: =SUMIFS(总收入!$D$4:$D$5000,总收入!$B$4:$B$5000,">="&DATE(VALUE(LEFT($A36,4)),VALUE(RIGHT($A36,2)),1),总收入!$B$4:$B$5000,"<"&DATE(VALUE(LEFT($A36,4)),VALUE(RIGHT($A36,2))+1,1)) -> 0 | C36: =SUMIFS(总支出!$D$4:$D$5000,总支出!$B$4:$B$5000,">="&DATE(VALUE(LEFT($A36,4)),VALUE(RIGHT($A36,2)),1),总支出!$B$4:$B$5000,"<"&DATE(VALUE(LEFT($A36,4)),VALUE(RIGHT($A36,2))+1,1),总支出!$H$4:$H$5000,"个人支出") -> 0 | D36: =SUMIFS(总支出!$D$4:$D$5000,总支出!$B$4:$B$5000,">="&DATE(VALUE(LEFT($A36,4)),VALUE(RIGHT($A36,2)),1),总支出!$B$4:$B$5000,"<"&DATE(VALUE(LEFT($A36,4)),VALUE(RIGHT($A36,2))+1,1),总支出!$H$4:$H$5000,"个人支出",总支出!$G$4:$G$5000,"必要") -> 0 | E36: =SUMIFS(总支出!$D$4:$D$5000,总支出!$B$4:$B$5000,">="&DATE(VALUE(LEFT($A36,4)),VALUE(RIGHT($A36,2)),1),总支出!$B$4:$B$5000,"<"&DATE(VALUE(LEFT($A36,4)),VALUE(RIGHT($A36,2))+1,1),总支出!$H$4:$H$5000,"个人支出",总支出!$G$4:$G$5000,"弹性") -> 0 | F36: =SUMIFS(总支出!$D$4:$D$5000,总支出!$B$4:$B$5000,">="&DATE(VALUE(LEFT($A36,4)),VALUE(RIGHT($A36,2)),1),总支出!$B$4:$B$5000,"<"&DATE(VALUE(LEFT($A36,4)),VALUE(RIGHT($A36,2))+1,1),总支出!$H$4:$H$5000,"个人支出",总支出!$F$4:$F$5000,"固定") -> 0 | G36: =SUMIFS(总支出!$D$4:$D$5000,总支出!$B$4:$B$5000,">="&DATE(VALUE(LEFT($A36,4)),VALUE(RIGHT($A36,2)),1),总支出!$B$4:$B$5000,"<"&DATE(VALUE(LEFT($A36,4)),VALUE(RIGHT($A36,2))+1,1),总支出!$H$4:$H$5000,"个人支出",总支出!$F$4:$F$5000,"可变") -> 0 | H36: =SUMIFS(总支出!$D$4:$D$5000,总支出!$B$4:$B$5000,">="&DATE(VALUE(LEFT($A36,4)),VALUE(RIGHT($A36,2)),1),总支出!$B$4:$B$5000,"<"&DATE(VALUE(LEFT($A36,4)),VALUE(RIGHT($A36,2))+1,1),总支出!$H$4:$H$5000,"个人支出",总支出!$F$4:$F$5000,"一次性") -> 0 | I36: =SUMIFS(总支出!$D$4:$D$5000,总支出!$B$4:$B$5000,">="&DATE(VALUE(LEFT($A36,4)),VALUE(RIGHT($A36,2)),1),总支出!$B$4:$B$5000,"<"&DATE(VALUE(LEFT($A36,4)),VALUE(RIGHT($A36,2))+1,1),总支出!$H$4:$H$5000,"个人支出",总支出!$E$4:$E$5000,"住房") -> 0 | J36: =B36-C36 -> 0 | K36: =IF(OR(B36>0,C36>0),1,0) -> 0 | L36: =SUMIFS(总支出!$D$4:$D$5000,总支出!$B$4:$B$5000,">="&DATE(VALUE(LEFT($A36,4)),VALUE(RIGHT($A36,2)),1),总支出!$B$4:$B$5000,"<"&DATE(VALUE(LEFT($A36,4)),VALUE(RIGHT($A36,2))+1,1),总支出!$H$4:$H$5000,"房产支出") -> 0 | M36: =SUMIFS(总支出!$D$4:$D$5000,总支出!$B$4:$B$5000,">="&DATE(VALUE(LEFT($A36,4)),VALUE(RIGHT($A36,2)),1),总支出!$B$4:$B$5000,"<"&DATE(VALUE(LEFT($A36,4)),VALUE(RIGHT($A36,2))+1,1),总支出!$H$4:$H$5000,"投资转账") -> 0 | N36: =SUMIFS(总支出!$D$4:$D$5000,总支出!$B$4:$B$5000,">="&DATE(VALUE(LEFT($A36,4)),VALUE(RIGHT($A36,2)),1),总支出!$B$4:$B$5000,"<"&DATE(VALUE(LEFT($A36,4)),VALUE(RIGHT($A36,2))+1,1),总支出!$H$4:$H$5000,"内部转账") -> 0 | O36: =SUMIFS(税费计算明细!$S$4:$S$5000,税费计算明细!$C$4:$C$5000,$A36) -> 0
A37: 2026-10 | B37: =SUMIFS(总收入!$D$4:$D$5000,总收入!$B$4:$B$5000,">="&DATE(VALUE(LEFT($A37,4)),VALUE(RIGHT($A37,2)),1),总收入!$B$4:$B$5000,"<"&DATE(VALUE(LEFT($A37,4)),VALUE(RIGHT($A37,2))+1,1)) -> 0 | C37: =SUMIFS(总支出!$D$4:$D$5000,总支出!$B$4:$B$5000,">="&DATE(VALUE(LEFT($A37,4)),VALUE(RIGHT($A37,2)),1),总支出!$B$4:$B$5000,"<"&DATE(VALUE(LEFT($A37,4)),VALUE(RIGHT($A37,2))+1,1),总支出!$H$4:$H$5000,"个人支出") -> 0 | D37: =SUMIFS(总支出!$D$4:$D$5000,总支出!$B$4:$B$5000,">="&DATE(VALUE(LEFT($A37,4)),VALUE(RIGHT($A37,2)),1),总支出!$B$4:$B$5000,"<"&DATE(VALUE(LEFT($A37,4)),VALUE(RIGHT($A37,2))+1,1),总支出!$H$4:$H$5000,"个人支出",总支出!$G$4:$G$5000,"必要") -> 0 | E37: =SUMIFS(总支出!$D$4:$D$5000,总支出!$B$4:$B$5000,">="&DATE(VALUE(LEFT($A37,4)),VALUE(RIGHT($A37,2)),1),总支出!$B$4:$B$5000,"<"&DATE(VALUE(LEFT($A37,4)),VALUE(RIGHT($A37,2))+1,1),总支出!$H$4:$H$5000,"个人支出",总支出!$G$4:$G$5000,"弹性") -> 0 | F37: =SUMIFS(总支出!$D$4:$D$5000,总支出!$B$4:$B$5000,">="&DATE(VALUE(LEFT($A37,4)),VALUE(RIGHT($A37,2)),1),总支出!$B$4:$B$5000,"<"&DATE(VALUE(LEFT($A37,4)),VALUE(RIGHT($A37,2))+1,1),总支出!$H$4:$H$5000,"个人支出",总支出!$F$4:$F$5000,"固定") -> 0 | G37: =SUMIFS(总支出!$D$4:$D$5000,总支出!$B$4:$B$5000,">="&DATE(VALUE(LEFT($A37,4)),VALUE(RIGHT($A37,2)),1),总支出!$B$4:$B$5000,"<"&DATE(VALUE(LEFT($A37,4)),VALUE(RIGHT($A37,2))+1,1),总支出!$H$4:$H$5000,"个人支出",总支出!$F$4:$F$5000,"可变") -> 0 | H37: =SUMIFS(总支出!$D$4:$D$5000,总支出!$B$4:$B$5000,">="&DATE(VALUE(LEFT($A37,4)),VALUE(RIGHT($A37,2)),1),总支出!$B$4:$B$5000,"<"&DATE(VALUE(LEFT($A37,4)),VALUE(RIGHT($A37,2))+1,1),总支出!$H$4:$H$5000,"个人支出",总支出!$F$4:$F$5000,"一次性") -> 0 | I37: =SUMIFS(总支出!$D$4:$D$5000,总支出!$B$4:$B$5000,">="&DATE(VALUE(LEFT($A37,4)),VALUE(RIGHT($A37,2)),1),总支出!$B$4:$B$5000,"<"&DATE(VALUE(LEFT($A37,4)),VALUE(RIGHT($A37,2))+1,1),总支出!$H$4:$H$5000,"个人支出",总支出!$E$4:$E$5000,"住房") -> 0 | J37: =B37-C37 -> 0 | K37: =IF(OR(B37>0,C37>0),1,0) -> 0 | L37: =SUMIFS(总支出!$D$4:$D$5000,总支出!$B$4:$B$5000,">="&DATE(VALUE(LEFT($A37,4)),VALUE(RIGHT($A37,2)),1),总支出!$B$4:$B$5000,"<"&DATE(VALUE(LEFT($A37,4)),VALUE(RIGHT($A37,2))+1,1),总支出!$H$4:$H$5000,"房产支出") -> 0 | M37: =SUMIFS(总支出!$D$4:$D$5000,总支出!$B$4:$B$5000,">="&DATE(VALUE(LEFT($A37,4)),VALUE(RIGHT($A37,2)),1),总支出!$B$4:$B$5000,"<"&DATE(VALUE(LEFT($A37,4)),VALUE(RIGHT($A37,2))+1,1),总支出!$H$4:$H$5000,"投资转账") -> 0 | N37: =SUMIFS(总支出!$D$4:$D$5000,总支出!$B$4:$B$5000,">="&DATE(VALUE(LEFT($A37,4)),VALUE(RIGHT($A37,2)),1),总支出!$B$4:$B$5000,"<"&DATE(VALUE(LEFT($A37,4)),VALUE(RIGHT($A37,2))+1,1),总支出!$H$4:$H$5000,"内部转账") -> 0 | O37: =SUMIFS(税费计算明细!$S$4:$S$5000,税费计算明细!$C$4:$C$5000,$A37) -> 0
A38: 2026-11 | B38: =SUMIFS(总收入!$D$4:$D$5000,总收入!$B$4:$B$5000,">="&DATE(VALUE(LEFT($A38,4)),VALUE(RIGHT($A38,2)),1),总收入!$B$4:$B$5000,"<"&DATE(VALUE(LEFT($A38,4)),VALUE(RIGHT($A38,2))+1,1)) -> 0 | C38: =SUMIFS(总支出!$D$4:$D$5000,总支出!$B$4:$B$5000,">="&DATE(VALUE(LEFT($A38,4)),VALUE(RIGHT($A38,2)),1),总支出!$B$4:$B$5000,"<"&DATE(VALUE(LEFT($A38,4)),VALUE(RIGHT($A38,2))+1,1),总支出!$H$4:$H$5000,"个人支出") -> 0 | D38: =SUMIFS(总支出!$D$4:$D$5000,总支出!$B$4:$B$5000,">="&DATE(VALUE(LEFT($A38,4)),VALUE(RIGHT($A38,2)),1),总支出!$B$4:$B$5000,"<"&DATE(VALUE(LEFT($A38,4)),VALUE(RIGHT($A38,2))+1,1),总支出!$H$4:$H$5000,"个人支出",总支出!$G$4:$G$5000,"必要") -> 0 | E38: =SUMIFS(总支出!$D$4:$D$5000,总支出!$B$4:$B$5000,">="&DATE(VALUE(LEFT($A38,4)),VALUE(RIGHT($A38,2)),1),总支出!$B$4:$B$5000,"<"&DATE(VALUE(LEFT($A38,4)),VALUE(RIGHT($A38,2))+1,1),总支出!$H$4:$H$5000,"个人支出",总支出!$G$4:$G$5000,"弹性") -> 0 | F38: =SUMIFS(总支出!$D$4:$D$5000,总支出!$B$4:$B$5000,">="&DATE(VALUE(LEFT($A38,4)),VALUE(RIGHT($A38,2)),1),总支出!$B$4:$B$5000,"<"&DATE(VALUE(LEFT($A38,4)),VALUE(RIGHT($A38,2))+1,1),总支出!$H$4:$H$5000,"个人支出",总支出!$F$4:$F$5000,"固定") -> 0 | G38: =SUMIFS(总支出!$D$4:$D$5000,总支出!$B$4:$B$5000,">="&DATE(VALUE(LEFT($A38,4)),VALUE(RIGHT($A38,2)),1),总支出!$B$4:$B$5000,"<"&DATE(VALUE(LEFT($A38,4)),VALUE(RIGHT($A38,2))+1,1),总支出!$H$4:$H$5000,"个人支出",总支出!$F$4:$F$5000,"可变") -> 0 | H38: =SUMIFS(总支出!$D$4:$D$5000,总支出!$B$4:$B$5000,">="&DATE(VALUE(LEFT($A38,4)),VALUE(RIGHT($A38,2)),1),总支出!$B$4:$B$5000,"<"&DATE(VALUE(LEFT($A38,4)),VALUE(RIGHT($A38,2))+1,1),总支出!$H$4:$H$5000,"个人支出",总支出!$F$4:$F$5000,"一次性") -> 0 | I38: =SUMIFS(总支出!$D$4:$D$5000,总支出!$B$4:$B$5000,">="&DATE(VALUE(LEFT($A38,4)),VALUE(RIGHT($A38,2)),1),总支出!$B$4:$B$5000,"<"&DATE(VALUE(LEFT($A38,4)),VALUE(RIGHT($A38,2))+1,1),总支出!$H$4:$H$5000,"个人支出",总支出!$E$4:$E$5000,"住房") -> 0 | J38: =B38-C38 -> 0 | K38: =IF(OR(B38>0,C38>0),1,0) -> 0 | L38: =SUMIFS(总支出!$D$4:$D$5000,总支出!$B$4:$B$5000,">="&DATE(VALUE(LEFT($A38,4)),VALUE(RIGHT($A38,2)),1),总支出!$B$4:$B$5000,"<"&DATE(VALUE(LEFT($A38,4)),VALUE(RIGHT($A38,2))+1,1),总支出!$H$4:$H$5000,"房产支出") -> 0 | M38: =SUMIFS(总支出!$D$4:$D$5000,总支出!$B$4:$B$5000,">="&DATE(VALUE(LEFT($A38,4)),VALUE(RIGHT($A38,2)),1),总支出!$B$4:$B$5000,"<"&DATE(VALUE(LEFT($A38,4)),VALUE(RIGHT($A38,2))+1,1),总支出!$H$4:$H$5000,"投资转账") -> 0 | N38: =SUMIFS(总支出!$D$4:$D$5000,总支出!$B$4:$B$5000,">="&DATE(VALUE(LEFT($A38,4)),VALUE(RIGHT($A38,2)),1),总支出!$B$4:$B$5000,"<"&DATE(VALUE(LEFT($A38,4)),VALUE(RIGHT($A38,2))+1,1),总支出!$H$4:$H$5000,"内部转账") -> 0 | O38: =SUMIFS(税费计算明细!$S$4:$S$5000,税费计算明细!$C$4:$C$5000,$A38) -> 0
A39: 2026-12 | B39: =SUMIFS(总收入!$D$4:$D$5000,总收入!$B$4:$B$5000,">="&DATE(VALUE(LEFT($A39,4)),VALUE(RIGHT($A39,2)),1),总收入!$B$4:$B$5000,"<"&DATE(VALUE(LEFT($A39,4)),VALUE(RIGHT($A39,2))+1,1)) -> 0 | C39: =SUMIFS(总支出!$D$4:$D$5000,总支出!$B$4:$B$5000,">="&DATE(VALUE(LEFT($A39,4)),VALUE(RIGHT($A39,2)),1),总支出!$B$4:$B$5000,"<"&DATE(VALUE(LEFT($A39,4)),VALUE(RIGHT($A39,2))+1,1),总支出!$H$4:$H$5000,"个人支出") -> 0 | D39: =SUMIFS(总支出!$D$4:$D$5000,总支出!$B$4:$B$5000,">="&DATE(VALUE(LEFT($A39,4)),VALUE(RIGHT($A39,2)),1),总支出!$B$4:$B$5000,"<"&DATE(VALUE(LEFT($A39,4)),VALUE(RIGHT($A39,2))+1,1),总支出!$H$4:$H$5000,"个人支出",总支出!$G$4:$G$5000,"必要") -> 0 | E39: =SUMIFS(总支出!$D$4:$D$5000,总支出!$B$4:$B$5000,">="&DATE(VALUE(LEFT($A39,4)),VALUE(RIGHT($A39,2)),1),总支出!$B$4:$B$5000,"<"&DATE(VALUE(LEFT($A39,4)),VALUE(RIGHT($A39,2))+1,1),总支出!$H$4:$H$5000,"个人支出",总支出!$G$4:$G$5000,"弹性") -> 0 | F39: =SUMIFS(总支出!$D$4:$D$5000,总支出!$B$4:$B$5000,">="&DATE(VALUE(LEFT($A39,4)),VALUE(RIGHT($A39,2)),1),总支出!$B$4:$B$5000,"<"&DATE(VALUE(LEFT($A39,4)),VALUE(RIGHT($A39,2))+1,1),总支出!$H$4:$H$5000,"个人支出",总支出!$F$4:$F$5000,"固定") -> 0 | G39: =SUMIFS(总支出!$D$4:$D$5000,总支出!$B$4:$B$5000,">="&DATE(VALUE(LEFT($A39,4)),VALUE(RIGHT($A39,2)),1),总支出!$B$4:$B$5000,"<"&DATE(VALUE(LEFT($A39,4)),VALUE(RIGHT($A39,2))+1,1),总支出!$H$4:$H$5000,"个人支出",总支出!$F$4:$F$5000,"可变") -> 0 | H39: =SUMIFS(总支出!$D$4:$D$5000,总支出!$B$4:$B$5000,">="&DATE(VALUE(LEFT($A39,4)),VALUE(RIGHT($A39,2)),1),总支出!$B$4:$B$5000,"<"&DATE(VALUE(LEFT($A39,4)),VALUE(RIGHT($A39,2))+1,1),总支出!$H$4:$H$5000,"个人支出",总支出!$F$4:$F$5000,"一次性") -> 0 | I39: =SUMIFS(总支出!$D$4:$D$5000,总支出!$B$4:$B$5000,">="&DATE(VALUE(LEFT($A39,4)),VALUE(RIGHT($A39,2)),1),总支出!$B$4:$B$5000,"<"&DATE(VALUE(LEFT($A39,4)),VALUE(RIGHT($A39,2))+1,1),总支出!$H$4:$H$5000,"个人支出",总支出!$E$4:$E$5000,"住房") -> 0 | J39: =B39-C39 -> 0 | K39: =IF(OR(B39>0,C39>0),1,0) -> 0 | L39: =SUMIFS(总支出!$D$4:$D$5000,总支出!$B$4:$B$5000,">="&DATE(VALUE(LEFT($A39,4)),VALUE(RIGHT($A39,2)),1),总支出!$B$4:$B$5000,"<"&DATE(VALUE(LEFT($A39,4)),VALUE(RIGHT($A39,2))+1,1),总支出!$H$4:$H$5000,"房产支出") -> 0 | M39: =SUMIFS(总支出!$D$4:$D$5000,总支出!$B$4:$B$5000,">="&DATE(VALUE(LEFT($A39,4)),VALUE(RIGHT($A39,2)),1),总支出!$B$4:$B$5000,"<"&DATE(VALUE(LEFT($A39,4)),VALUE(RIGHT($A39,2))+1,1),总支出!$H$4:$H$5000,"投资转账") -> 0 | N39: =SUMIFS(总支出!$D$4:$D$5000,总支出!$B$4:$B$5000,">="&DATE(VALUE(LEFT($A39,4)),VALUE(RIGHT($A39,2)),1),总支出!$B$4:$B$5000,"<"&DATE(VALUE(LEFT($A39,4)),VALUE(RIGHT($A39,2))+1,1),总支出!$H$4:$H$5000,"内部转账") -> 0 | O39: =SUMIFS(税费计算明细!$S$4:$S$5000,税费计算明细!$C$4:$C$5000,$A39) -> 0
A44: 主类别 | B44: 2026-01 | C44: 2026-02 | D44: 2026-03 | E44: 2026-04 | F44: 2026-05 | G44: 2026-06 | H44: 2026-07 | I44: 2026-08 | J44: 2026-09 | K44: 2026-10 | L44: 2026-11 | M44: 2026-12 | N44: 月均 | O44: 年化 | P44: 占个人月支出比例
A45: 住房 | B45: =SUMIFS(总支出!$D$4:$D$5000,总支出!$B$4:$B$5000,">="&DATE(VALUE(LEFT(B$44,4)),VALUE(RIGHT(B$44,2)),1),总支出!$B$4:$B$5000,"<"&DATE(VALUE(LEFT(B$44,4)),VALUE(RIGHT(B$44,2))+1,1),总支出!$H$4:$H$5000,"个人支出",总支出!$E$4:$E$5000,$A45) -> 3000 | C45: =SUMIFS(总支出!$D$4:$D$5000,总支出!$B$4:$B$5000,">="&DATE(VALUE(LEFT(C$44,4)),VALUE(RIGHT(C$44,2)),1),总支出!$B$4:$B$5000,"<"&DATE(VALUE(LEFT(C$44,4)),VALUE(RIGHT(C$44,2))+1,1),总支出!$H$4:$H$5000,"个人支出",总支出!$E$4:$E$5000,$A45) -> 3000 | D45: =SUMIFS(总支出!$D$4:$D$5000,总支出!$B$4:$B$5000,">="&DATE(VALUE(LEFT(D$44,4)),VALUE(RIGHT(D$44,2)),1),总支出!$B$4:$B$5000,"<"&DATE(VALUE(LEFT(D$44,4)),VALUE(RIGHT(D$44,2))+1,1),总支出!$H$4:$H$5000,"个人支出",总支出!$E$4:$E$5000,$A45) -> 0 | E45: =SUMIFS(总支出!$D$4:$D$5000,总支出!$B$4:$B$5000,">="&DATE(VALUE(LEFT(E$44,4)),VALUE(RIGHT(E$44,2)),1),总支出!$B$4:$B$5000,"<"&DATE(VALUE(LEFT(E$44,4)),VALUE(RIGHT(E$44,2))+1,1),总支出!$H$4:$H$5000,"个人支出",总支出!$E$4:$E$5000,$A45) -> 0 | F45: =SUMIFS(总支出!$D$4:$D$5000,总支出!$B$4:$B$5000,">="&DATE(VALUE(LEFT(F$44,4)),VALUE(RIGHT(F$44,2)),1),总支出!$B$4:$B$5000,"<"&DATE(VALUE(LEFT(F$44,4)),VALUE(RIGHT(F$44,2))+1,1),总支出!$H$4:$H$5000,"个人支出",总支出!$E$4:$E$5000,$A45) -> 0 | G45: =SUMIFS(总支出!$D$4:$D$5000,总支出!$B$4:$B$5000,">="&DATE(VALUE(LEFT(G$44,4)),VALUE(RIGHT(G$44,2)),1),总支出!$B$4:$B$5000,"<"&DATE(VALUE(LEFT(G$44,4)),VALUE(RIGHT(G$44,2))+1,1),总支出!$H$4:$H$5000,"个人支出",总支出!$E$4:$E$5000,$A45) -> 0 | H45: =SUMIFS(总支出!$D$4:$D$5000,总支出!$B$4:$B$5000,">="&DATE(VALUE(LEFT(H$44,4)),VALUE(RIGHT(H$44,2)),1),总支出!$B$4:$B$5000,"<"&DATE(VALUE(LEFT(H$44,4)),VALUE(RIGHT(H$44,2))+1,1),总支出!$H$4:$H$5000,"个人支出",总支出!$E$4:$E$5000,$A45) -> 0 | I45: =SUMIFS(总支出!$D$4:$D$5000,总支出!$B$4:$B$5000,">="&DATE(VALUE(LEFT(I$44,4)),VALUE(RIGHT(I$44,2)),1),总支出!$B$4:$B$5000,"<"&DATE(VALUE(LEFT(I$44,4)),VALUE(RIGHT(I$44,2))+1,1),总支出!$H$4:$H$5000,"个人支出",总支出!$E$4:$E$5000,$A45) -> 0 | ... M45: =SUMIFS(总支出!$D$4:$D$5000,总支出!$B$4:$B$5000,">="&DATE(VALUE(LEFT(M$44,4)),VALUE(RIGHT(M$44,2)),1),总支出!$B$4:$B$5000,"<"&DATE(VALUE(LEFT(M$44,4)),VALUE(RIGHT(M$44,2))+1,1),总支出!$H$4:$H$5000,"个人支出",总支出!$E$4:$E$5000,$A45) -> 0 | N45: =IF($B$4=0,0,SUM(B45:M45)/$B$4) -> 3000 | O45: =N45*12 -> 36000 | P45: =IFERROR(N45/$B$7,0) -> 0.58252427
A46: 餐饮 | B46: =SUMIFS(总支出!$D$4:$D$5000,总支出!$B$4:$B$5000,">="&DATE(VALUE(LEFT(B$44,4)),VALUE(RIGHT(B$44,2)),1),总支出!$B$4:$B$5000,"<"&DATE(VALUE(LEFT(B$44,4)),VALUE(RIGHT(B$44,2))+1,1),总支出!$H$4:$H$5000,"个人支出",总支出!$E$4:$E$5000,$A46) -> 770 | C46: =SUMIFS(总支出!$D$4:$D$5000,总支出!$B$4:$B$5000,">="&DATE(VALUE(LEFT(C$44,4)),VALUE(RIGHT(C$44,2)),1),总支出!$B$4:$B$5000,"<"&DATE(VALUE(LEFT(C$44,4)),VALUE(RIGHT(C$44,2))+1,1),总支出!$H$4:$H$5000,"个人支出",总支出!$E$4:$E$5000,$A46) -> 870 | D46: =SUMIFS(总支出!$D$4:$D$5000,总支出!$B$4:$B$5000,">="&DATE(VALUE(LEFT(D$44,4)),VALUE(RIGHT(D$44,2)),1),总支出!$B$4:$B$5000,"<"&DATE(VALUE(LEFT(D$44,4)),VALUE(RIGHT(D$44,2))+1,1),总支出!$H$4:$H$5000,"个人支出",总支出!$E$4:$E$5000,$A46) -> 0 | E46: =SUMIFS(总支出!$D$4:$D$5000,总支出!$B$4:$B$5000,">="&DATE(VALUE(LEFT(E$44,4)),VALUE(RIGHT(E$44,2)),1),总支出!$B$4:$B$5000,"<"&DATE(VALUE(LEFT(E$44,4)),VALUE(RIGHT(E$44,2))+1,1),总支出!$H$4:$H$5000,"个人支出",总支出!$E$4:$E$5000,$A46) -> 0 | F46: =SUMIFS(总支出!$D$4:$D$5000,总支出!$B$4:$B$5000,">="&DATE(VALUE(LEFT(F$44,4)),VALUE(RIGHT(F$44,2)),1),总支出!$B$4:$B$5000,"<"&DATE(VALUE(LEFT(F$44,4)),VALUE(RIGHT(F$44,2))+1,1),总支出!$H$4:$H$5000,"个人支出",总支出!$E$4:$E$5000,$A46) -> 0 | G46: =SUMIFS(总支出!$D$4:$D$5000,总支出!$B$4:$B$5000,">="&DATE(VALUE(LEFT(G$44,4)),VALUE(RIGHT(G$44,2)),1),总支出!$B$4:$B$5000,"<"&DATE(VALUE(LEFT(G$44,4)),VALUE(RIGHT(G$44,2))+1,1),总支出!$H$4:$H$5000,"个人支出",总支出!$E$4:$E$5000,$A46) -> 0 | H46: =SUMIFS(总支出!$D$4:$D$5000,总支出!$B$4:$B$5000,">="&DATE(VALUE(LEFT(H$44,4)),VALUE(RIGHT(H$44,2)),1),总支出!$B$4:$B$5000,"<"&DATE(VALUE(LEFT(H$44,4)),VALUE(RIGHT(H$44,2))+1,1),总支出!$H$4:$H$5000,"个人支出",总支出!$E$4:$E$5000,$A46) -> 0 | I46: =SUMIFS(总支出!$D$4:$D$5000,总支出!$B$4:$B$5000,">="&DATE(VALUE(LEFT(I$44,4)),VALUE(RIGHT(I$44,2)),1),总支出!$B$4:$B$5000,"<"&DATE(VALUE(LEFT(I$44,4)),VALUE(RIGHT(I$44,2))+1,1),总支出!$H$4:$H$5000,"个人支出",总支出!$E$4:$E$5000,$A46) -> 0 | ... M46: =SUMIFS(总支出!$D$4:$D$5000,总支出!$B$4:$B$5000,">="&DATE(VALUE(LEFT(M$44,4)),VALUE(RIGHT(M$44,2)),1),总支出!$B$4:$B$5000,"<"&DATE(VALUE(LEFT(M$44,4)),VALUE(RIGHT(M$44,2))+1,1),总支出!$H$4:$H$5000,"个人支出",总支出!$E$4:$E$5000,$A46) -> 0 | N46: =IF($B$4=0,0,SUM(B46:M46)/$B$4) -> 820 | O46: =N46*12 -> 9840 | P46: =IFERROR(N46/$B$7,0) -> 0.1592233
A47: 交通 | B47: =SUMIFS(总支出!$D$4:$D$5000,总支出!$B$4:$B$5000,">="&DATE(VALUE(LEFT(B$44,4)),VALUE(RIGHT(B$44,2)),1),总支出!$B$4:$B$5000,"<"&DATE(VALUE(LEFT(B$44,4)),VALUE(RIGHT(B$44,2))+1,1),总支出!$H$4:$H$5000,"个人支出",总支出!$E$4:$E$5000,$A47) -> 220 | C47: =SUMIFS(总支出!$D$4:$D$5000,总支出!$B$4:$B$5000,">="&DATE(VALUE(LEFT(C$44,4)),VALUE(RIGHT(C$44,2)),1),总支出!$B$4:$B$5000,"<"&DATE(VALUE(LEFT(C$44,4)),VALUE(RIGHT(C$44,2))+1,1),总支出!$H$4:$H$5000,"个人支出",总支出!$E$4:$E$5000,$A47) -> 260 | D47: =SUMIFS(总支出!$D$4:$D$5000,总支出!$B$4:$B$5000,">="&DATE(VALUE(LEFT(D$44,4)),VALUE(RIGHT(D$44,2)),1),总支出!$B$4:$B$5000,"<"&DATE(VALUE(LEFT(D$44,4)),VALUE(RIGHT(D$44,2))+1,1),总支出!$H$4:$H$5000,"个人支出",总支出!$E$4:$E$5000,$A47) -> 0 | E47: =SUMIFS(总支出!$D$4:$D$5000,总支出!$B$4:$B$5000,">="&DATE(VALUE(LEFT(E$44,4)),VALUE(RIGHT(E$44,2)),1),总支出!$B$4:$B$5000,"<"&DATE(VALUE(LEFT(E$44,4)),VALUE(RIGHT(E$44,2))+1,1),总支出!$H$4:$H$5000,"个人支出",总支出!$E$4:$E$5000,$A47) -> 0 | F47: =SUMIFS(总支出!$D$4:$D$5000,总支出!$B$4:$B$5000,">="&DATE(VALUE(LEFT(F$44,4)),VALUE(RIGHT(F$44,2)),1),总支出!$B$4:$B$5000,"<"&DATE(VALUE(LEFT(F$44,4)),VALUE(RIGHT(F$44,2))+1,1),总支出!$H$4:$H$5000,"个人支出",总支出!$E$4:$E$5000,$A47) -> 0 | G47: =SUMIFS(总支出!$D$4:$D$5000,总支出!$B$4:$B$5000,">="&DATE(VALUE(LEFT(G$44,4)),VALUE(RIGHT(G$44,2)),1),总支出!$B$4:$B$5000,"<"&DATE(VALUE(LEFT(G$44,4)),VALUE(RIGHT(G$44,2))+1,1),总支出!$H$4:$H$5000,"个人支出",总支出!$E$4:$E$5000,$A47) -> 0 | H47: =SUMIFS(总支出!$D$4:$D$5000,总支出!$B$4:$B$5000,">="&DATE(VALUE(LEFT(H$44,4)),VALUE(RIGHT(H$44,2)),1),总支出!$B$4:$B$5000,"<"&DATE(VALUE(LEFT(H$44,4)),VALUE(RIGHT(H$44,2))+1,1),总支出!$H$4:$H$5000,"个人支出",总支出!$E$4:$E$5000,$A47) -> 0 | I47: =SUMIFS(总支出!$D$4:$D$5000,总支出!$B$4:$B$5000,">="&DATE(VALUE(LEFT(I$44,4)),VALUE(RIGHT(I$44,2)),1),总支出!$B$4:$B$5000,"<"&DATE(VALUE(LEFT(I$44,4)),VALUE(RIGHT(I$44,2))+1,1),总支出!$H$4:$H$5000,"个人支出",总支出!$E$4:$E$5000,$A47) -> 0 | ... M47: =SUMIFS(总支出!$D$4:$D$5000,总支出!$B$4:$B$5000,">="&DATE(VALUE(LEFT(M$44,4)),VALUE(RIGHT(M$44,2)),1),总支出!$B$4:$B$5000,"<"&DATE(VALUE(LEFT(M$44,4)),VALUE(RIGHT(M$44,2))+1,1),总支出!$H$4:$H$5000,"个人支出",总支出!$E$4:$E$5000,$A47) -> 0 | N47: =IF($B$4=0,0,SUM(B47:M47)/$B$4) -> 240 | O47: =N47*12 -> 2880 | P47: =IFERROR(N47/$B$7,0) -> 0.046601942
A48: 通讯 | B48: =SUMIFS(总支出!$D$4:$D$5000,总支出!$B$4:$B$5000,">="&DATE(VALUE(LEFT(B$44,4)),VALUE(RIGHT(B$44,2)),1),总支出!$B$4:$B$5000,"<"&DATE(VALUE(LEFT(B$44,4)),VALUE(RIGHT(B$44,2))+1,1),总支出!$H$4:$H$5000,"个人支出",总支出!$E$4:$E$5000,$A48) -> 60 | C48: =SUMIFS(总支出!$D$4:$D$5000,总支出!$B$4:$B$5000,">="&DATE(VALUE(LEFT(C$44,4)),VALUE(RIGHT(C$44,2)),1),总支出!$B$4:$B$5000,"<"&DATE(VALUE(LEFT(C$44,4)),VALUE(RIGHT(C$44,2))+1,1),总支出!$H$4:$H$5000,"个人支出",总支出!$E$4:$E$5000,$A48) -> 60 | D48: =SUMIFS(总支出!$D$4:$D$5000,总支出!$B$4:$B$5000,">="&DATE(VALUE(LEFT(D$44,4)),VALUE(RIGHT(D$44,2)),1),总支出!$B$4:$B$5000,"<"&DATE(VALUE(LEFT(D$44,4)),VALUE(RIGHT(D$44,2))+1,1),总支出!$H$4:$H$5000,"个人支出",总支出!$E$4:$E$5000,$A48) -> 0 | E48: =SUMIFS(总支出!$D$4:$D$5000,总支出!$B$4:$B$5000,">="&DATE(VALUE(LEFT(E$44,4)),VALUE(RIGHT(E$44,2)),1),总支出!$B$4:$B$5000,"<"&DATE(VALUE(LEFT(E$44,4)),VALUE(RIGHT(E$44,2))+1,1),总支出!$H$4:$H$5000,"个人支出",总支出!$E$4:$E$5000,$A48) -> 0 | F48: =SUMIFS(总支出!$D$4:$D$5000,总支出!$B$4:$B$5000,">="&DATE(VALUE(LEFT(F$44,4)),VALUE(RIGHT(F$44,2)),1),总支出!$B$4:$B$5000,"<"&DATE(VALUE(LEFT(F$44,4)),VALUE(RIGHT(F$44,2))+1,1),总支出!$H$4:$H$5000,"个人支出",总支出!$E$4:$E$5000,$A48) -> 0 | G48: =SUMIFS(总支出!$D$4:$D$5000,总支出!$B$4:$B$5000,">="&DATE(VALUE(LEFT(G$44,4)),VALUE(RIGHT(G$44,2)),1),总支出!$B$4:$B$5000,"<"&DATE(VALUE(LEFT(G$44,4)),VALUE(RIGHT(G$44,2))+1,1),总支出!$H$4:$H$5000,"个人支出",总支出!$E$4:$E$5000,$A48) -> 0 | H48: =SUMIFS(总支出!$D$4:$D$5000,总支出!$B$4:$B$5000,">="&DATE(VALUE(LEFT(H$44,4)),VALUE(RIGHT(H$44,2)),1),总支出!$B$4:$B$5000,"<"&DATE(VALUE(LEFT(H$44,4)),VALUE(RIGHT(H$44,2))+1,1),总支出!$H$4:$H$5000,"个人支出",总支出!$E$4:$E$5000,$A48) -> 0 | I48: =SUMIFS(总支出!$D$4:$D$5000,总支出!$B$4:$B$5000,">="&DATE(VALUE(LEFT(I$44,4)),VALUE(RIGHT(I$44,2)),1),总支出!$B$4:$B$5000,"<"&DATE(VALUE(LEFT(I$44,4)),VALUE(RIGHT(I$44,2))+1,1),总支出!$H$4:$H$5000,"个人支出",总支出!$E$4:$E$5000,$A48) -> 0 | ... M48: =SUMIFS(总支出!$D$4:$D$5000,总支出!$B$4:$B$5000,">="&DATE(VALUE(LEFT(M$44,4)),VALUE(RIGHT(M$44,2)),1),总支出!$B$4:$B$5000,"<"&DATE(VALUE(LEFT(M$44,4)),VALUE(RIGHT(M$44,2))+1,1),总支出!$H$4:$H$5000,"个人支出",总支出!$E$4:$E$5000,$A48) -> 0 | N48: =IF($B$4=0,0,SUM(B48:M48)/$B$4) -> 60 | O48: =N48*12 -> 720 | P48: =IFERROR(N48/$B$7,0) -> 0.011650485
A49: 订阅 | B49: =SUMIFS(总支出!$D$4:$D$5000,总支出!$B$4:$B$5000,">="&DATE(VALUE(LEFT(B$44,4)),VALUE(RIGHT(B$44,2)),1),总支出!$B$4:$B$5000,"<"&DATE(VALUE(LEFT(B$44,4)),VALUE(RIGHT(B$44,2))+1,1),总支出!$H$4:$H$5000,"个人支出",总支出!$E$4:$E$5000,$A49) -> 30 | C49: =SUMIFS(总支出!$D$4:$D$5000,总支出!$B$4:$B$5000,">="&DATE(VALUE(LEFT(C$44,4)),VALUE(RIGHT(C$44,2)),1),总支出!$B$4:$B$5000,"<"&DATE(VALUE(LEFT(C$44,4)),VALUE(RIGHT(C$44,2))+1,1),总支出!$H$4:$H$5000,"个人支出",总支出!$E$4:$E$5000,$A49) -> 45 | D49: =SUMIFS(总支出!$D$4:$D$5000,总支出!$B$4:$B$5000,">="&DATE(VALUE(LEFT(D$44,4)),VALUE(RIGHT(D$44,2)),1),总支出!$B$4:$B$5000,"<"&DATE(VALUE(LEFT(D$44,4)),VALUE(RIGHT(D$44,2))+1,1),总支出!$H$4:$H$5000,"个人支出",总支出!$E$4:$E$5000,$A49) -> 0 | E49: =SUMIFS(总支出!$D$4:$D$5000,总支出!$B$4:$B$5000,">="&DATE(VALUE(LEFT(E$44,4)),VALUE(RIGHT(E$44,2)),1),总支出!$B$4:$B$5000,"<"&DATE(VALUE(LEFT(E$44,4)),VALUE(RIGHT(E$44,2))+1,1),总支出!$H$4:$H$5000,"个人支出",总支出!$E$4:$E$5000,$A49) -> 0 | F49: =SUMIFS(总支出!$D$4:$D$5000,总支出!$B$4:$B$5000,">="&DATE(VALUE(LEFT(F$44,4)),VALUE(RIGHT(F$44,2)),1),总支出!$B$4:$B$5000,"<"&DATE(VALUE(LEFT(F$44,4)),VALUE(RIGHT(F$44,2))+1,1),总支出!$H$4:$H$5000,"个人支出",总支出!$E$4:$E$5000,$A49) -> 0 | G49: =SUMIFS(总支出!$D$4:$D$5000,总支出!$B$4:$B$5000,">="&DATE(VALUE(LEFT(G$44,4)),VALUE(RIGHT(G$44,2)),1),总支出!$B$4:$B$5000,"<"&DATE(VALUE(LEFT(G$44,4)),VALUE(RIGHT(G$44,2))+1,1),总支出!$H$4:$H$5000,"个人支出",总支出!$E$4:$E$5000,$A49) -> 0 | H49: =SUMIFS(总支出!$D$4:$D$5000,总支出!$B$4:$B$5000,">="&DATE(VALUE(LEFT(H$44,4)),VALUE(RIGHT(H$44,2)),1),总支出!$B$4:$B$5000,"<"&DATE(VALUE(LEFT(H$44,4)),VALUE(RIGHT(H$44,2))+1,1),总支出!$H$4:$H$5000,"个人支出",总支出!$E$4:$E$5000,$A49) -> 0 | I49: =SUMIFS(总支出!$D$4:$D$5000,总支出!$B$4:$B$5000,">="&DATE(VALUE(LEFT(I$44,4)),VALUE(RIGHT(I$44,2)),1),总支出!$B$4:$B$5000,"<"&DATE(VALUE(LEFT(I$44,4)),VALUE(RIGHT(I$44,2))+1,1),总支出!$H$4:$H$5000,"个人支出",总支出!$E$4:$E$5000,$A49) -> 0 | ... M49: =SUMIFS(总支出!$D$4:$D$5000,总支出!$B$4:$B$5000,">="&DATE(VALUE(LEFT(M$44,4)),VALUE(RIGHT(M$44,2)),1),总支出!$B$4:$B$5000,"<"&DATE(VALUE(LEFT(M$44,4)),VALUE(RIGHT(M$44,2))+1,1),总支出!$H$4:$H$5000,"个人支出",总支出!$E$4:$E$5000,$A49) -> 0 | N49: =IF($B$4=0,0,SUM(B49:M49)/$B$4) -> 37.5 | O49: =N49*12 -> 450 | P49: =IFERROR(N49/$B$7,0) -> 0.0072815534
A50: 购物 | B50: =SUMIFS(总支出!$D$4:$D$5000,总支出!$B$4:$B$5000,">="&DATE(VALUE(LEFT(B$44,4)),VALUE(RIGHT(B$44,2)),1),总支出!$B$4:$B$5000,"<"&DATE(VALUE(LEFT(B$44,4)),VALUE(RIGHT(B$44,2))+1,1),总支出!$H$4:$H$5000,"个人支出",总支出!$E$4:$E$5000,$A50) -> 250 | C50: =SUMIFS(总支出!$D$4:$D$5000,总支出!$B$4:$B$5000,">="&DATE(VALUE(LEFT(C$44,4)),VALUE(RIGHT(C$44,2)),1),总支出!$B$4:$B$5000,"<"&DATE(VALUE(LEFT(C$44,4)),VALUE(RIGHT(C$44,2))+1,1),总支出!$H$4:$H$5000,"个人支出",总支出!$E$4:$E$5000,$A50) -> 300 | D50: =SUMIFS(总支出!$D$4:$D$5000,总支出!$B$4:$B$5000,">="&DATE(VALUE(LEFT(D$44,4)),VALUE(RIGHT(D$44,2)),1),总支出!$B$4:$B$5000,"<"&DATE(VALUE(LEFT(D$44,4)),VALUE(RIGHT(D$44,2))+1,1),总支出!$H$4:$H$5000,"个人支出",总支出!$E$4:$E$5000,$A50) -> 0 | E50: =SUMIFS(总支出!$D$4:$D$5000,总支出!$B$4:$B$5000,">="&DATE(VALUE(LEFT(E$44,4)),VALUE(RIGHT(E$44,2)),1),总支出!$B$4:$B$5000,"<"&DATE(VALUE(LEFT(E$44,4)),VALUE(RIGHT(E$44,2))+1,1),总支出!$H$4:$H$5000,"个人支出",总支出!$E$4:$E$5000,$A50) -> 0 | F50: =SUMIFS(总支出!$D$4:$D$5000,总支出!$B$4:$B$5000,">="&DATE(VALUE(LEFT(F$44,4)),VALUE(RIGHT(F$44,2)),1),总支出!$B$4:$B$5000,"<"&DATE(VALUE(LEFT(F$44,4)),VALUE(RIGHT(F$44,2))+1,1),总支出!$H$4:$H$5000,"个人支出",总支出!$E$4:$E$5000,$A50) -> 0 | G50: =SUMIFS(总支出!$D$4:$D$5000,总支出!$B$4:$B$5000,">="&DATE(VALUE(LEFT(G$44,4)),VALUE(RIGHT(G$44,2)),1),总支出!$B$4:$B$5000,"<"&DATE(VALUE(LEFT(G$44,4)),VALUE(RIGHT(G$44,2))+1,1),总支出!$H$4:$H$5000,"个人支出",总支出!$E$4:$E$5000,$A50) -> 0 | H50: =SUMIFS(总支出!$D$4:$D$5000,总支出!$B$4:$B$5000,">="&DATE(VALUE(LEFT(H$44,4)),VALUE(RIGHT(H$44,2)),1),总支出!$B$4:$B$5000,"<"&DATE(VALUE(LEFT(H$44,4)),VALUE(RIGHT(H$44,2))+1,1),总支出!$H$4:$H$5000,"个人支出",总支出!$E$4:$E$5000,$A50) -> 0 | I50: =SUMIFS(总支出!$D$4:$D$5000,总支出!$B$4:$B$5000,">="&DATE(VALUE(LEFT(I$44,4)),VALUE(RIGHT(I$44,2)),1),总支出!$B$4:$B$5000,"<"&DATE(VALUE(LEFT(I$44,4)),VALUE(RIGHT(I$44,2))+1,1),总支出!$H$4:$H$5000,"个人支出",总支出!$E$4:$E$5000,$A50) -> 0 | ... M50: =SUMIFS(总支出!$D$4:$D$5000,总支出!$B$4:$B$5000,">="&DATE(VALUE(LEFT(M$44,4)),VALUE(RIGHT(M$44,2)),1),总支出!$B$4:$B$5000,"<"&DATE(VALUE(LEFT(M$44,4)),VALUE(RIGHT(M$44,2))+1,1),总支出!$H$4:$H$5000,"个人支出",总支出!$E$4:$E$5000,$A50) -> 0 | N50: =IF($B$4=0,0,SUM(B50:M50)/$B$4) -> 275 | O50: =N50*12 -> 3300 | P50: =IFERROR(N50/$B$7,0) -> 0.053398058
A51: 医疗 | B51: =SUMIFS(总支出!$D$4:$D$5000,总支出!$B$4:$B$5000,">="&DATE(VALUE(LEFT(B$44,4)),VALUE(RIGHT(B$44,2)),1),总支出!$B$4:$B$5000,"<"&DATE(VALUE(LEFT(B$44,4)),VALUE(RIGHT(B$44,2))+1,1),总支出!$H$4:$H$5000,"个人支出",总支出!$E$4:$E$5000,$A51) -> 80 | C51: =SUMIFS(总支出!$D$4:$D$5000,总支出!$B$4:$B$5000,">="&DATE(VALUE(LEFT(C$44,4)),VALUE(RIGHT(C$44,2)),1),总支出!$B$4:$B$5000,"<"&DATE(VALUE(LEFT(C$44,4)),VALUE(RIGHT(C$44,2))+1,1),总支出!$H$4:$H$5000,"个人支出",总支出!$E$4:$E$5000,$A51) -> 100 | D51: =SUMIFS(总支出!$D$4:$D$5000,总支出!$B$4:$B$5000,">="&DATE(VALUE(LEFT(D$44,4)),VALUE(RIGHT(D$44,2)),1),总支出!$B$4:$B$5000,"<"&DATE(VALUE(LEFT(D$44,4)),VALUE(RIGHT(D$44,2))+1,1),总支出!$H$4:$H$5000,"个人支出",总支出!$E$4:$E$5000,$A51) -> 0 | E51: =SUMIFS(总支出!$D$4:$D$5000,总支出!$B$4:$B$5000,">="&DATE(VALUE(LEFT(E$44,4)),VALUE(RIGHT(E$44,2)),1),总支出!$B$4:$B$5000,"<"&DATE(VALUE(LEFT(E$44,4)),VALUE(RIGHT(E$44,2))+1,1),总支出!$H$4:$H$5000,"个人支出",总支出!$E$4:$E$5000,$A51) -> 0 | F51: =SUMIFS(总支出!$D$4:$D$5000,总支出!$B$4:$B$5000,">="&DATE(VALUE(LEFT(F$44,4)),VALUE(RIGHT(F$44,2)),1),总支出!$B$4:$B$5000,"<"&DATE(VALUE(LEFT(F$44,4)),VALUE(RIGHT(F$44,2))+1,1),总支出!$H$4:$H$5000,"个人支出",总支出!$E$4:$E$5000,$A51) -> 0 | G51: =SUMIFS(总支出!$D$4:$D$5000,总支出!$B$4:$B$5000,">="&DATE(VALUE(LEFT(G$44,4)),VALUE(RIGHT(G$44,2)),1),总支出!$B$4:$B$5000,"<"&DATE(VALUE(LEFT(G$44,4)),VALUE(RIGHT(G$44,2))+1,1),总支出!$H$4:$H$5000,"个人支出",总支出!$E$4:$E$5000,$A51) -> 0 | H51: =SUMIFS(总支出!$D$4:$D$5000,总支出!$B$4:$B$5000,">="&DATE(VALUE(LEFT(H$44,4)),VALUE(RIGHT(H$44,2)),1),总支出!$B$4:$B$5000,"<"&DATE(VALUE(LEFT(H$44,4)),VALUE(RIGHT(H$44,2))+1,1),总支出!$H$4:$H$5000,"个人支出",总支出!$E$4:$E$5000,$A51) -> 0 | I51: =SUMIFS(总支出!$D$4:$D$5000,总支出!$B$4:$B$5000,">="&DATE(VALUE(LEFT(I$44,4)),VALUE(RIGHT(I$44,2)),1),总支出!$B$4:$B$5000,"<"&DATE(VALUE(LEFT(I$44,4)),VALUE(RIGHT(I$44,2))+1,1),总支出!$H$4:$H$5000,"个人支出",总支出!$E$4:$E$5000,$A51) -> 0 | ... M51: =SUMIFS(总支出!$D$4:$D$5000,总支出!$B$4:$B$5000,">="&DATE(VALUE(LEFT(M$44,4)),VALUE(RIGHT(M$44,2)),1),总支出!$B$4:$B$5000,"<"&DATE(VALUE(LEFT(M$44,4)),VALUE(RIGHT(M$44,2))+1,1),总支出!$H$4:$H$5000,"个人支出",总支出!$E$4:$E$5000,$A51) -> 0 | N51: =IF($B$4=0,0,SUM(B51:M51)/$B$4) -> 90 | O51: =N51*12 -> 1080 | P51: =IFERROR(N51/$B$7,0) -> 0.017475728
A52: 运动 | B52: =SUMIFS(总支出!$D$4:$D$5000,总支出!$B$4:$B$5000,">="&DATE(VALUE(LEFT(B$44,4)),VALUE(RIGHT(B$44,2)),1),总支出!$B$4:$B$5000,"<"&DATE(VALUE(LEFT(B$44,4)),VALUE(RIGHT(B$44,2))+1,1),总支出!$H$4:$H$5000,"个人支出",总支出!$E$4:$E$5000,$A52) -> 70 | C52: =SUMIFS(总支出!$D$4:$D$5000,总支出!$B$4:$B$5000,">="&DATE(VALUE(LEFT(C$44,4)),VALUE(RIGHT(C$44,2)),1),总支出!$B$4:$B$5000,"<"&DATE(VALUE(LEFT(C$44,4)),VALUE(RIGHT(C$44,2))+1,1),总支出!$H$4:$H$5000,"个人支出",总支出!$E$4:$E$5000,$A52) -> 70 | D52: =SUMIFS(总支出!$D$4:$D$5000,总支出!$B$4:$B$5000,">="&DATE(VALUE(LEFT(D$44,4)),VALUE(RIGHT(D$44,2)),1),总支出!$B$4:$B$5000,"<"&DATE(VALUE(LEFT(D$44,4)),VALUE(RIGHT(D$44,2))+1,1),总支出!$H$4:$H$5000,"个人支出",总支出!$E$4:$E$5000,$A52) -> 0 | E52: =SUMIFS(总支出!$D$4:$D$5000,总支出!$B$4:$B$5000,">="&DATE(VALUE(LEFT(E$44,4)),VALUE(RIGHT(E$44,2)),1),总支出!$B$4:$B$5000,"<"&DATE(VALUE(LEFT(E$44,4)),VALUE(RIGHT(E$44,2))+1,1),总支出!$H$4:$H$5000,"个人支出",总支出!$E$4:$E$5000,$A52) -> 0 | F52: =SUMIFS(总支出!$D$4:$D$5000,总支出!$B$4:$B$5000,">="&DATE(VALUE(LEFT(F$44,4)),VALUE(RIGHT(F$44,2)),1),总支出!$B$4:$B$5000,"<"&DATE(VALUE(LEFT(F$44,4)),VALUE(RIGHT(F$44,2))+1,1),总支出!$H$4:$H$5000,"个人支出",总支出!$E$4:$E$5000,$A52) -> 0 | G52: =SUMIFS(总支出!$D$4:$D$5000,总支出!$B$4:$B$5000,">="&DATE(VALUE(LEFT(G$44,4)),VALUE(RIGHT(G$44,2)),1),总支出!$B$4:$B$5000,"<"&DATE(VALUE(LEFT(G$44,4)),VALUE(RIGHT(G$44,2))+1,1),总支出!$H$4:$H$5000,"个人支出",总支出!$E$4:$E$5000,$A52) -> 0 | H52: =SUMIFS(总支出!$D$4:$D$5000,总支出!$B$4:$B$5000,">="&DATE(VALUE(LEFT(H$44,4)),VALUE(RIGHT(H$44,2)),1),总支出!$B$4:$B$5000,"<"&DATE(VALUE(LEFT(H$44,4)),VALUE(RIGHT(H$44,2))+1,1),总支出!$H$4:$H$5000,"个人支出",总支出!$E$4:$E$5000,$A52) -> 0 | I52: =SUMIFS(总支出!$D$4:$D$5000,总支出!$B$4:$B$5000,">="&DATE(VALUE(LEFT(I$44,4)),VALUE(RIGHT(I$44,2)),1),总支出!$B$4:$B$5000,"<"&DATE(VALUE(LEFT(I$44,4)),VALUE(RIGHT(I$44,2))+1,1),总支出!$H$4:$H$5000,"个人支出",总支出!$E$4:$E$5000,$A52) -> 0 | ... M52: =SUMIFS(总支出!$D$4:$D$5000,总支出!$B$4:$B$5000,">="&DATE(VALUE(LEFT(M$44,4)),VALUE(RIGHT(M$44,2)),1),总支出!$B$4:$B$5000,"<"&DATE(VALUE(LEFT(M$44,4)),VALUE(RIGHT(M$44,2))+1,1),总支出!$H$4:$H$5000,"个人支出",总支出!$E$4:$E$5000,$A52) -> 0 | N52: =IF($B$4=0,0,SUM(B52:M52)/$B$4) -> 70 | O52: =N52*12 -> 840 | P52: =IFERROR(N52/$B$7,0) -> 0.013592233
A53: 学习 | B53: =SUMIFS(总支出!$D$4:$D$5000,总支出!$B$4:$B$5000,">="&DATE(VALUE(LEFT(B$44,4)),VALUE(RIGHT(B$44,2)),1),总支出!$B$4:$B$5000,"<"&DATE(VALUE(LEFT(B$44,4)),VALUE(RIGHT(B$44,2))+1,1),总支出!$H$4:$H$5000,"个人支出",总支出!$E$4:$E$5000,$A53) -> 120 | C53: =SUMIFS(总支出!$D$4:$D$5000,总支出!$B$4:$B$5000,">="&DATE(VALUE(LEFT(C$44,4)),VALUE(RIGHT(C$44,2)),1),总支出!$B$4:$B$5000,"<"&DATE(VALUE(LEFT(C$44,4)),VALUE(RIGHT(C$44,2))+1,1),总支出!$H$4:$H$5000,"个人支出",总支出!$E$4:$E$5000,$A53) -> 140 | D53: =SUMIFS(总支出!$D$4:$D$5000,总支出!$B$4:$B$5000,">="&DATE(VALUE(LEFT(D$44,4)),VALUE(RIGHT(D$44,2)),1),总支出!$B$4:$B$5000,"<"&DATE(VALUE(LEFT(D$44,4)),VALUE(RIGHT(D$44,2))+1,1),总支出!$H$4:$H$5000,"个人支出",总支出!$E$4:$E$5000,$A53) -> 0 | E53: =SUMIFS(总支出!$D$4:$D$5000,总支出!$B$4:$B$5000,">="&DATE(VALUE(LEFT(E$44,4)),VALUE(RIGHT(E$44,2)),1),总支出!$B$4:$B$5000,"<"&DATE(VALUE(LEFT(E$44,4)),VALUE(RIGHT(E$44,2))+1,1),总支出!$H$4:$H$5000,"个人支出",总支出!$E$4:$E$5000,$A53) -> 0 | F53: =SUMIFS(总支出!$D$4:$D$5000,总支出!$B$4:$B$5000,">="&DATE(VALUE(LEFT(F$44,4)),VALUE(RIGHT(F$44,2)),1),总支出!$B$4:$B$5000,"<"&DATE(VALUE(LEFT(F$44,4)),VALUE(RIGHT(F$44,2))+1,1),总支出!$H$4:$H$5000,"个人支出",总支出!$E$4:$E$5000,$A53) -> 0 | G53: =SUMIFS(总支出!$D$4:$D$5000,总支出!$B$4:$B$5000,">="&DATE(VALUE(LEFT(G$44,4)),VALUE(RIGHT(G$44,2)),1),总支出!$B$4:$B$5000,"<"&DATE(VALUE(LEFT(G$44,4)),VALUE(RIGHT(G$44,2))+1,1),总支出!$H$4:$H$5000,"个人支出",总支出!$E$4:$E$5000,$A53) -> 0 | H53: =SUMIFS(总支出!$D$4:$D$5000,总支出!$B$4:$B$5000,">="&DATE(VALUE(LEFT(H$44,4)),VALUE(RIGHT(H$44,2)),1),总支出!$B$4:$B$5000,"<"&DATE(VALUE(LEFT(H$44,4)),VALUE(RIGHT(H$44,2))+1,1),总支出!$H$4:$H$5000,"个人支出",总支出!$E$4:$E$5000,$A53) -> 0 | I53: =SUMIFS(总支出!$D$4:$D$5000,总支出!$B$4:$B$5000,">="&DATE(VALUE(LEFT(I$44,4)),VALUE(RIGHT(I$44,2)),1),总支出!$B$4:$B$5000,"<"&DATE(VALUE(LEFT(I$44,4)),VALUE(RIGHT(I$44,2))+1,1),总支出!$H$4:$H$5000,"个人支出",总支出!$E$4:$E$5000,$A53) -> 0 | ... M53: =SUMIFS(总支出!$D$4:$D$5000,总支出!$B$4:$B$5000,">="&DATE(VALUE(LEFT(M$44,4)),VALUE(RIGHT(M$44,2)),1),总支出!$B$4:$B$5000,"<"&DATE(VALUE(LEFT(M$44,4)),VALUE(RIGHT(M$44,2))+1,1),总支出!$H$4:$H$5000,"个人支出",总支出!$E$4:$E$5000,$A53) -> 0 | N53: =IF($B$4=0,0,SUM(B53:M53)/$B$4) -> 130 | O53: =N53*12 -> 1560 | P53: =IFERROR(N53/$B$7,0) -> 0.025242718
A54: 宠物 | B54: =SUMIFS(总支出!$D$4:$D$5000,总支出!$B$4:$B$5000,">="&DATE(VALUE(LEFT(B$44,4)),VALUE(RIGHT(B$44,2)),1),总支出!$B$4:$B$5000,"<"&DATE(VALUE(LEFT(B$44,4)),VALUE(RIGHT(B$44,2))+1,1),总支出!$H$4:$H$5000,"个人支出",总支出!$E$4:$E$5000,$A54) -> 90 | C54: =SUMIFS(总支出!$D$4:$D$5000,总支出!$B$4:$B$5000,">="&DATE(VALUE(LEFT(C$44,4)),VALUE(RIGHT(C$44,2)),1),总支出!$B$4:$B$5000,"<"&DATE(VALUE(LEFT(C$44,4)),VALUE(RIGHT(C$44,2))+1,1),总支出!$H$4:$H$5000,"个人支出",总支出!$E$4:$E$5000,$A54) -> 100 | D54: =SUMIFS(总支出!$D$4:$D$5000,总支出!$B$4:$B$5000,">="&DATE(VALUE(LEFT(D$44,4)),VALUE(RIGHT(D$44,2)),1),总支出!$B$4:$B$5000,"<"&DATE(VALUE(LEFT(D$44,4)),VALUE(RIGHT(D$44,2))+1,1),总支出!$H$4:$H$5000,"个人支出",总支出!$E$4:$E$5000,$A54) -> 0 | E54: =SUMIFS(总支出!$D$4:$D$5000,总支出!$B$4:$B$5000,">="&DATE(VALUE(LEFT(E$44,4)),VALUE(RIGHT(E$44,2)),1),总支出!$B$4:$B$5000,"<"&DATE(VALUE(LEFT(E$44,4)),VALUE(RIGHT(E$44,2))+1,1),总支出!$H$4:$H$5000,"个人支出",总支出!$E$4:$E$5000,$A54) -> 0 | F54: =SUMIFS(总支出!$D$4:$D$5000,总支出!$B$4:$B$5000,">="&DATE(VALUE(LEFT(F$44,4)),VALUE(RIGHT(F$44,2)),1),总支出!$B$4:$B$5000,"<"&DATE(VALUE(LEFT(F$44,4)),VALUE(RIGHT(F$44,2))+1,1),总支出!$H$4:$H$5000,"个人支出",总支出!$E$4:$E$5000,$A54) -> 0 | G54: =SUMIFS(总支出!$D$4:$D$5000,总支出!$B$4:$B$5000,">="&DATE(VALUE(LEFT(G$44,4)),VALUE(RIGHT(G$44,2)),1),总支出!$B$4:$B$5000,"<"&DATE(VALUE(LEFT(G$44,4)),VALUE(RIGHT(G$44,2))+1,1),总支出!$H$4:$H$5000,"个人支出",总支出!$E$4:$E$5000,$A54) -> 0 | H54: =SUMIFS(总支出!$D$4:$D$5000,总支出!$B$4:$B$5000,">="&DATE(VALUE(LEFT(H$44,4)),VALUE(RIGHT(H$44,2)),1),总支出!$B$4:$B$5000,"<"&DATE(VALUE(LEFT(H$44,4)),VALUE(RIGHT(H$44,2))+1,1),总支出!$H$4:$H$5000,"个人支出",总支出!$E$4:$E$5000,$A54) -> 0 | I54: =SUMIFS(总支出!$D$4:$D$5000,总支出!$B$4:$B$5000,">="&DATE(VALUE(LEFT(I$44,4)),VALUE(RIGHT(I$44,2)),1),总支出!$B$4:$B$5000,"<"&DATE(VALUE(LEFT(I$44,4)),VALUE(RIGHT(I$44,2))+1,1),总支出!$H$4:$H$5000,"个人支出",总支出!$E$4:$E$5000,$A54) -> 0 | ... M54: =SUMIFS(总支出!$D$4:$D$5000,总支出!$B$4:$B$5000,">="&DATE(VALUE(LEFT(M$44,4)),VALUE(RIGHT(M$44,2)),1),总支出!$B$4:$B$5000,"<"&DATE(VALUE(LEFT(M$44,4)),VALUE(RIGHT(M$44,2))+1,1),总支出!$H$4:$H$5000,"个人支出",总支出!$E$4:$E$5000,$A54) -> 0 | N54: =IF($B$4=0,0,SUM(B54:M54)/$B$4) -> 95 | O54: =N54*12 -> 1140 | P54: =IFERROR(N54/$B$7,0) -> 0.018446602
A55: 娱乐 | B55: =SUMIFS(总支出!$D$4:$D$5000,总支出!$B$4:$B$5000,">="&DATE(VALUE(LEFT(B$44,4)),VALUE(RIGHT(B$44,2)),1),总支出!$B$4:$B$5000,"<"&DATE(VALUE(LEFT(B$44,4)),VALUE(RIGHT(B$44,2))+1,1),总支出!$H$4:$H$5000,"个人支出",总支出!$E$4:$E$5000,$A55) -> 100 | C55: =SUMIFS(总支出!$D$4:$D$5000,总支出!$B$4:$B$5000,">="&DATE(VALUE(LEFT(C$44,4)),VALUE(RIGHT(C$44,2)),1),总支出!$B$4:$B$5000,"<"&DATE(VALUE(LEFT(C$44,4)),VALUE(RIGHT(C$44,2))+1,1),总支出!$H$4:$H$5000,"个人支出",总支出!$E$4:$E$5000,$A55) -> 120 | D55: =SUMIFS(总支出!$D$4:$D$5000,总支出!$B$4:$B$5000,">="&DATE(VALUE(LEFT(D$44,4)),VALUE(RIGHT(D$44,2)),1),总支出!$B$4:$B$5000,"<"&DATE(VALUE(LEFT(D$44,4)),VALUE(RIGHT(D$44,2))+1,1),总支出!$H$4:$H$5000,"个人支出",总支出!$E$4:$E$5000,$A55) -> 0 | E55: =SUMIFS(总支出!$D$4:$D$5000,总支出!$B$4:$B$5000,">="&DATE(VALUE(LEFT(E$44,4)),VALUE(RIGHT(E$44,2)),1),总支出!$B$4:$B$5000,"<"&DATE(VALUE(LEFT(E$44,4)),VALUE(RIGHT(E$44,2))+1,1),总支出!$H$4:$H$5000,"个人支出",总支出!$E$4:$E$5000,$A55) -> 0 | F55: =SUMIFS(总支出!$D$4:$D$5000,总支出!$B$4:$B$5000,">="&DATE(VALUE(LEFT(F$44,4)),VALUE(RIGHT(F$44,2)),1),总支出!$B$4:$B$5000,"<"&DATE(VALUE(LEFT(F$44,4)),VALUE(RIGHT(F$44,2))+1,1),总支出!$H$4:$H$5000,"个人支出",总支出!$E$4:$E$5000,$A55) -> 0 | G55: =SUMIFS(总支出!$D$4:$D$5000,总支出!$B$4:$B$5000,">="&DATE(VALUE(LEFT(G$44,4)),VALUE(RIGHT(G$44,2)),1),总支出!$B$4:$B$5000,"<"&DATE(VALUE(LEFT(G$44,4)),VALUE(RIGHT(G$44,2))+1,1),总支出!$H$4:$H$5000,"个人支出",总支出!$E$4:$E$5000,$A55) -> 0 | H55: =SUMIFS(总支出!$D$4:$D$5000,总支出!$B$4:$B$5000,">="&DATE(VALUE(LEFT(H$44,4)),VALUE(RIGHT(H$44,2)),1),总支出!$B$4:$B$5000,"<"&DATE(VALUE(LEFT(H$44,4)),VALUE(RIGHT(H$44,2))+1,1),总支出!$H$4:$H$5000,"个人支出",总支出!$E$4:$E$5000,$A55) -> 0 | I55: =SUMIFS(总支出!$D$4:$D$5000,总支出!$B$4:$B$5000,">="&DATE(VALUE(LEFT(I$44,4)),VALUE(RIGHT(I$44,2)),1),总支出!$B$4:$B$5000,"<"&DATE(VALUE(LEFT(I$44,4)),VALUE(RIGHT(I$44,2))+1,1),总支出!$H$4:$H$5000,"个人支出",总支出!$E$4:$E$5000,$A55) -> 0 | ... M55: =SUMIFS(总支出!$D$4:$D$5000,总支出!$B$4:$B$5000,">="&DATE(VALUE(LEFT(M$44,4)),VALUE(RIGHT(M$44,2)),1),总支出!$B$4:$B$5000,"<"&DATE(VALUE(LEFT(M$44,4)),VALUE(RIGHT(M$44,2))+1,1),总支出!$H$4:$H$5000,"个人支出",总支出!$E$4:$E$5000,$A55) -> 0 | N55: =IF($B$4=0,0,SUM(B55:M55)/$B$4) -> 110 | O55: =N55*12 -> 1320 | P55: =IFERROR(N55/$B$7,0) -> 0.021359223
A56: 税费 | B56: =SUMIFS(总支出!$D$4:$D$5000,总支出!$B$4:$B$5000,">="&DATE(VALUE(LEFT(B$44,4)),VALUE(RIGHT(B$44,2)),1),总支出!$B$4:$B$5000,"<"&DATE(VALUE(LEFT(B$44,4)),VALUE(RIGHT(B$44,2))+1,1),总支出!$H$4:$H$5000,"个人支出",总支出!$E$4:$E$5000,$A56) -> 100 | C56: =SUMIFS(总支出!$D$4:$D$5000,总支出!$B$4:$B$5000,">="&DATE(VALUE(LEFT(C$44,4)),VALUE(RIGHT(C$44,2)),1),总支出!$B$4:$B$5000,"<"&DATE(VALUE(LEFT(C$44,4)),VALUE(RIGHT(C$44,2))+1,1),总支出!$H$4:$H$5000,"个人支出",总支出!$E$4:$E$5000,$A56) -> 150 | D56: =SUMIFS(总支出!$D$4:$D$5000,总支出!$B$4:$B$5000,">="&DATE(VALUE(LEFT(D$44,4)),VALUE(RIGHT(D$44,2)),1),总支出!$B$4:$B$5000,"<"&DATE(VALUE(LEFT(D$44,4)),VALUE(RIGHT(D$44,2))+1,1),总支出!$H$4:$H$5000,"个人支出",总支出!$E$4:$E$5000,$A56) -> 0 | E56: =SUMIFS(总支出!$D$4:$D$5000,总支出!$B$4:$B$5000,">="&DATE(VALUE(LEFT(E$44,4)),VALUE(RIGHT(E$44,2)),1),总支出!$B$4:$B$5000,"<"&DATE(VALUE(LEFT(E$44,4)),VALUE(RIGHT(E$44,2))+1,1),总支出!$H$4:$H$5000,"个人支出",总支出!$E$4:$E$5000,$A56) -> 0 | F56: =SUMIFS(总支出!$D$4:$D$5000,总支出!$B$4:$B$5000,">="&DATE(VALUE(LEFT(F$44,4)),VALUE(RIGHT(F$44,2)),1),总支出!$B$4:$B$5000,"<"&DATE(VALUE(LEFT(F$44,4)),VALUE(RIGHT(F$44,2))+1,1),总支出!$H$4:$H$5000,"个人支出",总支出!$E$4:$E$5000,$A56) -> 0 | G56: =SUMIFS(总支出!$D$4:$D$5000,总支出!$B$4:$B$5000,">="&DATE(VALUE(LEFT(G$44,4)),VALUE(RIGHT(G$44,2)),1),总支出!$B$4:$B$5000,"<"&DATE(VALUE(LEFT(G$44,4)),VALUE(RIGHT(G$44,2))+1,1),总支出!$H$4:$H$5000,"个人支出",总支出!$E$4:$E$5000,$A56) -> 0 | H56: =SUMIFS(总支出!$D$4:$D$5000,总支出!$B$4:$B$5000,">="&DATE(VALUE(LEFT(H$44,4)),VALUE(RIGHT(H$44,2)),1),总支出!$B$4:$B$5000,"<"&DATE(VALUE(LEFT(H$44,4)),VALUE(RIGHT(H$44,2))+1,1),总支出!$H$4:$H$5000,"个人支出",总支出!$E$4:$E$5000,$A56) -> 0 | I56: =SUMIFS(总支出!$D$4:$D$5000,总支出!$B$4:$B$5000,">="&DATE(VALUE(LEFT(I$44,4)),VALUE(RIGHT(I$44,2)),1),总支出!$B$4:$B$5000,"<"&DATE(VALUE(LEFT(I$44,4)),VALUE(RIGHT(I$44,2))+1,1),总支出!$H$4:$H$5000,"个人支出",总支出!$E$4:$E$5000,$A56) -> 0 | ... M56: =SUMIFS(总支出!$D$4:$D$5000,总支出!$B$4:$B$5000,">="&DATE(VALUE(LEFT(M$44,4)),VALUE(RIGHT(M$44,2)),1),总支出!$B$4:$B$5000,"<"&DATE(VALUE(LEFT(M$44,4)),VALUE(RIGHT(M$44,2))+1,1),总支出!$H$4:$H$5000,"个人支出",总支出!$E$4:$E$5000,$A56) -> 0 | N56: =IF($B$4=0,0,SUM(B56:M56)/$B$4) -> 125 | O56: =N56*12 -> 1500 | P56: =IFERROR(N56/$B$7,0) -> 0.024271845
A57: 其他 | B57: =SUMIFS(总支出!$D$4:$D$5000,总支出!$B$4:$B$5000,">="&DATE(VALUE(LEFT(B$44,4)),VALUE(RIGHT(B$44,2)),1),总支出!$B$4:$B$5000,"<"&DATE(VALUE(LEFT(B$44,4)),VALUE(RIGHT(B$44,2))+1,1),总支出!$H$4:$H$5000,"个人支出",总支出!$E$4:$E$5000,$A57) -> 110 | C57: =SUMIFS(总支出!$D$4:$D$5000,总支出!$B$4:$B$5000,">="&DATE(VALUE(LEFT(C$44,4)),VALUE(RIGHT(C$44,2)),1),总支出!$B$4:$B$5000,"<"&DATE(VALUE(LEFT(C$44,4)),VALUE(RIGHT(C$44,2))+1,1),总支出!$H$4:$H$5000,"个人支出",总支出!$E$4:$E$5000,$A57) -> 85 | D57: =SUMIFS(总支出!$D$4:$D$5000,总支出!$B$4:$B$5000,">="&DATE(VALUE(LEFT(D$44,4)),VALUE(RIGHT(D$44,2)),1),总支出!$B$4:$B$5000,"<"&DATE(VALUE(LEFT(D$44,4)),VALUE(RIGHT(D$44,2))+1,1),总支出!$H$4:$H$5000,"个人支出",总支出!$E$4:$E$5000,$A57) -> 0 | E57: =SUMIFS(总支出!$D$4:$D$5000,总支出!$B$4:$B$5000,">="&DATE(VALUE(LEFT(E$44,4)),VALUE(RIGHT(E$44,2)),1),总支出!$B$4:$B$5000,"<"&DATE(VALUE(LEFT(E$44,4)),VALUE(RIGHT(E$44,2))+1,1),总支出!$H$4:$H$5000,"个人支出",总支出!$E$4:$E$5000,$A57) -> 0 | F57: =SUMIFS(总支出!$D$4:$D$5000,总支出!$B$4:$B$5000,">="&DATE(VALUE(LEFT(F$44,4)),VALUE(RIGHT(F$44,2)),1),总支出!$B$4:$B$5000,"<"&DATE(VALUE(LEFT(F$44,4)),VALUE(RIGHT(F$44,2))+1,1),总支出!$H$4:$H$5000,"个人支出",总支出!$E$4:$E$5000,$A57) -> 0 | G57: =SUMIFS(总支出!$D$4:$D$5000,总支出!$B$4:$B$5000,">="&DATE(VALUE(LEFT(G$44,4)),VALUE(RIGHT(G$44,2)),1),总支出!$B$4:$B$5000,"<"&DATE(VALUE(LEFT(G$44,4)),VALUE(RIGHT(G$44,2))+1,1),总支出!$H$4:$H$5000,"个人支出",总支出!$E$4:$E$5000,$A57) -> 0 | H57: =SUMIFS(总支出!$D$4:$D$5000,总支出!$B$4:$B$5000,">="&DATE(VALUE(LEFT(H$44,4)),VALUE(RIGHT(H$44,2)),1),总支出!$B$4:$B$5000,"<"&DATE(VALUE(LEFT(H$44,4)),VALUE(RIGHT(H$44,2))+1,1),总支出!$H$4:$H$5000,"个人支出",总支出!$E$4:$E$5000,$A57) -> 0 | I57: =SUMIFS(总支出!$D$4:$D$5000,总支出!$B$4:$B$5000,">="&DATE(VALUE(LEFT(I$44,4)),VALUE(RIGHT(I$44,2)),1),总支出!$B$4:$B$5000,"<"&DATE(VALUE(LEFT(I$44,4)),VALUE(RIGHT(I$44,2))+1,1),总支出!$H$4:$H$5000,"个人支出",总支出!$E$4:$E$5000,$A57) -> 0 | ... M57: =SUMIFS(总支出!$D$4:$D$5000,总支出!$B$4:$B$5000,">="&DATE(VALUE(LEFT(M$44,4)),VALUE(RIGHT(M$44,2)),1),总支出!$B$4:$B$5000,"<"&DATE(VALUE(LEFT(M$44,4)),VALUE(RIGHT(M$44,2))+1,1),总支出!$H$4:$H$5000,"个人支出",总支出!$E$4:$E$5000,$A57) -> 0 | N57: =IF($B$4=0,0,SUM(B57:M57)/$B$4) -> 97.5 | O57: =N57*12 -> 1170 | P57: =IFERROR(N57/$B$7,0) -> 0.018932039
A63: 情景 | B63: 月支出基准 | C63: 年度基准 | D63: 说明
A64: Lean 必要生活 | B64: =$B$8 -> 4000 | C64: =B64*12 -> 48000 | D64: 只按必要支出估算最低生活底盘
A65: Normal 当前生活 | B65: =$B$7 -> 5150 | C65: =B65*12 -> 61800 | D65: 按当前平均个人支出估算
A66: Conservative 保守 | B66: =MAX($C$28:$C$39) -> 5300 | C66: =B66*12 -> 63600 | D66: 用最高月支出作为压力测试

Sheet 税费计算明细
A1: 税费计算明细
A2: 本页由公式自动从“总支出”和“税费设置”读取。用户通常不需要修改。
A3: 记录编号 | B3: 日期 | C3: 月份 | D3: 支出内容 | E3: 支出金额 | F3: 主类别 | G3: 分析口径 | H3: 用户税费类型 | I3: 默认税费类型 | J3: 最终税费类型 | K3: 纳入估算 | L3: 应税消费 | M3: 零税率消费 | N3: 免税消费 | O3: 其他/不适用 | P3: 税前金额 | Q3: 联邦税估算 | R3: 省级税估算 | S3: 消费税合计
A4: =IF(总支出!A4="","",总支出!A4) -> 支出-0001 | B4: =IF(总支出!B4="","",总支出!B4) -> 46023 | C4: =IF(B4="","",TEXT(B4,"yyyy-mm")) -> 2026-01 | D4: =IF(总支出!C4="","",总支出!C4) -> 房租 | E4: =IF(总支出!D4="","",总支出!D4) -> 3000 | F4: =IF(总支出!E4="","",总支出!E4) -> 住房 | G4: =IF(总支出!H4="","",总支出!H4) -> 个人支出 | H4: =IF(总支出!I4="","自动",总支出!I4) -> 免税 | I4: =IF(F4="","",IFERROR(VLOOKUP(F4,税费设置!$A$15:$B$27,2,FALSE),"含税不明")) -> 免税 | J4: =IF(D4="","",IF(H4="自动",I4,H4)) -> 免税 | K4: =IF(AND(税费设置!$B$5="是",G4="个人支出",J4="应税"),"是","否") -> 否 | L4: =IF(K4="是",E4,0) -> 0 | M4: =IF(AND(G4="个人支出",J4="零税率"),E4,0) -> 0 | N4: =IF(AND(G4="个人支出",J4="免税"),E4,0) -> 3000 | O4: =IF(AND(G4="个人支出",OR(J4="含税不明",J4="不适用")),E4,0) -> 0 | P4: =IF(K4<>"是",0,IF(税费设置!$B$6="是",E4/(1+税费设置!$B$10),E4)) -> 0 | Q4: =IF(K4<>"是",0,P4*税费设置!$B$8) -> 0 | R4: =IF(K4<>"是",0,P4*税费设置!$B$9) -> 0 | S4: =Q4+R4 -> 0
A5: =IF(总支出!A5="","",总支出!A5) -> 支出-0002 | B5: =IF(总支出!B5="","",总支出!B5) -> 46025 | C5: =IF(B5="","",TEXT(B5,"yyyy-mm")) -> 2026-01 | D5: =IF(总支出!C5="","",总支出!C5) -> 超市基础食品：鸡蛋、蔬菜、牛奶 | E5: =IF(总支出!D5="","",总支出!D5) -> 450 | F5: =IF(总支出!E5="","",总支出!E5) -> 餐饮 | G5: =IF(总支出!H5="","",总支出!H5) -> 个人支出 | H5: =IF(总支出!I5="","自动",总支出!I5) -> 零税率 | I5: =IF(F5="","",IFERROR(VLOOKUP(F5,税费设置!$A$15:$B$27,2,FALSE),"含税不明")) -> 应税 | J5: =IF(D5="","",IF(H5="自动",I5,H5)) -> 零税率 | K5: =IF(AND(税费设置!$B$5="是",G5="个人支出",J5="应税"),"是","否") -> 否 | L5: =IF(K5="是",E5,0) -> 0 | M5: =IF(AND(G5="个人支出",J5="零税率"),E5,0) -> 450 | N5: =IF(AND(G5="个人支出",J5="免税"),E5,0) -> 0 | O5: =IF(AND(G5="个人支出",OR(J5="含税不明",J5="不适用")),E5,0) -> 0 | P5: =IF(K5<>"是",0,IF(税费设置!$B$6="是",E5/(1+税费设置!$B$10),E5)) -> 0 | Q5: =IF(K5<>"是",0,P5*税费设置!$B$8) -> 0 | R5: =IF(K5<>"是",0,P5*税费设置!$B$9) -> 0 | S5: =Q5+R5 -> 0
A6: =IF(总支出!A6="","",总支出!A6) -> 支出-0003 | B6: =IF(总支出!B6="","",总支出!B6) -> 46027 | C6: =IF(B6="","",TEXT(B6,"yyyy-mm")) -> 2026-01 | D6: =IF(总支出!C6="","",总支出!C6) -> 餐厅外食 | E6: =IF(总支出!D6="","",总支出!D6) -> 320 | F6: =IF(总支出!E6="","",总支出!E6) -> 餐饮 | G6: =IF(总支出!H6="","",总支出!H6) -> 个人支出 | H6: =IF(总支出!I6="","自动",总支出!I6) -> 应税 | I6: =IF(F6="","",IFERROR(VLOOKUP(F6,税费设置!$A$15:$B$27,2,FALSE),"含税不明")) -> 应税 | J6: =IF(D6="","",IF(H6="自动",I6,H6)) -> 应税 | K6: =IF(AND(税费设置!$B$5="是",G6="个人支出",J6="应税"),"是","否") -> 是 | L6: =IF(K6="是",E6,0) -> 320 | M6: =IF(AND(G6="个人支出",J6="零税率"),E6,0) -> 0 | N6: =IF(AND(G6="个人支出",J6="免税"),E6,0) -> 0 | O6: =IF(AND(G6="个人支出",OR(J6="含税不明",J6="不适用")),E6,0) -> 0 | P6: =IF(K6<>"是",0,IF(税费设置!$B$6="是",E6/(1+税费设置!$B$10),E6)) -> 278.32137 | Q6: =IF(K6<>"是",0,P6*税费设置!$B$8) -> 13.916069 | R6: =IF(K6<>"是",0,P6*税费设置!$B$9) -> 27.762557 | S6: =Q6+R6 -> 41.678626
A7: =IF(总支出!A7="","",总支出!A7) -> 支出-0004 | B7: =IF(总支出!B7="","",总支出!B7) -> 46029 | C7: =IF(B7="","",TEXT(B7,"yyyy-mm")) -> 2026-01 | D7: =IF(总支出!C7="","",总支出!C7) -> 加油 | E7: =IF(总支出!D7="","",总支出!D7) -> 220 | F7: =IF(总支出!E7="","",总支出!E7) -> 交通 | G7: =IF(总支出!H7="","",总支出!H7) -> 个人支出 | H7: =IF(总支出!I7="","自动",总支出!I7) -> 应税 | I7: =IF(F7="","",IFERROR(VLOOKUP(F7,税费设置!$A$15:$B$27,2,FALSE),"含税不明")) -> 应税 | J7: =IF(D7="","",IF(H7="自动",I7,H7)) -> 应税 | K7: =IF(AND(税费设置!$B$5="是",G7="个人支出",J7="应税"),"是","否") -> 是 | L7: =IF(K7="是",E7,0) -> 220 | M7: =IF(AND(G7="个人支出",J7="零税率"),E7,0) -> 0 | N7: =IF(AND(G7="个人支出",J7="免税"),E7,0) -> 0 | O7: =IF(AND(G7="个人支出",OR(J7="含税不明",J7="不适用")),E7,0) -> 0 | P7: =IF(K7<>"是",0,IF(税费设置!$B$6="是",E7/(1+税费设置!$B$10),E7)) -> 191.34594 | Q7: =IF(K7<>"是",0,P7*税费设置!$B$8) -> 9.5672972 | R7: =IF(K7<>"是",0,P7*税费设置!$B$9) -> 19.086758 | S7: =Q7+R7 -> 28.654055
A8: =IF(总支出!A8="","",总支出!A8) -> 支出-0005 | B8: =IF(总支出!B8="","",总支出!B8) -> 46030 | C8: =IF(B8="","",TEXT(B8,"yyyy-mm")) -> 2026-01 | D8: =IF(总支出!C8="","",总支出!C8) -> 手机通讯费 | E8: =IF(总支出!D8="","",总支出!D8) -> 60 | F8: =IF(总支出!E8="","",总支出!E8) -> 通讯 | G8: =IF(总支出!H8="","",总支出!H8) -> 个人支出 | H8: =IF(总支出!I8="","自动",总支出!I8) -> 应税 | I8: =IF(F8="","",IFERROR(VLOOKUP(F8,税费设置!$A$15:$B$27,2,FALSE),"含税不明")) -> 应税 | J8: =IF(D8="","",IF(H8="自动",I8,H8)) -> 应税 | K8: =IF(AND(税费设置!$B$5="是",G8="个人支出",J8="应税"),"是","否") -> 是 | L8: =IF(K8="是",E8,0) -> 60 | M8: =IF(AND(G8="个人支出",J8="零税率"),E8,0) -> 0 | N8: =IF(AND(G8="个人支出",J8="免税"),E8,0) -> 0 | O8: =IF(AND(G8="个人支出",OR(J8="含税不明",J8="不适用")),E8,0) -> 0 | P8: =IF(K8<>"是",0,IF(税费设置!$B$6="是",E8/(1+税费设置!$B$10),E8)) -> 52.185258 | Q8: =IF(K8<>"是",0,P8*税费设置!$B$8) -> 2.6092629 | R8: =IF(K8<>"是",0,P8*税费设置!$B$9) -> 5.2054795 | S8: =Q8+R8 -> 7.8147423
A9: =IF(总支出!A9="","",总支出!A9) -> 支出-0006 | B9: =IF(总支出!B9="","",总支出!B9) -> 46031 | C9: =IF(B9="","",TEXT(B9,"yyyy-mm")) -> 2026-01 | D9: =IF(总支出!C9="","",总支出!C9) -> 云服务订阅 | E9: =IF(总支出!D9="","",总支出!D9) -> 30 | F9: =IF(总支出!E9="","",总支出!E9) -> 订阅 | G9: =IF(总支出!H9="","",总支出!H9) -> 个人支出 | H9: =IF(总支出!I9="","自动",总支出!I9) -> 应税 | I9: =IF(F9="","",IFERROR(VLOOKUP(F9,税费设置!$A$15:$B$27,2,FALSE),"含税不明")) -> 应税 | J9: =IF(D9="","",IF(H9="自动",I9,H9)) -> 应税 | K9: =IF(AND(税费设置!$B$5="是",G9="个人支出",J9="应税"),"是","否") -> 是 | L9: =IF(K9="是",E9,0) -> 30 | M9: =IF(AND(G9="个人支出",J9="零税率"),E9,0) -> 0 | N9: =IF(AND(G9="个人支出",J9="免税"),E9,0) -> 0 | O9: =IF(AND(G9="个人支出",OR(J9="含税不明",J9="不适用")),E9,0) -> 0 | P9: =IF(K9<>"是",0,IF(税费设置!$B$6="是",E9/(1+税费设置!$B$10),E9)) -> 26.092629 | Q9: =IF(K9<>"是",0,P9*税费设置!$B$8) -> 1.3046314 | R9: =IF(K9<>"是",0,P9*税费设置!$B$9) -> 2.6027397 | S9: =Q9+R9 -> 3.9073712
A10: =IF(总支出!A10="","",总支出!A10) -> 支出-0007 | B10: =IF(总支出!B10="","",总支出!B10) -> 46032 | C10: =IF(B10="","",TEXT(B10,"yyyy-mm")) -> 2026-01 | D10: =IF(总支出!C10="","",总支出!C10) -> 衣物与日用品购物 | E10: =IF(总支出!D10="","",总支出!D10) -> 250 | F10: =IF(总支出!E10="","",总支出!E10) -> 购物 | G10: =IF(总支出!H10="","",总支出!H10) -> 个人支出 | H10: =IF(总支出!I10="","自动",总支出!I10) -> 应税 | I10: =IF(F10="","",IFERROR(VLOOKUP(F10,税费设置!$A$15:$B$27,2,FALSE),"含税不明")) -> 应税 | J10: =IF(D10="","",IF(H10="自动",I10,H10)) -> 应税 | K10: =IF(AND(税费设置!$B$5="是",G10="个人支出",J10="应税"),"是","否") -> 是 | L10: =IF(K10="是",E10,0) -> 250 | M10: =IF(AND(G10="个人支出",J10="零税率"),E10,0) -> 0 | N10: =IF(AND(G10="个人支出",J10="免税"),E10,0) -> 0 | O10: =IF(AND(G10="个人支出",OR(J10="含税不明",J10="不适用")),E10,0) -> 0 | P10: =IF(K10<>"是",0,IF(税费设置!$B$6="是",E10/(1+税费设置!$B$10),E10)) -> 217.43857 | Q10: =IF(K10<>"是",0,P10*税费设置!$B$8) -> 10.871929 | R10: =IF(K10<>"是",0,P10*税费设置!$B$9) -> 21.689498 | S10: =Q10+R10 -> 32.561426
A11: =IF(总支出!A11="","",总支出!A11) -> 支出-0008 | B11: =IF(总支出!B11="","",总支出!B11) -> 46034 | C11: =IF(B11="","",TEXT(B11,"yyyy-mm")) -> 2026-01 | D11: =IF(总支出!C11="","",总支出!C11) -> 药品和医疗用品 | E11: =IF(总支出!D11="","",总支出!D11) -> 80 | F11: =IF(总支出!E11="","",总支出!E11) -> 医疗 | G11: =IF(总支出!H11="","",总支出!H11) -> 个人支出 | H11: =IF(总支出!I11="","自动",总支出!I11) -> 免税 | I11: =IF(F11="","",IFERROR(VLOOKUP(F11,税费设置!$A$15:$B$27,2,FALSE),"含税不明")) -> 免税 | J11: =IF(D11="","",IF(H11="自动",I11,H11)) -> 免税 | K11: =IF(AND(税费设置!$B$5="是",G11="个人支出",J11="应税"),"是","否") -> 否 | L11: =IF(K11="是",E11,0) -> 0 | M11: =IF(AND(G11="个人支出",J11="零税率"),E11,0) -> 0 | N11: =IF(AND(G11="个人支出",J11="免税"),E11,0) -> 80 | O11: =IF(AND(G11="个人支出",OR(J11="含税不明",J11="不适用")),E11,0) -> 0 | P11: =IF(K11<>"是",0,IF(税费设置!$B$6="是",E11/(1+税费设置!$B$10),E11)) -> 0 | Q11: =IF(K11<>"是",0,P11*税费设置!$B$8) -> 0 | R11: =IF(K11<>"是",0,P11*税费设置!$B$9) -> 0 | S11: =Q11+R11 -> 0
A12: =IF(总支出!A12="","",总支出!A12) -> 支出-0009 | B12: =IF(总支出!B12="","",总支出!B12) -> 46037 | C12: =IF(B12="","",TEXT(B12,"yyyy-mm")) -> 2026-01 | D12: =IF(总支出!C12="","",总支出!C12) -> 健身房月费 | E12: =IF(总支出!D12="","",总支出!D12) -> 70 | F12: =IF(总支出!E12="","",总支出!E12) -> 运动 | G12: =IF(总支出!H12="","",总支出!H12) -> 个人支出 | H12: =IF(总支出!I12="","自动",总支出!I12) -> 应税 | I12: =IF(F12="","",IFERROR(VLOOKUP(F12,税费设置!$A$15:$B$27,2,FALSE),"含税不明")) -> 应税 | J12: =IF(D12="","",IF(H12="自动",I12,H12)) -> 应税 | K12: =IF(AND(税费设置!$B$5="是",G12="个人支出",J12="应税"),"是","否") -> 是 | L12: =IF(K12="是",E12,0) -> 70 | M12: =IF(AND(G12="个人支出",J12="零税率"),E12,0) -> 0 | N12: =IF(AND(G12="个人支出",J12="免税"),E12,0) -> 0 | O12: =IF(AND(G12="个人支出",OR(J12="含税不明",J12="不适用")),E12,0) -> 0 | P12: =IF(K12<>"是",0,IF(税费设置!$B$6="是",E12/(1+税费设置!$B$10),E12)) -> 60.882801 | Q12: =IF(K12<>"是",0,P12*税费设置!$B$8) -> 3.04414 | R12: =IF(K12<>"是",0,P12*税费设置!$B$9) -> 6.0730594 | S12: =Q12+R12 -> 9.1171994
A13: =IF(总支出!A13="","",总支出!A13) -> 支出-0010 | B13: =IF(总支出!B13="","",总支出!B13) -> 46038 | C13: =IF(B13="","",TEXT(B13,"yyyy-mm")) -> 2026-01 | D13: =IF(总支出!C13="","",总支出!C13) -> 课程与书籍 | E13: =IF(总支出!D13="","",总支出!D13) -> 120 | F13: =IF(总支出!E13="","",总支出!E13) -> 学习 | G13: =IF(总支出!H13="","",总支出!H13) -> 个人支出 | H13: =IF(总支出!I13="","自动",总支出!I13) -> 含税不明 | I13: =IF(F13="","",IFERROR(VLOOKUP(F13,税费设置!$A$15:$B$27,2,FALSE),"含税不明")) -> 含税不明 | J13: =IF(D13="","",IF(H13="自动",I13,H13)) -> 含税不明 | K13: =IF(AND(税费设置!$B$5="是",G13="个人支出",J13="应税"),"是","否") -> 否 | L13: =IF(K13="是",E13,0) -> 0 | M13: =IF(AND(G13="个人支出",J13="零税率"),E13,0) -> 0 | N13: =IF(AND(G13="个人支出",J13="免税"),E13,0) -> 0 | O13: =IF(AND(G13="个人支出",OR(J13="含税不明",J13="不适用")),E13,0) -> 120 | P13: =IF(K13<>"是",0,IF(税费设置!$B$6="是",E13/(1+税费设置!$B$10),E13)) -> 0 | Q13: =IF(K13<>"是",0,P13*税费设置!$B$8) -> 0 | R13: =IF(K13<>"是",0,P13*税费设置!$B$9) -> 0 | S13: =Q13+R13 -> 0
A14: =IF(总支出!A14="","",总支出!A14) -> 支出-0011 | B14: =IF(总支出!B14="","",总支出!B14) -> 46040 | C14: =IF(B14="","",TEXT(B14,"yyyy-mm")) -> 2026-01 | D14: =IF(总支出!C14="","",总支出!C14) -> 宠物食品和用品 | E14: =IF(总支出!D14="","",总支出!D14) -> 90 | F14: =IF(总支出!E14="","",总支出!E14) -> 宠物 | G14: =IF(总支出!H14="","",总支出!H14) -> 个人支出 | H14: =IF(总支出!I14="","自动",总支出!I14) -> 应税 | I14: =IF(F14="","",IFERROR(VLOOKUP(F14,税费设置!$A$15:$B$27,2,FALSE),"含税不明")) -> 应税 | J14: =IF(D14="","",IF(H14="自动",I14,H14)) -> 应税 | K14: =IF(AND(税费设置!$B$5="是",G14="个人支出",J14="应税"),"是","否") -> 是 | L14: =IF(K14="是",E14,0) -> 90 | M14: =IF(AND(G14="个人支出",J14="零税率"),E14,0) -> 0 | N14: =IF(AND(G14="个人支出",J14="免税"),E14,0) -> 0 | O14: =IF(AND(G14="个人支出",OR(J14="含税不明",J14="不适用")),E14,0) -> 0 | P14: =IF(K14<>"是",0,IF(税费设置!$B$6="是",E14/(1+税费设置!$B$10),E14)) -> 78.277886 | Q14: =IF(K14<>"是",0,P14*税费设置!$B$8) -> 3.9138943 | R14: =IF(K14<>"是",0,P14*税费设置!$B$9) -> 7.8082192 | S14: =Q14+R14 -> 11.722114
A15: =IF(总支出!A15="","",总支出!A15) -> 支出-0012 | B15: =IF(总支出!B15="","",总支出!B15) -> 46042 | C15: =IF(B15="","",TEXT(B15,"yyyy-mm")) -> 2026-01 | D15: =IF(总支出!C15="","",总支出!C15) -> 电影和游戏娱乐 | E15: =IF(总支出!D15="","",总支出!D15) -> 100 | F15: =IF(总支出!E15="","",总支出!E15) -> 娱乐 | G15: =IF(总支出!H15="","",总支出!H15) -> 个人支出 | H15: =IF(总支出!I15="","自动",总支出!I15) -> 应税 | I15: =IF(F15="","",IFERROR(VLOOKUP(F15,税费设置!$A$15:$B$27,2,FALSE),"含税不明")) -> 应税 | J15: =IF(D15="","",IF(H15="自动",I15,H15)) -> 应税 | K15: =IF(AND(税费设置!$B$5="是",G15="个人支出",J15="应税"),"是","否") -> 是 | L15: =IF(K15="是",E15,0) -> 100 | M15: =IF(AND(G15="个人支出",J15="零税率"),E15,0) -> 0 | N15: =IF(AND(G15="个人支出",J15="免税"),E15,0) -> 0 | O15: =IF(AND(G15="个人支出",OR(J15="含税不明",J15="不适用")),E15,0) -> 0 | P15: =IF(K15<>"是",0,IF(税费设置!$B$6="是",E15/(1+税费设置!$B$10),E15)) -> 86.975429 | Q15: =IF(K15<>"是",0,P15*税费设置!$B$8) -> 4.3487715 | R15: =IF(K15<>"是",0,P15*税费设置!$B$9) -> 8.6757991 | S15: =Q15+R15 -> 13.024571
... A5000: =IF(总支出!A5000="","",总支出!A5000) | B5000: =IF(总支出!B5000="","",总支出!B5000) | C5000: =IF(B5000="","",TEXT(B5000,"yyyy-mm")) | D5000: =IF(总支出!C5000="","",总支出!C5000) | E5000: =IF(总支出!D5000="","",总支出!D5000) | F5000: =IF(总支出!E5000="","",总支出!E5000) | G5000: =IF(总支出!H5000="","",总支出!H5000) | H5000: =IF(总支出!I5000="","自动",总支出!I5000) -> 自动 | I5000: =IF(F5000="","",IFERROR(VLOOKUP(F5000,税费设置!$A$15:$B$27,2,FALSE),"含税不明")) | J5000: =IF(D5000="","",IF(H5000="自动",I5000,H5000)) | K5000: =IF(AND(税费设置!$B$5="是",G5000="个人支出",J5000="应税"),"是","否") -> 否 | L5000: =IF(K5000="是",E5000,0) -> 0 | M5000: =IF(AND(G5000="个人支出",J5000="零税率"),E5000,0) -> 0 | N5000: =IF(AND(G5000="个人支出",J5000="免税"),E5000,0) -> 0 | O5000: =IF(AND(G5000="个人支出",OR(J5000="含税不明",J5000="不适用")),E5000,0) -> 0 | P5000: =IF(K5000<>"是",0,IF(税费设置!$B$6="是",E5000/(1+税费设置!$B$10),E5000)) -> 0 | Q5000: =IF(K5000<>"是",0,P5000*税费设置!$B$8) -> 0 | R5000: =IF(K5000<>"是",0,P5000*税费设置!$B$9) -> 0 | S5000: =Q5000+R5000 -> 0

Sheet 年度消费预测
A1: 年度消费预测
A2: 展示页：Lean / Normal / Conservative 三种情景。
A3: 情景 | B3: 月支出基准 | C3: 年度基准 | D3: 说明
A4: =公式枢纽!A64 -> Lean 必要生活 | B4: =公式枢纽!B64 -> 4000 | C4: =公式枢纽!C64 -> 48000 | D4: =公式枢纽!D64 -> 只按必要支出估算最低生活底盘
A5: =公式枢纽!A65 -> Normal 当前生活 | B5: =公式枢纽!B65 -> 5150 | C5: =公式枢纽!C65 -> 61800 | D5: =公式枢纽!D65 -> 按当前平均个人支出估算
A6: =公式枢纽!A66 -> Conservative 保守 | B6: =公式枢纽!B66 -> 5300 | C6: =公式枢纽!C66 -> 63600 | D6: =公式枢纽!D66 -> 用最高月支出作为压力测试

Sheet 保障金分析
A1: 保障金分析
A2: 展示页：按必要生活、当前生活和保守压力测试测算备用金。
A3: 基准 | B3: 月支出 | C3: 3个月 | D3: 6个月 | E3: 12个月 | F3: 自定义月份
A4: 必要生活 | B4: =公式枢纽!$B$8 -> 4000 | C4: =B4*3 -> 12000 | D4: =B4*6 -> 24000 | E4: =B4*12 -> 48000 | F4: =B4*输入设置!$B$8 -> 48000
A5: 当前生活 | B5: =公式枢纽!$B$7 -> 5150 | C5: =B5*3 -> 15450 | D5: =B5*6 -> 30900 | E5: =B5*12 -> 61800 | F5: =B5*输入设置!$B$8 -> 61800
A6: 保守压力 | B6: =MAX(公式枢纽!$C$28:$C$39) -> 5300 | C6: =B6*3 -> 15900 | D6: =B6*6 -> 31800 | E6: =B6*12 -> 63600 | F6: =B6*输入设置!$B$8 -> 63600

Sheet 可投资资金
A1: 可投资资金
A2: 展示页：根据当前现金和推荐现金储备估算可投资资金。
A3: 项目 | B3: 数值 | C3: 说明
A4: 当前可动用现金 | B4: =输入设置!$B$5 -> 30000 | C4: 来自输入设置
A5: 推荐现金储备 | B5: =公式枢纽!$B$20 -> 62800 | C5: 按月均支出、备用金月数、最低储备和额外缓冲计算
A6: 建议可投资资金 | B6: =公式枢纽!$B$21 -> 0 | C6: 当前现金超过推荐储备的部分
A7: 现金缺口 | B7: =公式枢纽!$B$22 -> 32800 | C7: 若现金未达到推荐储备，则显示缺口
A8: 现金覆盖月数 | B8: =公式枢纽!$B$16 -> 5.8252427 | C8: 当前现金 / 平均每月个人支出
A9: 现金安全等级 | B9: =公式枢纽!$B$23 -> 偏紧张 | C9: 根据覆盖月数判断
A10: 资金配置提示 | B10: =IF(B5>0,"先补足现金储备，再考虑投资",IF(B4>0,"可考虑将超出储备的资金分批投入长期投资","请先在输入设置填入当前现金")) -> 先补足现金储备，再考虑投资 | C10: 规则提示，非投资建议

Sheet 公式说明
A1: 公式说明与维护规则
A2: 本页说明如何维护模板、每个页面的用途，以及关键公式逻辑。
A4: 页面 | B4: 单元格/区域 | C4: 公式 / 逻辑 | D4: 含义 | E4: 是否需要手动改 | F4: 备注
A5: 总支出 | B5: A:J | C5: 用户输入 | D5: 记录所有支出。支出金额填正数，日期决定月份。 | E5: 需要 | F5: 每月追加
A6: 总收入 | B6: A:F | C6: 用户输入 | D6: 记录所有收入。收入金额填正数，日期决定月份。 | E6: 需要 | F6: 每月追加
A7: 输入设置 | B7: B5:B9 | C7: 用户输入 | D7: 当前现金、缓冲、风险偏好、备用金月数、最低储备下限。 | E7: 需要 | F7: 现金变化时更新
A8: 税费设置 | B8: B5:B10 | C8: 用户输入 + 公式 | D8: 是否启用税费估算、是否含税价、地区与税率。 | E8: 可选 | F8: 税率可按所在省份调整
A9: 税费设置 | B9: A15:C27 | C9: 规则表 | D9: 当总支出税费类型为“自动”时，按主类别默认判断。 | E9: 可选 | F9: 可根据实际收据调整
A10: 税费计算明细 | B10: A:S | C10: 公式 | D10: 从总支出读取数据，计算最终税费类型、税前金额和估算税额。 | E10: 不用 | F10: 用户通常只查看
A11: 消费税分析 | B11: A:I | C11: SUMIFS | D11: 按月份汇总应税、零税率、免税和估算税额。 | E11: 不用 | F11: 受税费设置开关控制
A12: 公式枢纽 | B12: B4:B25 | C12: 核心公式 | D12: 统一计算总收入、个人支出、月均支出、现金储备和消费税。 | E12: 不用 | F12: 展示页统一引用本页
A13: 公式枢纽 | B13: A28:O39 | C13: SUMIFS + 日期区间 | D13: 根据日期自动统计2026-01到2026-12月度汇总。 | E13: 不用 | F13: 公式范围覆盖第4行到第5000行
A14: 公式枢纽 | B14: A44:P57 | C14: SUMIFS | D14: 按主类别和月份统计类别支出、月均、年化和占比。 | E14: 不用 | F14: 新增主类别时需同步扩展
A15: 每月总结 | B15: 整页 | C15: 引用公式枢纽 | D15: 展示月度收入、支出、现金流和估算税额。 | E15: 不用 | F15: 展示层
... A20: 总览 | B20: 整页 | C20: 引用公式枢纽 | D20: 主要查看页面，含KPI、判断摘要和图表。 | E20: 不用 | F20: 展示层
A24: 核心公式字典
A25: 公式 | B25: 作用 | C25: 在本模板中的用法
A26: SUMIFS | B26: 条件汇总 | C26: 按日期区间、分析口径、类别、支出性质等条件统计金额
A27: IF | B27: 规则判断 | C27: 判断是否启用税费估算、是否有数据、现金安全等级
A28: IFERROR | B28: 错误处理 | C28: 当除以0或查找不到时显示0或默认值
A29: VLOOKUP | B29: 查找默认税费类型 | C29: 根据主类别在税费设置中查找默认税费类型
A30: MAX | B30: 取较大值 | C30: 推荐现金储备和可投资资金计算
A31: DATE / LEFT / RIGHT | B31: 从月份文本生成日期区间 | C31: 公式枢纽用2026-01生成当月开始和下月开始日期

Sheet 选项
A1: 选项与下拉列表
A2: 此页用于数据验证，不建议手动修改。
A4: 主类别 | B4: 支出性质 | C4: 必要程度 | D4: 分析口径 | E4: 税费类型 | F4: 收入类型 | G4: 是否 | H4: 地区
A5: 住房 | B5: 固定 | C5: 必要 | D5: 个人支出 | E5: 自动 | F5: 工资 | G5: 是 | H5: 魁北克
A6: 餐饮 | B6: 可变 | C6: 弹性 | D6: 投资转账 | E6: 零税率 | F6: 奖学金 | G6: 否 | H6: 安大略
A7: 交通 | B7: 一次性 | D7: 内部转账 | E7: 应税 | F7: 政府补助 | H7: 不列颠哥伦比亚
A8: 通讯 | D8: 房产支出 | E8: 免税 | F8: 投资收益 | H8: 阿尔伯塔
A9: 订阅 | D9: 排除 | E9: 含税不明 | F9: 退款 | H9: 自定义
A10: 购物 | E10: 不适用 | F10: 房租收入
A11: 医疗 | F11: 其他
A12: 运动
A13: 学习
A14: 宠物
A15: 娱乐
A16: 税费
A17: 其他
